Workbook

Sheet Req Init 1.1
A1: Kellanova POC | B1: all fields we need are on pgs 23-30 of NIF Training Deck
A3: Sections | B3: fields | C3: field type | D3: rules | F3: drop down/list of values
F4: Country that owns new item being created | G4: data repeated | H4: data repeated | I4: NIF KEY abbreviation nomenclature
A5: Product Setup | F5: Product Country | G5: Form Type | H5: Product Type | I5: Product Sub Type | J5: Project Type
B6: Business Area | C6: drop down | D6: "Kellanova" | F6: US - United States | G6: Case | H6: Bulk Case | I6: BULK CS, NO PKG UPC | J6: KUBIC
B7: Form Type | C7: drop down | F7: CA - Canada | G7: Case | H7: Bulk Case | I7: BULK CS, PKG | J7: PDR
B8: Product Country | C8: drop down | F8: MX - Mexico | G8: Case | H8: Bulk Case | I8: BULK CS, PKG RPK/RCP | J8: PWR
B9: Product Type | C9: drop down | G9: Case | H9: Canada Bulk Case | I9: CA BULK CS, PKG | J9: SCR
B10: Product Sub Type | C10: drop down | G10: Case | H10: Canada Bulk Case | I10: CA BULK CS, NO PKG UPC
B11: Is this a Pringle product? | C11: drop down | D11: yes/no | G11: Case | H11: Canada Club | I11: CA CLUB, TRADITIONAL
B12: Is this an RX product? | C12: drop down | D12: yes/no | G12: Case | H12: Canada Club | I12: CA CLUB, UL
B13: SAP Material Number | C13: not enterable | G13: Case | H13: Canada Straight Case | I13: CA CS, PKG
B14: Project Type | C14: drop down | G14: Case | H14: Canada Straight Case | I14: CA CS, PKG & PCH/INNER
B15: Project Name or Number | C15: free form | G15: Case | H15: Canada Straight Case Repack/RCP - existing PKG UPC | I15: CA CS, PKG RPK/RCP
B16: Set Category | C16: not enterable | D16: maybe filled in by Material Prefix answer (further down) | G16: Case | H16: Canada Straight Case Repack/RCP - existing PKG UPC | I16: CA CS, PKG & PCH/INNER RPK/RCP
B17: Brief Product Description | C17: free form | G17: Case | H17: Canada Straight Case Repack/RCP - new PKG UPC | I17: CA CS, PKG RPK/RCP
B18: Brief Project Overview | C18: free form | G18: Case | H18: Canada Straight Case Repack/RCP - new PKG UPC | I18: CA CS, PKG & PCH/INNER RPK/RCP
G19: Case | H19: Canada WIP Case | I19: CA WIP, CASE (HALB)
G20: Case | H20: Canada WIP Tote | I20: CA WIP, TOTE (HALB)
G21: Case | H21: Club | I21: CLUB, NON-TRADITIONAL
G22: Case | H22: Club | I22: CLUB, TRADITIONAL
G23: Case | H23: Club Repack/RCP | I23: CLUB, NON-TRADITIONAL RPK/RCP
G24: Case | H24: Club Repack/RCP | I24: CLUB, TRADITIONAL RPK/RCP
G25: Case | H25: DTC Bundle | I25: DTC
G26: Case | H26: EComm | I26: ECOMM CASE
G27: Case | H27: EComm | I27: ECOMM PACKAGE
G28: Display | H28: Full Mod | I28: DISPLAY, FULL MOD
G29: Display | H29: Half Mod | I29: DISPLAY, HALF MOD
G30: Display | H30: Qtr Mod | I30: DISPLAY, QTR MOD
... G39: WIP | H39: WIP Tote | I39: WIP, TOTE (HALB)
A44: Stated Weights/Case Count
B45: Stated Weight Applicable For | C45: drop down | F45: Stated Weight Applicable For | G45: Stated Weight Status | H45: Stated Net Weight UOM | I45: Case Count Status
B46: Stated Weight Status | C46: drop down | F46: Package | G46: Estimated | H46: OZ | I46: Estimated
B47: Stated Net Weight | C47: number | F47: Inner Item/Pouch | G47: Finalized | H47: G | I47: Finalized
B48: Stated Net Weight UOM | C48: drop down
B49: Case Count Status | C49: drop down
B50: Case Count | C50: number
A53: Reference Material
B54: Like SKU / Reference Material Number | C54: drop down | D54: references SAP db
A56: Product Determination Questions - Case | F56: Designated Customer Name
B57: Approved to sell via Ecommerce? | C57: drop down | D57: yes/no | F57: BASKIN ROBINS
B58: Is product designated to one customer? | C58: drop down | D58: yes/no | F58: DEMOULAS
B59: Designated Customer Name | C59: drop down | F59: KROGER
B60: Include Designated Cust. In Material Desc? | C60: drop down | D60: yes/no | F60: SODEXHO
B61: Variety Pack? | C61: drop down | D61: yes/no | F61: WAL-MART
B62: Variety Pack components have UPC Codes? | C62: drop down | D62: yes/no
B63: Build SKU Using Existing Package UPCs? | C63: drop down | D63: yes/no
B64: Is this item owned by Away From Home? | C64: drop down | D64: yes/no
B65: Is this an Export Product? | C65: drop down | D65: yes/no
B66: Build SKU Using Existing Package UPCs? | C66: drop down | D66: yes/no
B67: List Existing Export UPC Codes | C67: freeform
B68: Private Label? | C68: drop down | D68: yes/no
B69: Private Label Name | C69: freeform
B70: Build SKU Using Existing Private UPCs? | C70: drop down | D70: yes/no
B71: List Existing Private UPCs | C71: freeform
B72: Data Sync(GDSN)? | C72: drop down | D72: yes/no
A76: Product Determination Questions - Display | F76: Designated Customer Name
B77: Approved to sell via Ecommerce? | C77: drop down | D77: yes/no | F77: BASKIN ROBINS
B78: Is product designated to one customer? | C78: drop down | D78: yes/no | F78: DEMOULAS
B79: Designated Customer Name | C79: drop down | F79: KROGER
B80: Include Designated Cust. In Material Desc? | C80: drop down | D80: yes/no | F80: SODEXHO
B81: Build SKU Using Existing Package UPCs? | C81: drop down | D81: yes/no | F81: WAL-MART
B82: Is this item owned by Away From Home? | C82: drop down | D82: yes/no
B83: Is this an Export Product? | C83: drop down | D83: yes/no
B84: Data Sync(GDSN)? | C84: drop down | D84: yes/no
A87: Product Determination Questions - WIP
B88: Build SKU Using Existing Package UPCs? | C88: not enterable
B89: Is this item owned by Away From Home? | C89: drop down | D89: yes/no
B90: Is this an Export Product? | C90: drop down | D90: yes/no
B91: Build SKU Using Existing Package UPCs? | C91: drop down | D91: yes/no
B92: List Existing Export UPC Codes | C92: freeform
B93: Private Label? | C93: drop down | D93: yes/no
B94: Private Label Name | C94: freeform
B95: Build SKU Using Existing Private UPCs? | C95: drop down | D95: yes/no
B96: List Existing Private UPCs | C96: freeform
B97: Data Sync(GDSN)? | C97: drop down | D97: yes/no
A101: Other UPC Requirements | F101: Material Prefix | G101: Is a Compressed UPC Required for the Components?
B102: Material Prefix | C102: drop down | F102: Kellogg PT (38000) | G102: No
B103: Is a Compressed UPC Required for the Components? | C103: drop down | D103: yes/no | F103: Kellogg RKTBars (38000) | G103: Pouch
F104: Kellogg TownHouse (30100) | G104: Package
F105: Morningstar Farms (28989) | G105: Both
A111: Existing Printed Material Codes | F111: Compressed UPC Existing
B112: Package UPC Code | C112: freeform | F112: No
B113: Package K Number | C113: freeform | F113: Pouch
B114: Pouch UPC Code | C114: freeform | F114: Package
B115: Pouch K Number | C115: freeform | F115: Both
B116: List UPC Codes If Already Assigned | C116: freeform
B117: Compressed UPC Existing | C117: drop down
A119: UPC Table | B119: The rows in this table are filled in automatically based on the Setup Type chosen
B120: Alt UOM | C120: not enterable
B121: Base UOM | C121: not enterable
B122: UPC Required? | C122: not enterable
B123: Unique UPC? | C123: not enterable
A125: List Existing K Numbers
B126: List Any Existing Knumbers That Will Be Used | C126: freeform
A128: Special Packaging Requirements | F128: Additional Packaging for Launch
B129: Additional Packaging for Launch | C129: drop down | F129: Can
B130: Special Launch Number | C130: freeform | F130: Tray
F131: Jar

Sheet All sections of NIF PDF
A1: Review of NIF Training Deck - Bev Tyler | G1: dd = drop downs | K1: BR.xlsx file = https://demandchainai.sharepoint.com/:x:/s/KellanovaPOC/Ebpe4JJnLcJDsKN74E_FN2oBGy3SMnB3ieLdjMvL_nwzIge=VenuuF | V1: Complexity: | W1: 3 | X1: 2 | Y1: 1 | Z1: 0
G2: PRL=PRODUCT_REFERENCE_LIST.XLSX | K2: Trng_deck.ppt = https://demandchainai.sharepoint.com/:b:/s/KellanovaPOC/EUbYiN0y3vRHupu27Q5q6Q8BBsRldO5V1fX6na9le0eAuAe=crBJEK | V2: Hours: | W2: 1.5 | X2: 1 | Y2: 0.5 | Z2: 0
A3: UNIQUE FIELD # (order in Trng deck) | B3: Training Section | C3: section name | D3: field names in Trng deck | E3: #fields enterable in Trng deck | F3: page(s) of Trng deck | G3: types of fields | H3: required | I3: owner | J3: additional roles who can modify | K3: column referenced in BR.xlsx file (from Tamara) | L3: comments | M3: Business Rules (technical) | N3: Business Rules (AI ready) | O3: Business Rule status | P3: Timing status | Q3: Trng Sectn # | R3: Trng Sectn Priority | S3: Week | T3: Week Beginning Date | U3: PRIORITY (1..9) 1-highest 5-mid 9-lowest | V3: COMPLEXITY (3..1,0) 3-high 2-med 1-low 0-autofill | W3: Hours | X3: Sprint | Y3: Date: Field Last Reviewed for Business Rules | Z3: Date: Expert System Rules updated (Excel) | AA3: Date: Handed off to AI BOT team (Justin)
A4: 1001 | B4: Requestor - Project Initiation | C4: Requestor Initiate | D4: Requestor Name | E4: 0 | F4: 23 | G4: autofill | H4: yes | I4: Requestor | M4: pull name from user logged in | O4: done | P4: complete | Q4: =VLOOKUP(B4,LOV!$B:$C,2,FALSE) -> 10 | R4: =VLOOKUP(B4,LOV!$B:$D,3,FALSE) -> AA | S4: =VLOOKUP($X4,LOV!$F:$L,2,FALSE) -> WK2 | T4: =VLOOKUP($X4,LOV!$F:$L,7,FALSE) -> 45922 | U4: 9 | V4: 0 | W4: =IF(ISNUMBER(V4),HLOOKUP(V4,$V$1:$AA$2,2,FALSE)*E4,"") -> 0 | X4: E | Y4: 45923 | Z4: 45925 | AA4: 45929
A5: 1002 | B5: Requestor - Project Initiation | C5: Requestor Initiate | D5: Requestor Email | E5: 0 | F5: 23 | G5: autofill | H5: yes | I5: Requestor | M5: pull email from user logged in | O5: done | P5: complete | Q5: =VLOOKUP(B5,LOV!$B:$C,2,FALSE) -> 10 | R5: =VLOOKUP(B5,LOV!$B:$D,3,FALSE) -> AA | S5: =VLOOKUP($X5,LOV!$F:$L,2,FALSE) -> WK2 | T5: =VLOOKUP($X5,LOV!$F:$L,7,FALSE) -> 45922 | U5: 9 | V5: 0 | W5: =IF(ISNUMBER(V5),HLOOKUP(V5,$V$1:$AA$2,2,FALSE)*E5,"") -> 0 | X5: E | Y5: 45923 | Z5: 45925 | AA5: 45929
A6: 1003 | B6: Requestor - Project Initiation | C6: Requestor Initiate | D6: Requestor Date | E6: 0 | F6: 23 | G6: autofill | H6: yes | I6: Requestor | M6: pull date from computer | O6: done | P6: complete | Q6: =VLOOKUP(B6,LOV!$B:$C,2,FALSE) -> 10 | R6: =VLOOKUP(B6,LOV!$B:$D,3,FALSE) -> AA | S6: =VLOOKUP($X6,LOV!$F:$L,2,FALSE) -> WK2 | T6: =VLOOKUP($X6,LOV!$F:$L,7,FALSE) -> 45922 | U6: 9 | V6: 0 | W6: =IF(ISNUMBER(V6),HLOOKUP(V6,$V$1:$AA$2,2,FALSE)*E6,"") -> 0 | X6: E | Y6: 45923 | Z6: 45925 | AA6: 45929
A7: 1004 | B7: Requestor - Project Initiation | C7: Requestor Initiate | D7: Version | E7: 0 | F7: 23 | G7: autofill | H7: yes | I7: Requestor | M7: pull NIF version of the form | O7: done | P7: complete | Q7: =VLOOKUP(B7,LOV!$B:$C,2,FALSE) -> 10 | R7: =VLOOKUP(B7,LOV!$B:$D,3,FALSE) -> AA | S7: =VLOOKUP($X7,LOV!$F:$L,2,FALSE) -> WK2 | T7: =VLOOKUP($X7,LOV!$F:$L,7,FALSE) -> 45922 | U7: 9 | V7: 0 | W7: =IF(ISNUMBER(V7),HLOOKUP(V7,$V$1:$AA$2,2,FALSE)*E7,"") -> 0 | X7: E | Y7: 45923 | Z7: 45925 | AA7: 45929
A8: 1005 | B8: Requestor - Project Initiation | C8: Person Responsible | D8: Requestor | E8: 0 | F8: 23 | G8: dd: user roles | H8: yes | I8: Requestor | M8: pull name from user logged in | O8: done | P8: complete | Q8: =VLOOKUP(B8,LOV!$B:$C,2,FALSE) -> 10 | R8: =VLOOKUP(B8,LOV!$B:$D,3,FALSE) -> AA | S8: =VLOOKUP($X8,LOV!$F:$L,2,FALSE) -> WK2 | T8: =VLOOKUP($X8,LOV!$F:$L,7,FALSE) -> 45922 | U8: 9 | V8: 0 | W8: =IF(ISNUMBER(V8),HLOOKUP(V8,$V$1:$AA$2,2,FALSE)*E8,"") -> 0 | X8: E | Y8: 45923 | Z8: 45925 | AA8: 45929
A9: 1006 | B9: Requestor - Project Initiation | C9: Person Responsible | D9: LIM | E9: 1 | F9: 23, 32, 61 | G9: dd: reference list: PRL: LIM_Users | H9: yes | I9: Requestor | J9: LIM | M9: no Business Rules | O9: done | P9: complete | Q9: =VLOOKUP(B9,LOV!$B:$C,2,FALSE) -> 10 | R9: =VLOOKUP(B9,LOV!$B:$D,3,FALSE) -> AA | S9: =VLOOKUP($X9,LOV!$F:$L,2,FALSE) -> WK2 | T9: =VLOOKUP($X9,LOV!$F:$L,7,FALSE) -> 45922 | U9: 4 | V9: 1 | W9: =IF(ISNUMBER(V9),HLOOKUP(V9,$V$1:$AA$2,2,FALSE)*E9,"") -> 0.5 | X9: D | Y9: 45923 | Z9: 45925 | AA9: 45929
A10: 1305 | B10: Requestor - Project Initiation | C10: Product Setup | D10: Business Area | E10: 0 | F10: 0 | G10: dd: WKKC, KELLANOVA | H10: yes | I10: Requestor | L10: 9/24/25 new field identified | M10: autofill to KELLANOVA | O10: done | P10: complete | Q10: =VLOOKUP(B10,LOV!$B:$C,2,FALSE) -> 10 | R10: =VLOOKUP(B10,LOV!$B:$D,3,FALSE) -> AA | S10: =VLOOKUP($X10,LOV!$F:$L,2,FALSE) -> WK2 | T10: =VLOOKUP($X10,LOV!$F:$L,7,FALSE) -> 45922 | V10: 1 | W10: =IF(ISNUMBER(V10),HLOOKUP(V10,$V$1:$AA$2,2,FALSE)*E10,"") -> 0 | X10: E | Y10: 45924 | Z10: 45925 | AA10: 45929
A11: 1007 | B11: Requestor - Project Initiation | C11: Product Setup | D11: Form Type | E11: 1 | F11: 24 | G11: dd: CASE, DISPLAY, WIP | H11: yes | I11: Requestor | K11: col A | M11: Flowchart: Product Type / Product Sub Type | N11: Reliant on Product Country | O11: done | P11: complete | Q11: =VLOOKUP(B11,LOV!$B:$C,2,FALSE) -> 10 | R11: =VLOOKUP(B11,LOV!$B:$D,3,FALSE) -> AA | S11: =VLOOKUP($X11,LOV!$F:$L,2,FALSE) -> WK1 | T11: =VLOOKUP($X11,LOV!$F:$L,7,FALSE) -> 45916 | U11: 1 | V11: 3 | W11: =IF(ISNUMBER(V11),HLOOKUP(V11,$V$1:$AA$2,2,FALSE)*E11,"") -> 1.5 | X11: A | Y11: 45918 | Z11: 45921 | AA11: 45922
A12: 1008 | B12: Requestor - Project Initiation | C12: Product Setup | D12: Product Country | E12: 1 | F12: 24 | G12: dd: reference list: PRODUCT_COUNTRY.XLSX | H12: yes | I12: Requestor | K12: NOT in BR.xlsx | M12: Flowchart: Product Type / Product Sub Type | O12: done | P12: complete | Q12: =VLOOKUP(B12,LOV!$B:$C,2,FALSE) -> 10 | R12: =VLOOKUP(B12,LOV!$B:$D,3,FALSE) -> AA | S12: =VLOOKUP($X12,LOV!$F:$L,2,FALSE) -> WK1 | T12: =VLOOKUP($X12,LOV!$F:$L,7,FALSE) -> 45916 | U12: 1 | V12: 3 | W12: =IF(ISNUMBER(V12),HLOOKUP(V12,$V$1:$AA$2,2,FALSE)*E12,"") -> 1.5 | X12: A | Y12: 45918 | Z12: 45921 | AA12: 45922
A13: 1009 | B13: Requestor - Project Initiation | C13: Product Setup | D13: Product Type | E13: 1 | F13: 24 | G13: dd: reference list: PRODUCT_SETUP_TYPE.XLSX, Setup_Type column | H13: yes | I13: Requestor | K13: col B | L13: dependent on FORM TYPE | M13: Flowchart: Product Type / Product Sub Type | N13: Reliant on Product Country / Form Type | O13: done | P13: complete | Q13: =VLOOKUP(B13,LOV!$B:$C,2,FALSE) -> 10 | R13: =VLOOKUP(B13,LOV!$B:$D,3,FALSE) -> AA | S13: =VLOOKUP($X13,LOV!$F:$L,2,FALSE) -> WK1 | T13: =VLOOKUP($X13,LOV!$F:$L,7,FALSE) -> 45916 | U13: 1 | V13: 3 | W13: =IF(ISNUMBER(V13),HLOOKUP(V13,$V$1:$AA$2,2,FALSE)*E13,"") -> 1.5 | X13: A | Y13: 45924 | Z13: 45924 | AA13: 45929
A14: 1010 | B14: Requestor - Project Initiation | C14: Product Setup | D14: Product Sub Type | E14: 1 | F14: 24 | G14: dd: reference list: PRODUCT_SETUP_TYPE.XLSX, Setup_Qualifier column | H14: yes | I14: Requestor | K14: col C | L14: dependent on PRODUCT TYPE | M14: Flowchart: Product Type / Product Sub Type | N14: Reliant on Product Country / Form Type / Product Type | O14: done | P14: complete | Q14: =VLOOKUP(B14,LOV!$B:$C,2,FALSE) -> 10 | R14: =VLOOKUP(B14,LOV!$B:$D,3,FALSE) -> AA | S14: =VLOOKUP($X14,LOV!$F:$L,2,FALSE) -> WK1 | T14: =VLOOKUP($X14,LOV!$F:$L,7,FALSE) -> 45916 | U14: 1 | V14: 3 | W14: =IF(ISNUMBER(V14),HLOOKUP(V14,$V$1:$AA$2,2,FALSE)*E14,"") -> 1.5 | X14: A | Y14: 45918 | Z14: 45921 | AA14: 45922
A15: 1011 | B15: Requestor - Project Initiation | C15: Product Setup | D15: Is this a Pringles product | E15: 1 | F15: 24 | G15: dd: YES, NO | H15: yes | I15: Requestor | K15: NOT in BR.xlsx | M15: 1011 predecessor for pringles naming convention for country sold in as part of description (1175); plus Pringles Can Size (1235), and RTEC/Pringles Cube Size (1239) is required | O15: done | P15: complete | Q15: =VLOOKUP(B15,LOV!$B:$C,2,FALSE) -> 10 | R15: =VLOOKUP(B15,LOV!$B:$D,3,FALSE) -> AA | S15: =VLOOKUP($X15,LOV!$F:$L,2,FALSE) -> WK1 | T15: =VLOOKUP($X15,LOV!$F:$L,7,FALSE) -> 45916 | U15: 1 | V15: 1 | W15: =IF(ISNUMBER(V15),HLOOKUP(V15,$V$1:$AA$2,2,FALSE)*E15,"") -> 0.5 | X15: A | Y15: 45919 | Z15: 45923 | AA15: 45923
A16: 1012 | B16: Requestor - Project Initiation | C16: Product Setup | D16: Is this an RX Product | E16: 1 | F16: 24 | G16: dd: YES, NO | H16: yes | I16: Requestor | K16: NOT in BR.xlsx | M16: 1012 predecessor to: "Will product be sold DTC question" (1162), this will also kick off the DTC form at end of process; Dependencies 1292, 1301, 1302 | O16: done | P16: complete | Q16: =VLOOKUP(B16,LOV!$B:$C,2,FALSE) -> 10 | R16: =VLOOKUP(B16,LOV!$B:$D,3,FALSE) -> AA | S16: =VLOOKUP($X16,LOV!$F:$L,2,FALSE) -> WK1 | T16: =VLOOKUP($X16,LOV!$F:$L,7,FALSE) -> 45916 | U16: 1 | V16: 1 | W16: =IF(ISNUMBER(V16),HLOOKUP(V16,$V$1:$AA$2,2,FALSE)*E16,"") -> 0.5 | X16: A | Y16: 45919 | Z16: 45923 | AA16: 45923
A17: 1013 | B17: Requestor - Project Initiation | C17: Product Setup | D17: SAP Material Number | E17: 0 | F17: 24, 45 | G17: free form | H17: no | I17: Masterfiles | L17: same as field 1070 | M17: duplicate of 1070 | N17: (same as Material Number) | O17: done | P17: complete | Q17: =VLOOKUP(B17,LOV!$B:$C,2,FALSE) -> 10 | R17: =VLOOKUP(B17,LOV!$B:$D,3,FALSE) -> AA | S17: =VLOOKUP($X17,LOV!$F:$L,2,FALSE) -> WK1 | T17: =VLOOKUP($X17,LOV!$F:$L,7,FALSE) -> 45916 | U17: 1 | V17: 1 | W17: =IF(ISNUMBER(V17),HLOOKUP(V17,$V$1:$AA$2,2,FALSE)*E17,"") -> 0 | X17: B | Y17: 45919 | Z17: 45919 | AA17: 45919
A18: 1014 | B18: Requestor - Project Initiation | C18: Product Setup | D18: Project Type | E18: 1 | F18: 24 | G18: dd: KUBIC, PDR, PWR, SCR | H18: yes | I18: Requestor | K18: col E | M18: 1014: predecessor for: 1015, 1025 | O18: done | P18: complete | Q18: =VLOOKUP(B18,LOV!$B:$C,2,FALSE) -> 10 | R18: =VLOOKUP(B18,LOV!$B:$D,3,FALSE) -> AA | S18: =VLOOKUP($X18,LOV!$F:$L,2,FALSE) -> WK1 | T18: =VLOOKUP($X18,LOV!$F:$L,7,FALSE) -> 45916 | U18: 1 | V18: 2 | W18: =IF(ISNUMBER(V18),HLOOKUP(V18,$V$1:$AA$2,2,FALSE)*E18,"") -> 1 | X18: A | Y18: 45919 | Z18: 45922 | AA18: 45922
A19: 1015 | B19: Requestor - Project Initiation | C19: Product Setup | D19: Project Name or Number | E19: 1 | F19: 24 | G19: free form | H19: yes | I19: Requestor | K19: col G | M19: 1015: dependent on 1014 PROJECT TYPE: PDR and SCR is text (ex Tasty) PWR is numeric | O19: done | P19: complete | Q19: =VLOOKUP(B19,LOV!$B:$C,2,FALSE) -> 10 | R19: =VLOOKUP(B19,LOV!$B:$D,3,FALSE) -> AA | S19: =VLOOKUP($X19,LOV!$F:$L,2,FALSE) -> WK1 | T19: =VLOOKUP($X19,LOV!$F:$L,7,FALSE) -> 45916 | U19: 1 | V19: 1 | W19: =IF(ISNUMBER(V19),HLOOKUP(V19,$V$1:$AA$2,2,FALSE)*E19,"") -> 0.5 | X19: A | Y19: 45919 | Z19: 45922 | AA19: 45922
A20: 1016 | B20: Requestor - Project Initiation | C20: Product Setup | D20: Set Category | E20: 1 | F20: 0 | G20: dd: reference list: RDL_Categories.xlsx | H20: yes | I20: Requestor | K20: col I | L20: …not in Trng_deck.ppt; Bars, Crackers, Other Convenience, Salty Snacks, Frozen, Toaster Pastries, Veggies | M20: no known BR based on data entered | O20: done | P20: complete | Q20: =VLOOKUP(B20,LOV!$B:$C,2,FALSE) -> 10 | R20: =VLOOKUP(B20,LOV!$B:$D,3,FALSE) -> AA | S20: =VLOOKUP($X20,LOV!$F:$L,2,FALSE) -> WK1 | T20: =VLOOKUP($X20,LOV!$F:$L,7,FALSE) -> 45916 | U20: 1 | V20: 1 | W20: =IF(ISNUMBER(V20),HLOOKUP(V20,$V$1:$AA$2,2,FALSE)*E20,"") -> 0.5 | X20: A | Y20: 45919 | Z20: 45922 | AA20: 45922
A21: 1017 | B21: Requestor - Project Initiation | C21: Product Setup | D21: Brief Product Description | E21: 1 | F21: 24, 33, 73 | G21: free form | H21: yes | I21: Requestor | J21: LIM | K21: col K | L21: used for naming NIF form, but do not incorporate into AI | M21: no more than 40 characters | O21: done | P21: complete | Q21: =VLOOKUP(B21,LOV!$B:$C,2,FALSE) -> 10 | R21: =VLOOKUP(B21,LOV!$B:$D,3,FALSE) -> AA | S21: =VLOOKUP($X21,LOV!$F:$L,2,FALSE) -> WK1 | T21: =VLOOKUP($X21,LOV!$F:$L,7,FALSE) -> 45916 | U21: 1 | V21: 2 | W21: =IF(ISNUMBER(V21),HLOOKUP(V21,$V$1:$AA$2,2,FALSE)*E21,"") -> 1 | X21: B | Y21: 45919 | Z21: 45922 | AA21: 45922
A22: 1018 | B22: Requestor - Project Initiation | C22: Product Setup | D22: Brief Project Overview and Technical Notes | E22: 1 | F22: 24, 33, 73 | G22: free form | H22: yes | I22: Requestor | J22: LIM | K22: col M | L22: Be as detailed as possible and provide the flavor, package size and can size, if known | M22: no known BR based on data entered | O22: done | P22: complete | Q22: =VLOOKUP(B22,LOV!$B:$C,2,FALSE) -> 10 | R22: =VLOOKUP(B22,LOV!$B:$D,3,FALSE) -> AA | S22: =VLOOKUP($X22,LOV!$F:$L,2,FALSE) -> WK1 | T22: =VLOOKUP($X22,LOV!$F:$L,7,FALSE) -> 45916 | U22: 1 | V22: 2 | W22: =IF(ISNUMBER(V22),HLOOKUP(V22,$V$1:$AA$2,2,FALSE)*E22,"") -> 1 | X22: B | Y22: 45919 | Z22: 45922 | AA22: 45922
A23: 1019 | B23: Requestor - Project Initiation | C23: Stated Weights/Case Count | D23: Stated Weight Applicable For | E23: 1 | F23: 24, 33, 73 | G23: dd: PACKAGE, INNER ITEM/POUCH | H23: yes | I23: Requestor | J23: LIM | K23: col O | L23: informational only | M23: no known BR based on data entered | O23: done | P23: complete | Q23: =VLOOKUP(B23,LOV!$B:$C,2,FALSE) -> 10 | R23: =VLOOKUP(B23,LOV!$B:$D,3,FALSE) -> AA | S23: =VLOOKUP($X23,LOV!$F:$L,2,FALSE) -> WK1 | T23: =VLOOKUP($X23,LOV!$F:$L,7,FALSE) -> 45916 | U23: 2 | V23: 2 | W23: =IF(ISNUMBER(V23),HLOOKUP(V23,$V$1:$AA$2,2,FALSE)*E23,"") -> 1 | X23: B | Y23: 45919 | Z23: 45923 | AA23: 45929
A24: 1020 | B24: Requestor - Project Initiation | C24: Stated Weights/Case Count | D24: Stated Weight Status | E24: 1 | F24: 24, 33, 73 | G24: dd: ESTIMATED, FINALIZED | H24: yes | I24: Requestor | J24: LIM | K24: col Q | L24: informational only | M24: no known BR based on data entered | O24: done | P24: complete | Q24: =VLOOKUP(B24,LOV!$B:$C,2,FALSE) -> 10 | R24: =VLOOKUP(B24,LOV!$B:$D,3,FALSE) -> AA | S24: =VLOOKUP($X24,LOV!$F:$L,2,FALSE) -> WK1 | T24: =VLOOKUP($X24,LOV!$F:$L,7,FALSE) -> 45916 | U24: 2 | V24: 2 | W24: =IF(ISNUMBER(V24),HLOOKUP(V24,$V$1:$AA$2,2,FALSE)*E24,"") -> 1 | X24: B | Y24: 45919 | Z24: 45923 | AA24: 45929
A25: 1021 | B25: Requestor - Project Initiation | C25: Stated Weights/Case Count | D25: Stated Net Weight | E25: 1 | F25: 24, 33, 73, 99 | G25: free form | H25: yes | I25: Requestor | J25: LIM, Packaging Tech | K25: col S | L25: informational only | M25: no known BR based on data entered | O25: done | P25: complete | Q25: =VLOOKUP(B25,LOV!$B:$C,2,FALSE) -> 10 | R25: =VLOOKUP(B25,LOV!$B:$D,3,FALSE) -> AA | S25: =VLOOKUP($X25,LOV!$F:$L,2,FALSE) -> WK1 | T25: =VLOOKUP($X25,LOV!$F:$L,7,FALSE) -> 45916 | U25: 2 | V25: 1 | W25: =IF(ISNUMBER(V25),HLOOKUP(V25,$V$1:$AA$2,2,FALSE)*E25,"") -> 0.5 | X25: B | Y25: 45919 | Z25: 45923 | AA25: 45929
A26: 1022 | B26: Requestor - Project Initiation | C26: Stated Weights/Case Count | D26: Stated Net Weight UOM | E26: 1 | F26: 24, 33, 73 | G26: dd: OZ, LB, G, KG | H26: yes | I26: Requestor | J26: LIM | K26: col U | L26: informational only | M26: no known BR based on data entered | O26: done | P26: complete | Q26: =VLOOKUP(B26,LOV!$B:$C,2,FALSE) -> 10 | R26: =VLOOKUP(B26,LOV!$B:$D,3,FALSE) -> AA | S26: =VLOOKUP($X26,LOV!$F:$L,2,FALSE) -> WK1 | T26: =VLOOKUP($X26,LOV!$F:$L,7,FALSE) -> 45916 | U26: 2 | V26: 1 | W26: =IF(ISNUMBER(V26),HLOOKUP(V26,$V$1:$AA$2,2,FALSE)*E26,"") -> 0.5 | X26: B | Y26: 45919 | Z26: 45923 | AA26: 45929
A27: 1023 | B27: Requestor - Project Initiation | C27: Stated Weights/Case Count | D27: Case Count Status | E27: 1 | F27: 24, 33, 73 | G27: dd: ESTIMATED, FINALIZED | H27: yes | I27: Requestor | J27: LIM | K27: col W | L27: informational only | M27: no known BR based on data entered | O27: done | P27: complete | Q27: =VLOOKUP(B27,LOV!$B:$C,2,FALSE) -> 10 | R27: =VLOOKUP(B27,LOV!$B:$D,3,FALSE) -> AA | S27: =VLOOKUP($X27,LOV!$F:$L,2,FALSE) -> WK1 | T27: =VLOOKUP($X27,LOV!$F:$L,7,FALSE) -> 45916 | U27: 2 | V27: 2 | W27: =IF(ISNUMBER(V27),HLOOKUP(V27,$V$1:$AA$2,2,FALSE)*E27,"") -> 1 | X27: B | Y27: 45919 | Z27: 45923 | AA27: 45929
A28: 1024 | B28: Requestor - Project Initiation | C28: Stated Weights/Case Count | D28: Case Count | E28: 1 | F28: 24, 33, 73 | G28: free form | H28: yes | I28: Requestor | J28: LIM | K28: col Y | L28: informational only | M28: no known BR based on data entered | O28: done | P28: complete | Q28: =VLOOKUP(B28,LOV!$B:$C,2,FALSE) -> 10 | R28: =VLOOKUP(B28,LOV!$B:$D,3,FALSE) -> AA | S28: =VLOOKUP($X28,LOV!$F:$L,2,FALSE) -> WK1 | T28: =VLOOKUP($X28,LOV!$F:$L,7,FALSE) -> 45916 | U28: 2 | V28: 3 | W28: =IF(ISNUMBER(V28),HLOOKUP(V28,$V$1:$AA$2,2,FALSE)*E28,"") -> 1.5 | X28: B | Y28: 45919 | Z28: 45923 | AA28: 45929
A29: 1025 | B29: Requestor - Project Initiation | C29: Reference Material | D29: Like SKU / Reference Material Number | E29: 1 | F29: 25 | G29: SAP db list | H29: conditional | I29: Requestor | K29: NOT in BR.xlsx | L29: functionality of the SAP db is not needed in AI tool | M29: 1025: dependent on 1014 PROJECT TYPE: KUBIC (required) | O29: done | P29: complete | Q29: =VLOOKUP(B29,LOV!$B:$C,2,FALSE) -> 10 | R29: =VLOOKUP(B29,LOV!$B:$D,3,FALSE) -> AA | S29: =VLOOKUP($X29,LOV!$F:$L,2,FALSE) -> WK1 | T29: =VLOOKUP($X29,LOV!$F:$L,7,FALSE) -> 45916 | U29: 3 | V29: 3 | W29: =IF(ISNUMBER(V29),HLOOKUP(V29,$V$1:$AA$2,2,FALSE)*E29,"") -> 1.5 | X29: B | Y29: 45919 | Z29: 45923 | AA29: 45929
A30: 1026 | B30: Requestor - Project Initiation | C30: Product Determination Questions | D30: Approved to sell via Ecommerce | E30: 1 | F30: 25, 26 | G30: dd: YES, NO | H30: yes | I30: Requestor | K30: col Z | L30: CASE and DISPLAY only; If YES, then loads record: TRADE CHANNEL (1166)=ONLINE | M30: 1026 dependent PRODUCT TYPE (1009)=ECOMM or DTC BUNDLE, then this is defaulted to YES (locks field); If Product Country (1008) CANADA then default to NO; Form Type (1007) DISPLAY=open but not required, CASE=required, WIP=not available | O30: done | P30: complete | Q30: =VLOOKUP(B30,LOV!$B:$C,2,FALSE) -> 10 | R30: =VLOOKUP(B30,LOV!$B:$D,3,FALSE) -> AA | S30: =VLOOKUP($X30,LOV!$F:$L,2,FALSE) -> WK1 | T30: =VLOOKUP($X30,LOV!$F:$L,7,FALSE) -> 45916 | U30: 3 | V30: 1 | W30: =IF(ISNUMBER(V30),HLOOKUP(V30,$V$1:$AA$2,2,FALSE)*E30,"") -> 0.5 | X30: B | Y30: 45919 | Z30: 45924 | AA30: 45929
A31: 1027 | B31: Requestor - Project Initiation | C31: Product Determination Questions | D31: Is product designated to one customer | E31: 1 | F31: 25, 26 | G31: dd: YES, NO | H31: yes | I31: Requestor | K31: col AB | L31: CASE and DISPLAY | M31: 1027: predecessor to 1028, 1029 | O31: done | P31: complete | Q31: =VLOOKUP(B31,LOV!$B:$C,2,FALSE) -> 10 | R31: =VLOOKUP(B31,LOV!$B:$D,3,FALSE) -> AA | S31: =VLOOKUP($X31,LOV!$F:$L,2,FALSE) -> WK1 | T31: =VLOOKUP($X31,LOV!$F:$L,7,FALSE) -> 45916 | U31: 3 | V31: 1 | W31: =IF(ISNUMBER(V31),HLOOKUP(V31,$V$1:$AA$2,2,FALSE)*E31,"") -> 0.5 | X31: B | Y31: 45919 | Z31: 45923 | AA31: 45929
A32: 1028 | B32: Requestor - Project Initiation | C32: Product Determination Questions | D32: Designated Customer Name | E32: 1 | F32: 25, 26 | G32: dd: reference list: PRL: Designated Customer Name | H32: conditional | I32: Requestor | K32: col AD | L32: CASE and DISPLAY | M32: 1028 dependent on: Is product designated to one customer (1027) =YES | O32: done | P32: complete | Q32: =VLOOKUP(B32,LOV!$B:$C,2,FALSE) -> 10 | R32: =VLOOKUP(B32,LOV!$B:$D,3,FALSE) -> AA | S32: =VLOOKUP($X32,LOV!$F:$L,2,FALSE) -> WK1 | T32: =VLOOKUP($X32,LOV!$F:$L,7,FALSE) -> 45916 | U32: 3 | V32: 2 | W32: =IF(ISNUMBER(V32),HLOOKUP(V32,$V$1:$AA$2,2,FALSE)*E32,"") -> 1 | X32: B | Y32: 45919 | Z32: 45923 | AA32: 45929
A33: 1029 | B33: Requestor - Project Initiation | C33: Product Determination Questions | D33: Include Designated Cust In Material Desc | E33: 1 | F33: 25, 26 | G33: dd: YES, NO | H33: yes | I33: Requestor | K33: col AF | L33: CASE and DISPLAY | M33: 1029 dependent on: Is product designated to one customer (1027)=YES; 1029 predecessor to 1129 | O33: done | P33: complete | Q33: =VLOOKUP(B33,LOV!$B:$C,2,FALSE) -> 10 | R33: =VLOOKUP(B33,LOV!$B:$D,3,FALSE) -> AA | S33: =VLOOKUP($X33,LOV!$F:$L,2,FALSE) -> WK1 | T33: =VLOOKUP($X33,LOV!$F:$L,7,FALSE) -> 45916 | U33: 3 | V33: 1 | W33: =IF(ISNUMBER(V33),HLOOKUP(V33,$V$1:$AA$2,2,FALSE)*E33,"") -> 0.5 | X33: B | Y33: 45919 | Z33: 45923 | AA33: 45929
A34: 1030 | B34: Requestor - Project Initiation | C34: Product Determination Questions | D34: Variety Pack | E34: 1 | F34: 25 | G34: dd: YES, NO | H34: yes | I34: Requestor | K34: col AH | L34: CASE | M34: 1030 dependent on Product Type (1009) and Product Subtype (1010); Flowchart: Variety Pack | O34: done | P34: complete | Q34: =VLOOKUP(B34,LOV!$B:$C,2,FALSE) -> 10 | R34: =VLOOKUP(B34,LOV!$B:$D,3,FALSE) -> AA | S34: =VLOOKUP($X34,LOV!$F:$L,2,FALSE) -> WK1 | T34: =VLOOKUP($X34,LOV!$F:$L,7,FALSE) -> 45916 | U34: 3 | V34: 1 | W34: =IF(ISNUMBER(V34),HLOOKUP(V34,$V$1:$AA$2,2,FALSE)*E34,"") -> 0.5 | X34: B | Y34: 45922 | Z34: 45923 | AA34: 45929
A35: 1031 | B35: Requestor - Project Initiation | C35: Product Determination Questions | D35: Variety Pack components have UPC codes | E35: 1 | F35: 25 | G35: dd: YES, NO | H35: yes | I35: Requestor | K35: col AJ | L35: CASE | M35: 1031 predecessor to 1188-1192; Flowchart: Variety Pack | O35: done | P35: complete | Q35: =VLOOKUP(B35,LOV!$B:$C,2,FALSE) -> 10 | R35: =VLOOKUP(B35,LOV!$B:$D,3,FALSE) -> AA | S35: =VLOOKUP($X35,LOV!$F:$L,2,FALSE) -> WK1 | T35: =VLOOKUP($X35,LOV!$F:$L,7,FALSE) -> 45916 | U35: 3 | V35: 1 | W35: =IF(ISNUMBER(V35),HLOOKUP(V35,$V$1:$AA$2,2,FALSE)*E35,"") -> 0.5 | X35: B | Y35: 45922 | Z35: 45923 | AA35: 45929
A36: 1032 | B36: Requestor - Project Initiation | C36: Product Determination Questions | D36: Build SKU Using Existing Package UPCs | E36: 1 | F36: 25, 26, 27 | G36: dd: YES, NO | H36: yes | I36: Requestor | K36: col AL | L36: autofill by FORM TYPE: CASE=YES, DISPLAY=NO, and WIP=NO | M36: Flowchart: Build SKU / Existing Printed | O36: done | P36: complete | Q36: =VLOOKUP(B36,LOV!$B:$C,2,FALSE) -> 10 | R36: =VLOOKUP(B36,LOV!$B:$D,3,FALSE) -> AA | S36: =VLOOKUP($X36,LOV!$F:$L,2,FALSE) -> WK2 | T36: =VLOOKUP($X36,LOV!$F:$L,7,FALSE) -> 45922 | U36: 3 | V36: 1 | W36: =IF(ISNUMBER(V36),HLOOKUP(V36,$V$1:$AA$2,2,FALSE)*E36,"") -> 0.5 | X36: C | Y36: 45922 | Z36: 45924 | AA36: 45929
A37: 1033 | B37: Requestor - Project Initiation | C37: Product Determination Questions | D37: Is this item owned by Away From Home | E37: 1 | F37: 25, 26, 27 | G37: dd: YES, NO | H37: yes | I37: Requestor | K37: col AN | L37: CASE, DISPLAY and WIP | M37: 1033 predecessor to: external material group (1085) | O37: done | P37: complete | Q37: =VLOOKUP(B37,LOV!$B:$C,2,FALSE) -> 10 | R37: =VLOOKUP(B37,LOV!$B:$D,3,FALSE) -> AA | S37: =VLOOKUP($X37,LOV!$F:$L,2,FALSE) -> WK2 | T37: =VLOOKUP($X37,LOV!$F:$L,7,FALSE) -> 45922 | U37: 3 | V37: 1 | W37: =IF(ISNUMBER(V37),HLOOKUP(V37,$V$1:$AA$2,2,FALSE)*E37,"") -> 0.5 | X37: C | Y37: 45922 | Z37: 45925 | AA37: 45929
A38: 1034 | B38: Requestor - Project Initiation | C38: Product Determination Questions | D38: Is this an Export Product | E38: 1 | F38: 26, 27, 28 | G38: dd: YES, NO | H38: yes | I38: Requestor | K38: col AP | L38: CASE, DISPLAY and WIP | M38: 1034 predecessor to: external material group (1085), build sku..export (1035), list existing export (1036) | O38: done | P38: complete | Q38: =VLOOKUP(B38,LOV!$B:$C,2,FALSE) -> 10 | R38: =VLOOKUP(B38,LOV!$B:$D,3,FALSE) -> AA | S38: =VLOOKUP($X38,LOV!$F:$L,2,FALSE) -> WK2 | T38: =VLOOKUP($X38,LOV!$F:$L,7,FALSE) -> 45922 | U38: 3 | V38: 1 | W38: =IF(ISNUMBER(V38),HLOOKUP(V38,$V$1:$AA$2,2,FALSE)*E38,"") -> 0.5 | X38: C | Y38: 45922 | Z38: 45925 | AA38: 45929
A39: 1035 | B39: Requestor - Project Initiation | C39: Product Determination Questions | D39: Build SKU Using Existing Export UPCs | E39: 1 | F39: 27, 28 | G39: dd: YES, NO | H39: yes | I39: Requestor | K39: col AR | L39: CASE and WIP | M39: 1035 dependent on 1034 | O39: done | P39: complete | Q39: =VLOOKUP(B39,LOV!$B:$C,2,FALSE) -> 10 | R39: =VLOOKUP(B39,LOV!$B:$D,3,FALSE) -> AA | S39: =VLOOKUP($X39,LOV!$F:$L,2,FALSE) -> WK2 | T39: =VLOOKUP($X39,LOV!$F:$L,7,FALSE) -> 45922 | U39: 3 | V39: 1 | W39: =IF(ISNUMBER(V39),HLOOKUP(V39,$V$1:$AA$2,2,FALSE)*E39,"") -> 0.5 | X39: C | Y39: 45922 | Z39: 45925 | AA39: 45929
A40: 1036 | B40: Requestor - Project Initiation | C40: Product Determination Questions | D40: List Existing Export UPC Codes | E40: 1 | F40: 27, 28 | G40: free form | H40: conditional | I40: Requestor | K40: col AT | L40: CASE and WIP | M40: 1036 dependent on 1034 | O40: done | P40: complete | Q40: =VLOOKUP(B40,LOV!$B:$C,2,FALSE) -> 10 | R40: =VLOOKUP(B40,LOV!$B:$D,3,FALSE) -> AA | S40: =VLOOKUP($X40,LOV!$F:$L,2,FALSE) -> WK2 | T40: =VLOOKUP($X40,LOV!$F:$L,7,FALSE) -> 45922 | U40: 3 | V40: 2 | W40: =IF(ISNUMBER(V40),HLOOKUP(V40,$V$1:$AA$2,2,FALSE)*E40,"") -> 1 | X40: C | Y40: 45922 | Z40: 45925 | AA40: 45929
A41: 1037 | B41: Requestor - Project Initiation | C41: Product Determination Questions | D41: Private Label | E41: 1 | F41: 27, 28 | G41: dd: YES, NO | H41: yes | I41: Requestor | K41: col AU | L41: CASE and WIP | M41: 1037 predecessor to 1038, 1039, 1040 | O41: done | P41: complete | Q41: =VLOOKUP(B41,LOV!$B:$C,2,FALSE) -> 10 | R41: =VLOOKUP(B41,LOV!$B:$D,3,FALSE) -> AA | S41: =VLOOKUP($X41,LOV!$F:$L,2,FALSE) -> WK2 | T41: =VLOOKUP($X41,LOV!$F:$L,7,FALSE) -> 45922 | U41: 3 | V41: 1 | W41: =IF(ISNUMBER(V41),HLOOKUP(V41,$V$1:$AA$2,2,FALSE)*E41,"") -> 0.5 | X41: C | Y41: 45922 | Z41: 45925 | AA41: 45929
A42: 1038 | B42: Requestor - Project Initiation | C42: Product Determination Questions | D42: Private Label Name | E42: 1 | F42: 27, 28 | G42: dd: reference list: PRL: Private Label Customers | H42: conditional | I42: Requestor | K42: col AW | L42: CASE and WIP | M42: 1038 dependent on 1037 | O42: done | P42: complete | Q42: =VLOOKUP(B42,LOV!$B:$C,2,FALSE) -> 10 | R42: =VLOOKUP(B42,LOV!$B:$D,3,FALSE) -> AA | S42: =VLOOKUP($X42,LOV!$F:$L,2,FALSE) -> WK2 | T42: =VLOOKUP($X42,LOV!$F:$L,7,FALSE) -> 45922 | U42: 3 | V42: 2 | W42: =IF(ISNUMBER(V42),HLOOKUP(V42,$V$1:$AA$2,2,FALSE)*E42,"") -> 1 | X42: C | Y42: 45922 | Z42: 45925 | AA42: 45929
A43: 1039 | B43: Requestor - Project Initiation | C43: Product Determination Questions | D43: Build SKU Using Existing Private UPCs | E43: 1 | F43: 27, 28 | G43: dd: YES, NO | H43: yes | I43: Requestor | K43: col AY | L43: CASE and WIP | M43: 1039 dependent on 1037 | O43: done | P43: complete | Q43: =VLOOKUP(B43,LOV!$B:$C,2,FALSE) -> 10 | R43: =VLOOKUP(B43,LOV!$B:$D,3,FALSE) -> AA | S43: =VLOOKUP($X43,LOV!$F:$L,2,FALSE) -> WK2 | T43: =VLOOKUP($X43,LOV!$F:$L,7,FALSE) -> 45922 | U43: 3 | V43: 1 | W43: =IF(ISNUMBER(V43),HLOOKUP(V43,$V$1:$AA$2,2,FALSE)*E43,"") -> 0.5 | X43: C | Y43: 45922 | Z43: 45925 | AA43: 45929
A44: 1040 | B44: Requestor - Project Initiation | C44: Product Determination Questions | D44: List Existing Private UPCs | E44: 1 | F44: 27, 28 | G44: free form | H44: conditional | I44: Requestor | K44: col BA | L44: CASE and WIP | M44: 1040 dependent on 1037 | O44: done | P44: complete | Q44: =VLOOKUP(B44,LOV!$B:$C,2,FALSE) -> 10 | R44: =VLOOKUP(B44,LOV!$B:$D,3,FALSE) -> AA | S44: =VLOOKUP($X44,LOV!$F:$L,2,FALSE) -> WK2 | T44: =VLOOKUP($X44,LOV!$F:$L,7,FALSE) -> 45922 | U44: 3 | V44: 2 | W44: =IF(ISNUMBER(V44),HLOOKUP(V44,$V$1:$AA$2,2,FALSE)*E44,"") -> 1 | X44: C | Y44: 45922 | Z44: 45925 | AA44: 45929
A45: 1041 | B45: Requestor - Project Initiation | C45: Product Determination Questions | D45: Data Sync(GDSN) | E45: 1 | F45: 26, 27, 28 | G45: dd: YES, NO | H45: no, appears that blank is viable | I45: Requestor | K45: NOT in BR.xlsx | L45: CASE, DISPLAY, and WIP | M45: Tamara: should always be YES per Shanan Walker; unless there are extinuating circumstances where they would not want the data to go to the customers | O45: done | P45: complete | Q45: =VLOOKUP(B45,LOV!$B:$C,2,FALSE) -> 10 | R45: =VLOOKUP(B45,LOV!$B:$D,3,FALSE) -> AA | S45: =VLOOKUP($X45,LOV!$F:$L,2,FALSE) -> WK2 | T45: =VLOOKUP($X45,LOV!$F:$L,7,FALSE) -> 45922 | U45: 3 | V45: 1 | W45: =IF(ISNUMBER(V45),HLOOKUP(V45,$V$1:$AA$2,2,FALSE)*E45,"") -> 0.5 | X45: C | Y45: 45922 | Z45: 45925 | AA45: 45929
A46: 1304 | B46: Requestor - Project Initiation | C46: Product Determination Questions | D46: Is this Non Sellable FERT WIP | E46: 1 | F46: 0 | G46: dd: YES, NO | H46: no, appears that blank is viable | I46: Requestor | K46: NOT in BR.xlsx | L46: 9/22/25 new field identified (FALB); currently on WIP form, but should be on CASE (Tamara to get NIF fixed) {as of 9/25/25 the distinction of the Form Type is not included in Expert System Rules} | M46: 1304 predecessor to Planning Variant (1151) and Material Description (1127) | O46: done | P46: complete | Q46: =VLOOKUP(B46,LOV!$B:$C,2,FALSE) -> 10 | R46: =VLOOKUP(B46,LOV!$B:$D,3,FALSE) -> AA | S46: =VLOOKUP($X46,LOV!$F:$L,2,FALSE) -> WK2 | T46: =VLOOKUP($X46,LOV!$F:$L,7,FALSE) -> 45922 | U46: 3 | V46: 3 | W46: =IF(ISNUMBER(V46),HLOOKUP(V46,$V$1:$AA$2,2,FALSE)*E46,"") -> 1.5 | X46: C | Y46: 45922 | Z46: 45925 | AA46: 45929
A47: 1042 | B47: Requestor - Project Initiation | C47: Other UPC Requirements | D47: Material Prefix Description | E47: 1 | F47: 28 | G47: dd: reference list: MATERIAL_PREFIX.XLSX | H47: yes | I47: Requestor | K47: col BB | M47: no known BR based on data entered | O47: done | P47: complete | Q47: =VLOOKUP(B47,LOV!$B:$C,2,FALSE) -> 10 | R47: =VLOOKUP(B47,LOV!$B:$D,3,FALSE) -> AA | S47: =VLOOKUP($X47,LOV!$F:$L,2,FALSE) -> WK2 | T47: =VLOOKUP($X47,LOV!$F:$L,7,FALSE) -> 45922 | U47: 3 | V47: 2 | W47: =IF(ISNUMBER(V47),HLOOKUP(V47,$V$1:$AA$2,2,FALSE)*E47,"") -> 1 | X47: D | Y47: 45922 | Z47: 45925 | AA47: 45929
A48: 1043 | B48: Requestor - Project Initiation | C48: Other UPC Requirements | D48: Is a Compressed UPC Required for the Components | E48: 1 | F48: 28 | G48: dd: NO, POUCH, PACKAGE, BOTH | H48: no, appears that blank is viable | I48: Requestor | K48: col BD | L48: no defaults exist; Used when space is limited (e.g., small packages or pouches) | M48: SAP Classification fields: PACKAGE BAR CODE TYPE, POUCH BAR CODE TYPE; no - (pkgcode=upc_a & pouchcode=upc_a); pouch=(pouchcode=upc_e & pkgcode=upc_a); pkg=(pkgcode=upc_e & pouchcode=upc_a); both=(pkgcode=upc_e & pouchcode=upc_e); Also drives how Masterfiles assigns the codes | O48: done | P48: complete | Q48: =VLOOKUP(B48,LOV!$B:$C,2,FALSE) -> 10 | R48: =VLOOKUP(B48,LOV!$B:$D,3,FALSE) -> AA | S48: =VLOOKUP($X48,LOV!$F:$L,2,FALSE) -> WK2 | T48: =VLOOKUP($X48,LOV!$F:$L,7,FALSE) -> 45922 | U48: 3 | V48: 2 | W48: =IF(ISNUMBER(V48),HLOOKUP(V48,$V$1:$AA$2,2,FALSE)*E48,"") -> 1 | X48: D | Y48: 45922 | Z48: 45925 | AA48: 45929
A49: 1044 | B49: Requestor - Project Initiation | C49: Existing Printed Material Codes | D49: Package UPC Code | E49: 1 | F49: 29 | G49: free form | H49: no | I49: Requestor | K49: col BF | L49: CASE only | M49: Flowchart: Build SKU / Existing Printed | O49: done | P49: complete | Q49: =VLOOKUP(B49,LOV!$B:$C,2,FALSE) -> 10 | R49: =VLOOKUP(B49,LOV!$B:$D,3,FALSE) -> AA | S49: =VLOOKUP($X49,LOV!$F:$L,2,FALSE) -> WK2 | T49: =VLOOKUP($X49,LOV!$F:$L,7,FALSE) -> 45922 | U49: 4 | V49: 2 | W49: =IF(ISNUMBER(V49),HLOOKUP(V49,$V$1:$AA$2,2,FALSE)*E49,"") -> 1 | X49: D | Y49: 45922 | Z49: 45924 | AA49: 45929
A50: 1045 | B50: Requestor - Project Initiation | C50: Existing Printed Material Codes | D50: Package K Number | E50: 1 | F50: 29 | G50: free form | H50: no | I50: Requestor | K50: col BH | L50: CASE only | M50: Flowchart: Build SKU / Existing Printed | O50: done | P50: complete | Q50: =VLOOKUP(B50,LOV!$B:$C,2,FALSE) -> 10 | R50: =VLOOKUP(B50,LOV!$B:$D,3,FALSE) -> AA | S50: =VLOOKUP($X50,LOV!$F:$L,2,FALSE) -> WK2 | T50: =VLOOKUP($X50,LOV!$F:$L,7,FALSE) -> 45922 | U50: 4 | V50: 2 | W50: =IF(ISNUMBER(V50),HLOOKUP(V50,$V$1:$AA$2,2,FALSE)*E50,"") -> 1 | X50: D | Y50: 45922 | Z50: 45924 | AA50: 45929
A51: 1046 | B51: Requestor - Project Initiation | C51: Existing Printed Material Codes | D51: Pouch UPC Code | E51: 1 | F51: 29 | G51: free form | H51: no | I51: Requestor | K51: col BJ | L51: CASE only | M51: Flowchart: Build SKU / Existing Printed | O51: done | P51: complete | Q51: =VLOOKUP(B51,LOV!$B:$C,2,FALSE) -> 10 | R51: =VLOOKUP(B51,LOV!$B:$D,3,FALSE) -> AA | S51: =VLOOKUP($X51,LOV!$F:$L,2,FALSE) -> WK2 | T51: =VLOOKUP($X51,LOV!$F:$L,7,FALSE) -> 45922 | U51: 4 | V51: 2 | W51: =IF(ISNUMBER(V51),HLOOKUP(V51,$V$1:$AA$2,2,FALSE)*E51,"") -> 1 | X51: D | Y51: 45922 | Z51: 45924 | AA51: 45929
A52: 1047 | B52: Requestor - Project Initiation | C52: Existing Printed Material Codes | D52: Pouch K Number | E52: 1 | F52: 29 | G52: free form | H52: no | I52: Requestor | K52: col BL | L52: CASE only | M52: Flowchart: Build SKU / Existing Printed | O52: done | P52: complete | Q52: =VLOOKUP(B52,LOV!$B:$C,2,FALSE) -> 10 | R52: =VLOOKUP(B52,LOV!$B:$D,3,FALSE) -> AA | S52: =VLOOKUP($X52,LOV!$F:$L,2,FALSE) -> WK2 | T52: =VLOOKUP($X52,LOV!$F:$L,7,FALSE) -> 45922 | U52: 4 | V52: 2 | W52: =IF(ISNUMBER(V52),HLOOKUP(V52,$V$1:$AA$2,2,FALSE)*E52,"") -> 1 | X52: D | Y52: 45922 | Z52: 45924 | AA52: 45929
A53: 1048 | B53: Requestor - Project Initiation | C53: Existing Printed Material Codes | D53: List UPC Codes If Already Assigned | E53: 1 | F53: 29 | G53: free form | H53: no | I53: Requestor | K53: NOT in BR.xlsx | L53: CASE only | M53: Flowchart: Build SKU / Existing Printed | O53: done | P53: complete | Q53: =VLOOKUP(B53,LOV!$B:$C,2,FALSE) -> 10 | R53: =VLOOKUP(B53,LOV!$B:$D,3,FALSE) -> AA | S53: =VLOOKUP($X53,LOV!$F:$L,2,FALSE) -> WK2 | T53: =VLOOKUP($X53,LOV!$F:$L,7,FALSE) -> 45922 | U53: 4 | V53: 2 | W53: =IF(ISNUMBER(V53),HLOOKUP(V53,$V$1:$AA$2,2,FALSE)*E53,"") -> 1 | X53: D | Y53: 45922 | Z53: 45924 | AA53: 45929
A54: 1049 | B54: Requestor - Project Initiation | C54: Existing Printed Material Codes | D54: Compressed UPC Existing | E54: 1 | F54: 29 | G54: dd: NO, POUCH, PACKAGE, BOTH | H54: no | I54: Requestor | K54: NOT in BR.xlsx | L54: CASE only; defaulted to NO (for all form types), but can be changed | M54: Flowchart: Build SKU / Existing Printed | O54: done | P54: complete | Q54: =VLOOKUP(B54,LOV!$B:$C,2,FALSE) -> 10 | R54: =VLOOKUP(B54,LOV!$B:$D,3,FALSE) -> AA | S54: =VLOOKUP($X54,LOV!$F:$L,2,FALSE) -> WK2 | T54: =VLOOKUP($X54,LOV!$F:$L,7,FALSE) -> 45922 | U54: 4 | V54: 2 | W54: =IF(ISNUMBER(V54),HLOOKUP(V54,$V$1:$AA$2,2,FALSE)*E54,"") -> 1 | X54: D | Y54: 45922 | Z54: 45924 | AA54: 45929
A55: 1050 | B55: Requestor - Project Initiation | C55: Special Packaging Requirements | D55: Sale Samples may be needed | E55: 1 | F55: 0 | G55: dd: YES, NO | H55: no, appears that blank is viable | I55: Requestor | K55: col BN | L55: …not in Trng_deck.ppt; only open for US and required: STRAIGHT CASE (not Repack); DISPLAY & WIP is locked/blank | M55: Tech name: [Sales_Sample_Question]; 1050 predecessor to "additional pkg for launch" (1053); | O55: done | P55: complete | Q55: =VLOOKUP(B55,LOV!$B:$C,2,FALSE) -> 10 | R55: =VLOOKUP(B55,LOV!$B:$D,3,FALSE) -> AA | S55: =VLOOKUP($X55,LOV!$F:$L,2,FALSE) -> WK2 | T55: =VLOOKUP($X55,LOV!$F:$L,7,FALSE) -> 45922 | U55: 4 | V55: 1 | W55: =IF(ISNUMBER(V55),HLOOKUP(V55,$V$1:$AA$2,2,FALSE)*E55,"") -> 0.5 | X55: D | Y55: 45923 | Z55: 45925 | AA55: 45929
A56: 1051 | B56: Requestor - Project Initiation | C56: UPC Table | D56: Unique UPC | E56: 0 | F56: 29 | G56: autofill | H56: no | I56: Requestor | L56: This section corresponds to the Setup Type that has been chosen, and will show you the UPC requirements. Not sure how this section gets triggered to pull in the correct data (as I can't seem to find it in the NIF Rules.docx). Maybe from the RDL: ALT_UOM {Alternate Unit Of Meaure table} | M56: (only displays for the requestor to review if the levels of the packaging look correct: ie is there a pouch level, if needed); no need to put in AI BOT: unless there is a way to pull the table from the NIF Evolve business rules automatically | O56: done | P56: complete | Q56: =VLOOKUP(B56,LOV!$B:$C,2,FALSE) -> 10 | R56: =VLOOKUP(B56,LOV!$B:$D,3,FALSE) -> AA | S56: =VLOOKUP($X56,LOV!$F:$L,2,FALSE) -> WK2 | T56: =VLOOKUP($X56,LOV!$F:$L,7,FALSE) -> 45922 | U56: 9 | V56: 0 | W56: =IF(ISNUMBER(V56),HLOOKUP(V56,$V$1:$AA$2,2,FALSE)*E56,"") -> 0 | X56: E | Y56: 45924 | Z56: 45925 | AA56: 45929
A57: 1052 | B57: Requestor - Project Initiation | C57: List Existing K Numbers | D57: List Any Existing Knumbers That Will Be Used | E57: 1 | F57: 30 | G57: free form | H57: no | I57: Requestor | K57: NOT in BR.xlsx | M57: no known BR based on data entered | O57: done | P57: complete | Q57: =VLOOKUP(B57,LOV!$B:$C,2,FALSE) -> 10 | R57: =VLOOKUP(B57,LOV!$B:$D,3,FALSE) -> AA | S57: =VLOOKUP($X57,LOV!$F:$L,2,FALSE) -> WK2 | T57: =VLOOKUP($X57,LOV!$F:$L,7,FALSE) -> 45922 | U57: 4 | V57: 2 | W57: =IF(ISNUMBER(V57),HLOOKUP(V57,$V$1:$AA$2,2,FALSE)*E57,"") -> 1 | X57: D | Y57: 45923 | Z57: 45925 | AA57: 45929
A58: 1053 | B58: Requestor - Project Initiation | C58: Special Packaging Requirements | D58: Additional Packaging for Launch | E58: 1 | F58: 30, 47, 56, 113 | G58: dd: reference list: ADDITIONAL_PACKAGING_LAUNCH.XLSX | H58: conditional | I58: Requestor | J58: Masterfiles | K58: col BP | L58: Multiple rows possible. | M58: Tech name: [Special_Launch_Selection]; 1053 dependent on 1050; open for all Form Type=CASE, not required; not DISPLAY or WIP; if "Sale Samples may be needed" (1050)=yes, set 1053 to "Sales Sample Package K number 999 Variant (KXXXXXX999)"; | O58: done | P58: complete | Q58: =VLOOKUP(B58,LOV!$B:$C,2,FALSE) -> 10 | R58: =VLOOKUP(B58,LOV!$B:$D,3,FALSE) -> AA | S58: =VLOOKUP($X58,LOV!$F:$L,2,FALSE) -> WK2 | T58: =VLOOKUP($X58,LOV!$F:$L,7,FALSE) -> 45922 | U58: 4 | V58: 2 | W58: =IF(ISNUMBER(V58),HLOOKUP(V58,$V$1:$AA$2,2,FALSE)*E58,"") -> 1 | X58: D | Y58: 45924 | Z58: 45925 | AA58: 45929
A59: 1054 | B59: LIM - Initial Review | C59: Priority | D59: Priority | E59: 1 | F59: 31 | G59: radio button: NORMAL, CBP, URGENT | I59: LIM | L59: used for naming NIF form | O59: upcoming | P59: current | Q59: =VLOOKUP(B59,LOV!$B:$C,2,FALSE) -> 20 | R59: =VLOOKUP(B59,LOV!$B:$D,3,FALSE) -> DD | S59: =VLOOKUP($X59,LOV!$F:$L,2,FALSE) -> WK3 | T59: =VLOOKUP($X59,LOV!$F:$L,7,FALSE) -> 45929 | V59: 1 | W59: =IF(ISNUMBER(V59),HLOOKUP(V59,$V$1:$AA$2,2,FALSE)*E59,"") -> 0.5 | X59: F
A60: 1055 | B60: LIM - Initial Review | C60: Packaging Tech Assignment | D60: Select Packaging Tech Assignment | E60: 1 | F60: 32, 61 | G60: radio button: BPS, Menasha/12 Associates, Canada VAS | I60: LIM | O60: upcoming | P60: current | Q60: =VLOOKUP(B60,LOV!$B:$C,2,FALSE) -> 20 | R60: =VLOOKUP(B60,LOV!$B:$D,3,FALSE) -> DD | S60: =VLOOKUP($X60,LOV!$F:$L,2,FALSE) -> WK3 | T60: =VLOOKUP($X60,LOV!$F:$L,7,FALSE) -> 45929 | V60: 1 | W60: =IF(ISNUMBER(V60),HLOOKUP(V60,$V$1:$AA$2,2,FALSE)*E60,"") -> 0.5 | X60: F
A61: 1056 | B61: LIM - Initial Review | C61: Person Responsible | D61: Masterfiles | E61: 1 | F61: 32, 61 | G61: dd: user roles | I61: LIM | O61: upcoming | P61: current | Q61: =VLOOKUP(B61,LOV!$B:$C,2,FALSE) -> 20 | R61: =VLOOKUP(B61,LOV!$B:$D,3,FALSE) -> DD | S61: =VLOOKUP($X61,LOV!$F:$L,2,FALSE) -> WK3 | T61: =VLOOKUP($X61,LOV!$F:$L,7,FALSE) -> 45929 | V61: 1 | W61: =IF(ISNUMBER(V61),HLOOKUP(V61,$V$1:$AA$2,2,FALSE)*E61,"") -> 0.5 | X61: F
A62: 1057 | B62: LIM - Initial Review | C62: Person Responsible | D62: EPM Finance | E62: 1 | F62: 32, 61 | G62: dd: user roles | I62: LIM | O62: upcoming | P62: current | Q62: =VLOOKUP(B62,LOV!$B:$C,2,FALSE) -> 20 | R62: =VLOOKUP(B62,LOV!$B:$D,3,FALSE) -> DD | S62: =VLOOKUP($X62,LOV!$F:$L,2,FALSE) -> WK3 | T62: =VLOOKUP($X62,LOV!$F:$L,7,FALSE) -> 45929 | V62: 1 | W62: =IF(ISNUMBER(V62),HLOOKUP(V62,$V$1:$AA$2,2,FALSE)*E62,"") -> 0.5 | X62: F
A63: 1058 | B63: LIM - Initial Review | C63: Person Responsible | D63: Data Integrity | E63: 1 | F63: 32, 61 | G63: dd: user roles | I63: LIM | O63: upcoming | P63: current | Q63: =VLOOKUP(B63,LOV!$B:$C,2,FALSE) -> 20 | R63: =VLOOKUP(B63,LOV!$B:$D,3,FALSE) -> DD | S63: =VLOOKUP($X63,LOV!$F:$L,2,FALSE) -> WK3 | T63: =VLOOKUP($X63,LOV!$F:$L,7,FALSE) -> 45929 | V63: 1 | W63: =IF(ISNUMBER(V63),HLOOKUP(V63,$V$1:$AA$2,2,FALSE)*E63,"") -> 0.5 | X63: F
A64: 1059 | B64: LIM - Initial Review | C64: Person Responsible | D64: Data Integrity (CA) | E64: 1 | F64: 32, 61 | G64: dd: user roles | I64: LIM | O64: upcoming | P64: current | Q64: =VLOOKUP(B64,LOV!$B:$C,2,FALSE) -> 20 | R64: =VLOOKUP(B64,LOV!$B:$D,3,FALSE) -> DD | S64: =VLOOKUP($X64,LOV!$F:$L,2,FALSE) -> WK3 | T64: =VLOOKUP($X64,LOV!$F:$L,7,FALSE) -> 45929 | V64: 1 | W64: =IF(ISNUMBER(V64),HLOOKUP(V64,$V$1:$AA$2,2,FALSE)*E64,"") -> 0.5 | X64: F
A65: 1060 | B65: LIM - Initial Review | C65: Person Responsible | D65: R&D Quality | E65: 1 | F65: 32, 61 | G65: dd: user roles | I65: LIM | O65: upcoming | P65: current | Q65: =VLOOKUP(B65,LOV!$B:$C,2,FALSE) -> 20 | R65: =VLOOKUP(B65,LOV!$B:$D,3,FALSE) -> DD | S65: =VLOOKUP($X65,LOV!$F:$L,2,FALSE) -> WK3 | T65: =VLOOKUP($X65,LOV!$F:$L,7,FALSE) -> 45929 | V65: 1 | W65: =IF(ISNUMBER(V65),HLOOKUP(V65,$V$1:$AA$2,2,FALSE)*E65,"") -> 0.5 | X65: F
A66: 1061 | B66: LIM - Initial Review | C66: Person Responsible | D66: Nutrition Labeling | E66: 1 | F66: 32, 61 | G66: dd: user roles | I66: LIM | O66: upcoming | P66: current | Q66: =VLOOKUP(B66,LOV!$B:$C,2,FALSE) -> 20 | R66: =VLOOKUP(B66,LOV!$B:$D,3,FALSE) -> DD | S66: =VLOOKUP($X66,LOV!$F:$L,2,FALSE) -> WK3 | T66: =VLOOKUP($X66,LOV!$F:$L,7,FALSE) -> 45929 | V66: 1 | W66: =IF(ISNUMBER(V66),HLOOKUP(V66,$V$1:$AA$2,2,FALSE)*E66,"") -> 0.5 | X66: F
A67: 1062 | B67: LIM - Initial Review | C67: Person Responsible | D67: Packaging Tech (Engineer) | E67: 1 | F67: 32, 61 | G67: dd: user roles | I67: LIM | O67: upcoming | P67: current | Q67: =VLOOKUP(B67,LOV!$B:$C,2,FALSE) -> 20 | R67: =VLOOKUP(B67,LOV!$B:$D,3,FALSE) -> DD | S67: =VLOOKUP($X67,LOV!$F:$L,2,FALSE) -> WK3 | T67: =VLOOKUP($X67,LOV!$F:$L,7,FALSE) -> 45929 | V67: 1 | W67: =IF(ISNUMBER(V67),HLOOKUP(V67,$V$1:$AA$2,2,FALSE)*E67,"") -> 0.5 | X67: F
A68: 1063 | B68: LIM - Initial Review | C68: Person Responsible | D68: Category Finance | E68: 1 | F68: 32, 61 | G68: dd: user roles | I68: LIM | O68: upcoming | P68: current | Q68: =VLOOKUP(B68,LOV!$B:$C,2,FALSE) -> 20 | R68: =VLOOKUP(B68,LOV!$B:$D,3,FALSE) -> DD | S68: =VLOOKUP($X68,LOV!$F:$L,2,FALSE) -> WK3 | T68: =VLOOKUP($X68,LOV!$F:$L,7,FALSE) -> 45929 | V68: 1 | W68: =IF(ISNUMBER(V68),HLOOKUP(V68,$V$1:$AA$2,2,FALSE)*E68,"") -> 0.5 | X68: F
A69: 1064 | B69: LIM - Initial Review | C69: Person Responsible | D69: Packaging Tech (BPS) | E69: 1 | F69: 32, 61 | G69: dd: user roles | I69: LIM | O69: upcoming | P69: current | Q69: =VLOOKUP(B69,LOV!$B:$C,2,FALSE) -> 20 | R69: =VLOOKUP(B69,LOV!$B:$D,3,FALSE) -> DD | S69: =VLOOKUP($X69,LOV!$F:$L,2,FALSE) -> WK3 | T69: =VLOOKUP($X69,LOV!$F:$L,7,FALSE) -> 45929 | V69: 1 | W69: =IF(ISNUMBER(V69),HLOOKUP(V69,$V$1:$AA$2,2,FALSE)*E69,"") -> 0.5 | X69: F
A70: 1065 | B70: LIM - Initial Review | C70: Person Responsible | D70: Packaging Tech (Menasha) | E70: 1 | F70: 32, 61 | G70: dd: user roles | I70: LIM | O70: upcoming | P70: current | Q70: =VLOOKUP(B70,LOV!$B:$C,2,FALSE) -> 20 | R70: =VLOOKUP(B70,LOV!$B:$D,3,FALSE) -> DD | S70: =VLOOKUP($X70,LOV!$F:$L,2,FALSE) -> WK3 | T70: =VLOOKUP($X70,LOV!$F:$L,7,FALSE) -> 45929 | V70: 1 | W70: =IF(ISNUMBER(V70),HLOOKUP(V70,$V$1:$AA$2,2,FALSE)*E70,"") -> 0.5 | X70: F
A71: 1066 | B71: LIM - Initial Review | C71: Person Responsible | D71: Packaging Tech (Canada VAS) | E71: 1 | F71: 32, 61 | G71: dd: user roles | I71: LIM | O71: upcoming | P71: current | Q71: =VLOOKUP(B71,LOV!$B:$C,2,FALSE) -> 20 | R71: =VLOOKUP(B71,LOV!$B:$D,3,FALSE) -> DD | S71: =VLOOKUP($X71,LOV!$F:$L,2,FALSE) -> WK3 | T71: =VLOOKUP($X71,LOV!$F:$L,7,FALSE) -> 45929 | V71: 1 | W71: =IF(ISNUMBER(V71),HLOOKUP(V71,$V$1:$AA$2,2,FALSE)*E71,"") -> 0.5 | X71: F
A72: 1067 | B72: LIM - Initial Review | C72: Product Setup | D72: Supply Chain Budget Forecast SKU | E72: 1 | F72: 33 | G72: dd: YES, NO | I72: LIM | L72: CASE only (not DISPLAY or WIP) | M72: 1067 predecessor to 1083-1097; if YES opens 1083+, if NO then skips Forecast section | O72: code rules | P72: current | Q72: =VLOOKUP(B72,LOV!$B:$C,2,FALSE) -> 20 | R72: =VLOOKUP(B72,LOV!$B:$D,3,FALSE) -> DD | S72: =VLOOKUP($X72,LOV!$F:$L,2,FALSE) -> WK3 | T72: =VLOOKUP($X72,LOV!$F:$L,7,FALSE) -> 45929 | V72: 2 | W72: =IF(ISNUMBER(V72),HLOOKUP(V72,$V$1:$AA$2,2,FALSE)*E72,"") -> 1 | X72: F | Y72: 45924
A73: 1068 | B73: LIM - Initial Review | C73: (buttons) Returns | D73: (LIM Initial) Return Comments | E73: 1 | F73: 36 | G73: free form | I73: LIM | O73: upcoming | P73: current | Q73: =VLOOKUP(B73,LOV!$B:$C,2,FALSE) -> 20 | R73: =VLOOKUP(B73,LOV!$B:$D,3,FALSE) -> DD | S73: =VLOOKUP($X73,LOV!$F:$L,2,FALSE) -> WK3 | T73: =VLOOKUP($X73,LOV!$F:$L,7,FALSE) -> 45929 | V73: 1 | W73: =IF(ISNUMBER(V73),HLOOKUP(V73,$V$1:$AA$2,2,FALSE)*E73,"") -> 0.5 | X73: F
A74: 1069 | B74: LIM - LIM REPORT | C74: LIM REPORT section | D74: 5 export (buttons) | E74: 1 | F74: 37-41 | G74: export buttons | I74: LIM | L74: read only form for exporting data to Excel | O74: upcoming | P74: future | Q74: =VLOOKUP(B74,LOV!$B:$C,2,FALSE) -> 30 | R74: =VLOOKUP(B74,LOV!$B:$D,3,FALSE) -> II | S74: =VLOOKUP($X74,LOV!$F:$L,2,FALSE) -> WK5 | T74: =VLOOKUP($X74,LOV!$F:$L,7,FALSE) -> 45943 | V74: 1 | W74: =IF(ISNUMBER(V74),HLOOKUP(V74,$V$1:$AA$2,2,FALSE)*E74,"") -> 0.5 | X74: H
A75: 1070 | B75: Masterfiles - Get Codes | C75: Material Number | D75: Material Number | E75: 1 | F75: 45, 56 | G75: free form | I75: Masterfiles | L75: (field 1013 is same but view only) | M75: no known BR based on data entered | O75: pending | P75: early | Q75: =VLOOKUP(B75,LOV!$B:$C,2,FALSE) -> 40 | R75: =VLOOKUP(B75,LOV!$B:$D,3,FALSE) -> GG | S75: =VLOOKUP($X75,LOV!$F:$L,2,FALSE) -> WK5 | T75: =VLOOKUP($X75,LOV!$F:$L,7,FALSE) -> 45943 | V75: 1 | W75: =IF(ISNUMBER(V75),HLOOKUP(V75,$V$1:$AA$2,2,FALSE)*E75,"") -> 0.5 | X75: H | Y75: 45919
A76: 1072 | B76: Masterfiles - Get Codes | C76: UPC, K#, and GTIN Codes | D76: UPC # | E76: 1 | F76: 47, 56, 113 | G76: free form | I76: Masterfiles | L76: rows of data: 4 (CS, PKG, LYR, UL); PCH | O76: upcoming | P76: future | Q76: =VLOOKUP(B76,LOV!$B:$C,2,FALSE) -> 40 | R76: =VLOOKUP(B76,LOV!$B:$D,3,FALSE) -> GG | S76: =VLOOKUP($X76,LOV!$F:$L,2,FALSE) -> WK5 | T76: =VLOOKUP($X76,LOV!$F:$L,7,FALSE) -> 45943 | V76: 1 | W76: =IF(ISNUMBER(V76),HLOOKUP(V76,$V$1:$AA$2,2,FALSE)*E76,"") -> 0.5 | X76: H
A77: 1073 | B77: Masterfiles - Get Codes | C77: UPC, K#, and GTIN Codes | D77: K # | E77: 1 | F77: 47, 56, 113 | G77: free form | I77: Masterfiles | L77: rows of data: 4 (CS, PKG, LYR, UL); PCH | O77: upcoming | P77: future | Q77: =VLOOKUP(B77,LOV!$B:$C,2,FALSE) -> 40 | R77: =VLOOKUP(B77,LOV!$B:$D,3,FALSE) -> GG | S77: =VLOOKUP($X77,LOV!$F:$L,2,FALSE) -> WK5 | T77: =VLOOKUP($X77,LOV!$F:$L,7,FALSE) -> 45943 | V77: 1 | W77: =IF(ISNUMBER(V77),HLOOKUP(V77,$V$1:$AA$2,2,FALSE)*E77,"") -> 0.5 | X77: H
A78: 1074 | B78: Masterfiles - Get Codes | C78: UPC, K#, and GTIN Codes | D78: Ct | E78: 0 | F78: 56, 113 | G78: autofill | I78: Masterfiles | L78: value appears to be ZU; need to verify; "EAN Cat" | O78: upcoming | P78: future | Q78: =VLOOKUP(B78,LOV!$B:$C,2,FALSE) -> 40 | R78: =VLOOKUP(B78,LOV!$B:$D,3,FALSE) -> GG | S78: =VLOOKUP($X78,LOV!$F:$L,2,FALSE) -> WK5 | T78: =VLOOKUP($X78,LOV!$F:$L,7,FALSE) -> 45943 | V78: 0 | W78: =IF(ISNUMBER(V78),HLOOKUP(V78,$V$1:$AA$2,2,FALSE)*E78,"") -> 0 | X78: H
A79: 1075 | B79: Masterfiles - Get Codes | C79: UPC, K#, and GTIN Codes | D79: UPC Required | E79: 0 | F79: 47, 56, 113 | G79: autofill | I79: Masterfiles | O79: upcoming | P79: future | Q79: =VLOOKUP(B79,LOV!$B:$C,2,FALSE) -> 40 | R79: =VLOOKUP(B79,LOV!$B:$D,3,FALSE) -> GG | S79: =VLOOKUP($X79,LOV!$F:$L,2,FALSE) -> WK5 | T79: =VLOOKUP($X79,LOV!$F:$L,7,FALSE) -> 45943 | V79: 0 | W79: =IF(ISNUMBER(V79),HLOOKUP(V79,$V$1:$AA$2,2,FALSE)*E79,"") -> 0 | X79: H
A80: 1076 | B80: Masterfiles - Get Codes | C80: UPC, K#, and GTIN Codes | D80: Unique or Same UPC | E80: 0 | F80: 47, 56, 113 | G80: autofill | I80: Masterfiles | O80: upcoming | P80: future | Q80: =VLOOKUP(B80,LOV!$B:$C,2,FALSE) -> 40 | R80: =VLOOKUP(B80,LOV!$B:$D,3,FALSE) -> GG | S80: =VLOOKUP($X80,LOV!$F:$L,2,FALSE) -> WK5 | T80: =VLOOKUP($X80,LOV!$F:$L,7,FALSE) -> 45943 | V80: 0 | W80: =IF(ISNUMBER(V80),HLOOKUP(V80,$V$1:$AA$2,2,FALSE)*E80,"") -> 0 | X80: H
A81: 1077 | B81: Masterfiles - Get Codes | C81: UPC, K#, and GTIN Codes | D81: GTIN Number | E81: 1 | F81: 47, 56, 113 | G81: free form | I81: Masterfiles | L81: rows of data: 4 (CS, PKG, LYR, UL); PCH | O81: upcoming | P81: future | Q81: =VLOOKUP(B81,LOV!$B:$C,2,FALSE) -> 40 | R81: =VLOOKUP(B81,LOV!$B:$D,3,FALSE) -> GG | S81: =VLOOKUP($X81,LOV!$F:$L,2,FALSE) -> WK5 | T81: =VLOOKUP($X81,LOV!$F:$L,7,FALSE) -> 45943 | V81: 1 | W81: =IF(ISNUMBER(V81),HLOOKUP(V81,$V$1:$AA$2,2,FALSE)*E81,"") -> 0.5 | X81: H
A82: 1078 | B82: Masterfiles - Get Codes | C82: UPC, K#, and GTIN Codes | D82: GTIN Required | E82: 0 | F82: 47, 56, 113 | G82: autofill | I82: Masterfiles | O82: upcoming | P82: future | Q82: =VLOOKUP(B82,LOV!$B:$C,2,FALSE) -> 40 | R82: =VLOOKUP(B82,LOV!$B:$D,3,FALSE) -> GG | S82: =VLOOKUP($X82,LOV!$F:$L,2,FALSE) -> WK5 | T82: =VLOOKUP($X82,LOV!$F:$L,7,FALSE) -> 45943 | V82: 0 | W82: =IF(ISNUMBER(V82),HLOOKUP(V82,$V$1:$AA$2,2,FALSE)*E82,"") -> 0 | X82: H
A83: 1079 | B83: Masterfiles - Get Codes | C83: UPC, K#, and GTIN Codes | D83: GTIN Prefix | E83: 0 | F83: 47, 56, 113 | G83: autofill | I83: Masterfiles | O83: upcoming | P83: future | Q83: =VLOOKUP(B83,LOV!$B:$C,2,FALSE) -> 40 | R83: =VLOOKUP(B83,LOV!$B:$D,3,FALSE) -> GG | S83: =VLOOKUP($X83,LOV!$F:$L,2,FALSE) -> WK5 | T83: =VLOOKUP($X83,LOV!$F:$L,7,FALSE) -> 45943 | V83: 0 | W83: =IF(ISNUMBER(V83),HLOOKUP(V83,$V$1:$AA$2,2,FALSE)*E83,"") -> 0 | X83: H
A84: 1080 | B84: Masterfiles - Get Codes | C84: UPC, K#, and GTIN Codes | D84: Unique or Same GTIN | E84: 0 | F84: 47, 56, 113 | G84: autofill | I84: Masterfiles | O84: upcoming | P84: future | Q84: =VLOOKUP(B84,LOV!$B:$C,2,FALSE) -> 40 | R84: =VLOOKUP(B84,LOV!$B:$D,3,FALSE) -> GG | S84: =VLOOKUP($X84,LOV!$F:$L,2,FALSE) -> WK5 | T84: =VLOOKUP($X84,LOV!$F:$L,7,FALSE) -> 45943 | V84: 0 | W84: =IF(ISNUMBER(V84),HLOOKUP(V84,$V$1:$AA$2,2,FALSE)*E84,"") -> 0 | X84: H
A85: 1081 | B85: Masterfiles - Get Codes | C85: UPC, K#, and GTIN Codes | D85: Special Launch K Number | E85: 1 | F85: 30, 47, 56, 113 | G85: free form | I85: Masterfiles | L85: Multiple rows possible. | O85: pending | P85: future | Q85: =VLOOKUP(B85,LOV!$B:$C,2,FALSE) -> 40 | R85: =VLOOKUP(B85,LOV!$B:$D,3,FALSE) -> GG | S85: =VLOOKUP($X85,LOV!$F:$L,2,FALSE) -> WK5 | T85: =VLOOKUP($X85,LOV!$F:$L,7,FALSE) -> 45943 | V85: 1 | W85: =IF(ISNUMBER(V85),HLOOKUP(V85,$V$1:$AA$2,2,FALSE)*E85,"") -> 0.5 | X85: H
A86: 1082 | B86: Masterfiles - Get Codes | C86: (buttons) Returns | D86: (MF Get Codes) Return Comments | E86: 1 | F86: 47 | G86: free form | I86: Masterfiles | O86: upcoming | P86: future | Q86: =VLOOKUP(B86,LOV!$B:$C,2,FALSE) -> 40 | R86: =VLOOKUP(B86,LOV!$B:$D,3,FALSE) -> GG | S86: =VLOOKUP($X86,LOV!$F:$L,2,FALSE) -> WK5 | T86: =VLOOKUP($X86,LOV!$F:$L,7,FALSE) -> 45943 | V86: 1 | W86: =IF(ISNUMBER(V86),HLOOKUP(V86,$V$1:$AA$2,2,FALSE)*E86,"") -> 0.5 | X86: H
A87: 1083 | B87: LIM - Forecast Approval | C87: Forecast SKU Requirements | D87: MFG Company | E87: 0 | F87: 51 | G87: dd: reference list: PRL: Manufacturing Company | H87: yes | I87: LIM | L87: LIM approval to setup Forecast sku; SAP Classification-Manufacturer Company | M87: 1083 dependent on 1107 Brand | O87: done | P87: complete | Q87: =VLOOKUP(B87,LOV!$B:$C,2,FALSE) -> 50 | R87: =VLOOKUP(B87,LOV!$B:$D,3,FALSE) -> BB | S87: =VLOOKUP($X87,LOV!$F:$L,2,FALSE) -> WK2 | T87: =VLOOKUP($X87,LOV!$F:$L,7,FALSE) -> 45922 | V87: 0 | W87: =IF(ISNUMBER(V87),HLOOKUP(V87,$V$1:$AA$2,2,FALSE)*E87,"") -> 0 | X87: E | Y87: 45924 | Z87: 45929 | AA87: 45929
A88: 1084 | B88: LIM - Forecast Approval | C88: Forecast SKU Requirements | D88: Material Group | E88: 1 | F88: 51, 74 | G88: dd: reference list: PRL: Material Group | H88: yes | I88: LIM | J88: Requestor | M88: if Product Type=BUNDLE (DTC) then MATERIAL Group=REPACK; otherwise select from dd | O88: done | P88: complete | Q88: =VLOOKUP(B88,LOV!$B:$C,2,FALSE) -> 50 | R88: =VLOOKUP(B88,LOV!$B:$D,3,FALSE) -> BB | S88: =VLOOKUP($X88,LOV!$F:$L,2,FALSE) -> WK2 | T88: =VLOOKUP($X88,LOV!$F:$L,7,FALSE) -> 45922 | U88: 5 | V88: 2 | W88: =IF(ISNUMBER(V88),HLOOKUP(V88,$V$1:$AA$2,2,FALSE)*E88,"") -> 1 | X88: E | Y88: 45924 | Z88: 45926 | AA88: 45929
A89: 1085 | B89: LIM - Forecast Approval | C89: Forecast SKU Requirements | D89: External Material Group | E89: 1 | F89: 51, 74, 105 | G89: dd: reference list: PRL: External Material Group | H89: yes | I89: LIM | J89: Requestor, CA Finance Tax | L89: Bev - check w/TT regarding specific wording in drop down (not part of RDL list) | M89: 1085 dependent on where CHANNEL=: AFH/Specialty (1033), Canada (1008), Export (1034), CLUB, RX- where there is a subselection of the list for these areas; otherwise it shows RETAIL choices | O89: done | P89: complete | Q89: =VLOOKUP(B89,LOV!$B:$C,2,FALSE) -> 50 | R89: =VLOOKUP(B89,LOV!$B:$D,3,FALSE) -> BB | S89: =VLOOKUP($X89,LOV!$F:$L,2,FALSE) -> WK2 | T89: =VLOOKUP($X89,LOV!$F:$L,7,FALSE) -> 45922 | U89: 5 | V89: 2 | W89: =IF(ISNUMBER(V89),HLOOKUP(V89,$V$1:$AA$2,2,FALSE)*E89,"") -> 1 | X89: E | Y89: 45924 | Z89: 45926 | AA89: 45929
A90: 1086 | B90: LIM - Forecast Approval | C90: Forecast SKU Requirements | D90: Estimated Standard Cost | E90: 1 | F90: 51, 107 | G90: free form | H90: yes | I90: LIM | J90: Category Finance | M90: no Business Rules, numbers and decimals only | O90: done | P90: complete | Q90: =VLOOKUP(B90,LOV!$B:$C,2,FALSE) -> 50 | R90: =VLOOKUP(B90,LOV!$B:$D,3,FALSE) -> BB | S90: =VLOOKUP($X90,LOV!$F:$L,2,FALSE) -> WK2 | T90: =VLOOKUP($X90,LOV!$F:$L,7,FALSE) -> 45922 | V90: 1 | W90: =IF(ISNUMBER(V90),HLOOKUP(V90,$V$1:$AA$2,2,FALSE)*E90,"") -> 0.5 | X90: E | Y90: 45924 | Z90: 45926 | AA90: 45929
A91: 1155 | B91: Requestor Update | C91: Product Details | D91: Specialty Channels Field Category | E91: 1 | F91: (not on pg 51), 74 | G91: dd: reference list: PRL: KSC Field Category | H91: yes | I91: Requestor | L91: 9/24/25 - in NIF PROD this field is on the LIM - Forecast Approval training section | M91: no known BR based on data entered | O91: done | P91: complete | Q91: =VLOOKUP(B91,LOV!$B:$C,2,FALSE) -> 100 | R91: =VLOOKUP(B91,LOV!$B:$D,3,FALSE) -> CC | S91: =VLOOKUP($X91,LOV!$F:$L,2,FALSE) -> WK2 | T91: =VLOOKUP($X91,LOV!$F:$L,7,FALSE) -> 45922 | U91: 5 | V91: 1 | W91: =IF(ISNUMBER(V91),HLOOKUP(V91,$V$1:$AA$2,2,FALSE)*E91,"") -> 0.5 | X91: E | Y91: 45924 | Z91: 45926 | AA91: 45929
A92: 1087 | B92: LIM - Forecast Approval | C92: Forecast SKU Requirements | D92: Red K Price | E92: 1 | F92: 51 | G92: free form | H92: yes | I92: LIM | L92: Tamara to test - Canada 9/26/25 - Query not included in Expert System Rules | M92: numbers and decimals; runs query_tax_classification query (what does this do | O92: done | P92: last week | Q92: =VLOOKUP(B92,LOV!$B:$C,2,FALSE) -> 50 | R92: =VLOOKUP(B92,LOV!$B:$D,3,FALSE) -> BB | S92: =VLOOKUP($X92,LOV!$F:$L,2,FALSE) -> WK2 | T92: =VLOOKUP($X92,LOV!$F:$L,7,FALSE) -> 45922 | V92: 1 | W92: =IF(ISNUMBER(V92),HLOOKUP(V92,$V$1:$AA$2,2,FALSE)*E92,"") -> 0.5 | X92: E | Y92: 45924 | Z92: 45926 | AA92: 45929
A93: 1088 | B93: LIM - Forecast Approval | C93: Forecast SKU Requirements | D93: Material Prefix | E93: 0 | F93: 51 | G93: autofill | I93: LIM | L93: based off SUB-TYPE DESCRIPTION | M93: display only - duplicate of Material Prefix Description (1042) | N93: (same as Material Prefix Description) | O93: done | P93: complete | Q93: =VLOOKUP(B93,LOV!$B:$C,2,FALSE) -> 50 | R93: =VLOOKUP(B93,LOV!$B:$D,3,FALSE) -> BB | S93: =VLOOKUP($X93,LOV!$F:$L,2,FALSE) -> WK2 | T93: =VLOOKUP($X93,LOV!$F:$L,7,FALSE) -> 45922 | V93: 0 | W93: =IF(ISNUMBER(V93),HLOOKUP(V93,$V$1:$AA$2,2,FALSE)*E93,"") -> 0 | X93: E | Y93: 45924 | Z93: 45929 | AA93: 45929
A94: 1089 | B94: LIM - Forecast Approval | C94: Forecast SKU Requirements | D94: Transportation Group | E94: 1 | F94: 51, 80 | G94: dd: reference list: PRL: Transportation Group | H94: yes | I94: LIM | M94: no known BR based on data entered | O94: done | P94: complete | Q94: =VLOOKUP(B94,LOV!$B:$C,2,FALSE) -> 50 | R94: =VLOOKUP(B94,LOV!$B:$D,3,FALSE) -> BB | S94: =VLOOKUP($X94,LOV!$F:$L,2,FALSE) -> WK2 | T94: =VLOOKUP($X94,LOV!$F:$L,7,FALSE) -> 45922 | V94: 2 | W94: =IF(ISNUMBER(V94),HLOOKUP(V94,$V$1:$AA$2,2,FALSE)*E94,"") -> 1 | X94: E | Y94: 45924 | Z94: 45926 | AA94: 45929
A95: 1090 | B95: LIM - Forecast Approval | C95: Forecast SKU Requirements | D95: Net Case Weight | E95: 1 | F95: 51 | G95: free form | H95: yes | I95: LIM | M95: 1090 predecessor to: If US then Imperial (1092) is required and Metric (1091) is open but not required, otherwise if NOT-US then Metric is required and Imperial is open but not required | O95: done | P95: complete | Q95: =VLOOKUP(B95,LOV!$B:$C,2,FALSE) -> 50 | R95: =VLOOKUP(B95,LOV!$B:$D,3,FALSE) -> BB | S95: =VLOOKUP($X95,LOV!$F:$L,2,FALSE) -> WK2 | T95: =VLOOKUP($X95,LOV!$F:$L,7,FALSE) -> 45922 | V95: 1 | W95: =IF(ISNUMBER(V95),HLOOKUP(V95,$V$1:$AA$2,2,FALSE)*E95,"") -> 0.5 | X95: E | Y95: 45924 | Z95: 45928 | AA95: 45929
A96: 1091 | B96: LIM - Forecast Approval | C96: Forecast SKU Requirements | D96: Metric Stated Net Pkg Wt | E96: 1 | F96: 51 | G96: free form | H96: conditional | I96: LIM | M96: 1091 dependent on 1090 | O96: done | P96: complete | Q96: =VLOOKUP(B96,LOV!$B:$C,2,FALSE) -> 50 | R96: =VLOOKUP(B96,LOV!$B:$D,3,FALSE) -> BB | S96: =VLOOKUP($X96,LOV!$F:$L,2,FALSE) -> WK2 | T96: =VLOOKUP($X96,LOV!$F:$L,7,FALSE) -> 45922 | V96: 1 | W96: =IF(ISNUMBER(V96),HLOOKUP(V96,$V$1:$AA$2,2,FALSE)*E96,"") -> 0.5 | X96: E | Y96: 45924 | Z96: 45928 | AA96: 45929
A97: 1092 | B97: LIM - Forecast Approval | C97: Forecast SKU Requirements | D97: Imperial Stated Net Pkg Wt | E97: 1 | F97: 51 | G97: free form | H97: conditional | I97: LIM | M97: 1092 dependent on 1090 | O97: done | P97: complete | Q97: =VLOOKUP(B97,LOV!$B:$C,2,FALSE) -> 50 | R97: =VLOOKUP(B97,LOV!$B:$D,3,FALSE) -> BB | S97: =VLOOKUP($X97,LOV!$F:$L,2,FALSE) -> WK2 | T97: =VLOOKUP($X97,LOV!$F:$L,7,FALSE) -> 45922 | V97: 1 | W97: =IF(ISNUMBER(V97),HLOOKUP(V97,$V$1:$AA$2,2,FALSE)*E97,"") -> 0.5 | X97: E | Y97: 45924 | Z97: 45928 | AA97: 45929
A98: 1093 | B98: LIM - Forecast Approval | C98: Forecast SKU Requirements | D98: Country Sold In | E98: 1 | F98: 51, 76 | G98: dd: reference list: PRL: COUNTRY | H98: yes | I98: LIM | J98: Requestor | L98: Multiple rows possible. 9/29/25 - DataSync would like this to only be one answer, as it causes issues otherwise. (not yet in NIF code) | M98: 9/29/25 - did not code: if AA then change to US (might be because Jon put US at the top of the list with the AA); no other business rules | O98: done | P98: complete | Q98: =VLOOKUP(B98,LOV!$B:$C,2,FALSE) -> 50 | R98: =VLOOKUP(B98,LOV!$B:$D,3,FALSE) -> BB | S98: =VLOOKUP($X98,LOV!$F:$L,2,FALSE) -> WK2 | T98: =VLOOKUP($X98,LOV!$F:$L,7,FALSE) -> 45922 | U98: 6 | V98: 2 | W98: =IF(ISNUMBER(V98),HLOOKUP(V98,$V$1:$AA$2,2,FALSE)*E98,"") -> 1 | X98: E | Y98: 45925 | Z98: 45928 | AA98: 45929
A99: 1094 | B99: LIM - Forecast Approval | C99: Forecast SKU Requirements | D99: Location | E99: 1 | F99: 51, 81 | G99: dd: reference list: ZMMU table (not in RDL or PRL) | H99: yes | I99: LIM | L99: 10/10/25 - asked Tamara; multipe rows possible | M99: 1094 predecessor to 1095 populates from ref list; if VAS=yes, then In/Out required | O99: done | P99: complete | Q99: =VLOOKUP(B99,LOV!$B:$C,2,FALSE) -> 50 | R99: =VLOOKUP(B99,LOV!$B:$D,3,FALSE) -> BB | S99: =VLOOKUP($X99,LOV!$F:$L,2,FALSE) -> WK2 | T99: =VLOOKUP($X99,LOV!$F:$L,7,FALSE) -> 45922 | V99: 2 | W99: =IF(ISNUMBER(V99),HLOOKUP(V99,$V$1:$AA$2,2,FALSE)*E99,"") -> 1 | X99: E | Y99: 45925 | Z99: 45929 | AA99: 45929
A100: 1095 | B100: LIM - Forecast Approval | C100: Forecast SKU Requirements | D100: Location Description | E100: 0 | F100: 51, 81 | G100: autofill | H100: no | I100: LIM | L100: Multiple rows possible. | M100: 1095 dependent on 1094 | O100: done | P100: complete | Q100: =VLOOKUP(B100,LOV!$B:$C,2,FALSE) -> 50 | R100: =VLOOKUP(B100,LOV!$B:$D,3,FALSE) -> BB | S100: =VLOOKUP($X100,LOV!$F:$L,2,FALSE) -> WK2 | T100: =VLOOKUP($X100,LOV!$F:$L,7,FALSE) -> 45922 | V100: 0 | W100: =IF(ISNUMBER(V100),HLOOKUP(V100,$V$1:$AA$2,2,FALSE)*E100,"") -> 0 | X100: E | Y100: 45925 | Z100: 45929 | AA100: 45929
...

Sheet Sprint fields
A1: Training Section - fields & complexity | P1: Complexity by Week and Training Section Priority | AC1: Timing Status by Week by Training Section Priority | AS1: Training Sections - number of fields to be defined
U5: Complexity
A6: # fields | H6: COMPLEXITY (3..1,0) 3-high 2-med 1-low 0-autofill | P6: Count of field names in Trng deck | U6: Complexity | AL6: Values | AS6: # fields
A7: Week | B7: Week Beginning Date | C7: Sprint | D7: Trng Sectn Priority | E7: Trng Sectn # | F7: Training Section | G7: field names in Trng deck | H7: 3 | I7: 2 | J7: 1 | K7: 0 | L7: Grand Total | P7: Week | Q7: Week Beginning Date | R7: Trng Sectn Priority | S7: Trng Sectn # | T7: Training Section | U7: 3 | V7: 2 | W7: 1 | X7: 0 | Y7: Grand Total | AC7: Week | AD7: Week Beginning Date | AE7: Sprint | AF7: Trng Sectn # | AG7: Training Section | AH7: UNIQUE FIELD # (order in Trng deck) | AI7: field names in Trng deck | AJ7: Business Rule status | AK7: COMPLEXITY (3..1,0) 3-high 2-med 1-low 0-autofill | AL7: # fields | AM7: Business Reviewd | AN7: Formatted Business Rules | AO7: Given to AI team | AS7: Trng Sectn # | AT7: Training Section | AU7: Total
A8: WK1 | B8: 45916 | C8: A | D8: AA | E8: 10 | F8: Requestor - Project Initiation | G8: Form Type | H8: 1 | L8: 1 | P8: WK1 | Q8: 45916 | R8: AA | S8: 10 | T8: Requestor - Project Initiation | U8: 6 | V8: 7 | W8: 12 | Y8: 25 | AC8: WK1 | AD8: 45916 | AE8: A | AF8: 10 | AG8: Requestor - Project Initiation | AH8: 1007 | AI8: Form Type | AJ8: done | AK8: 3 | AL8: 1 | AM8: 1 | AN8: 1 | AO8: 1 | AS8: 10 | AT8: Requestor - Project Initiation | AU8: 55
G9: Product Country | H9: 1 | L9: 1 | P9: WK1 Total | U9: 6 | V9: 7 | W9: 12 | Y9: 25 | AH9: 1008 | AI9: Product Country | AJ9: done | AK9: 3 | AL9: 1 | AM9: 1 | AN9: 1 | AO9: 1 | AS9: 20 | AT9: LIM - Initial Review | AU9: 15
G10: Product Sub Type | H10: 1 | L10: 1 | P10: WK2 | Q10: 45922 | R10: AA | S10: 10 | T10: Requestor - Project Initiation | U10: 1 | V10: 13 | W10: 10 | X10: 6 | Y10: 30 | AH10: 1009 | AI10: Product Type | AJ10: done | AK10: 3 | AL10: 1 | AM10: 1 | AN10: 1 | AO10: 1 | AS10: 30 | AT10: LIM - LIM REPORT | AU10: 1
G11: Product Type | H11: 1 | L11: 1 | R11: BB | S11: 50 | T11: LIM - Forecast Approval | U11: 3 | V11: 9 | W11: 17 | X11: 23 | Y11: 52 | AH11: 1010 | AI11: Product Sub Type | AJ11: done | AK11: 3 | AL11: 1 | AM11: 1 | AN11: 1 | AO11: 1 | AS11: 40 | AT11: Masterfiles - Get Codes | AU11: 13
G12: Project Name or Number | J12: 1 | L12: 1 | R12: CC | S12: 100 | T12: Requestor Update | V12: 2 | W12: 17 | X12: 5 | Y12: 24 | AH12: 1011 | AI12: Is this a Pringles product | AJ12: done | AK12: 1 | AL12: 1 | AM12: 1 | AN12: 1 | AO12: 1 | AS12: 50 | AT12: LIM - Forecast Approval | AU12: 52
G13: Project Type | I13: 1 | L13: 1 | P13: WK2 Total | U13: 4 | V13: 24 | W13: 44 | X13: 34 | Y13: 106 | AH13: 1012 | AI13: Is this an RX Product | AJ13: done | AK13: 1 | AL13: 1 | AM13: 1 | AN13: 1 | AO13: 1 | AS13: 60 | AT13: Masterfiles - Get Codes Forecast | AU13: 2
G14: Set Category | J14: 1 | L14: 1 | P14: WK3 | Q14: 45929 | R14: CC | S14: 100 | T14: Requestor Update | V14: 2 | W14: 21 | X14: 8 | Y14: 31 | AH14: 1014 | AI14: Project Type | AJ14: done | AK14: 2 | AL14: 1 | AM14: 1 | AN14: 1 | AO14: 1 | AS14: 70 | AT14: LIM - Launch | AU14: 1
G15: Is this a Pringles product | J15: 1 | L15: 1 | S15: 230 | T15: Requestor - Req Launch DTC | U15: 5 | V15: 1 | W15: 3 | Y15: 9 | AH15: 1015 | AI15: Project Name or Number | AJ15: done | AK15: 1 | AL15: 1 | AM15: 1 | AN15: 1 | AO15: 1 | AS15: 80 | AT15: LIM Launch - Update | AU15: 1
G16: Is this an RX Product | J16: 1 | L16: 1 | R16: DD | S16: 20 | T16: LIM - Initial Review | V16: 1 | W16: 14 | Y16: 15 | AH16: 1016 | AI16: Set Category | AJ16: done | AK16: 1 | AL16: 1 | AM16: 1 | AN16: 1 | AO16: 1 | AS16: 90 | AT16: ZNIF Dashboard - view only | AU16: 1
C17: B | D17: AA | E17: 10 | F17: Requestor - Project Initiation | G17: Approved to sell via Ecommerce | J17: 1 | L17: 1 | S17: 70 | T17: LIM - Launch | V17: 1 | Y17: 1 | AE17: B | AF17: 10 | AG17: Requestor - Project Initiation | AH17: 1013 | AI17: SAP Material Number | AJ17: done | AK17: 1 | AL17: 1 | AM17: 1 | AN17: 1 | AO17: 1 | AS17: 100 | AT17: Requestor Update | AU17: 55
G18: Brief Product Description | I18: 1 | L18: 1 | S18: 80 | T18: LIM Launch - Update | W18: 1 | Y18: 1 | AH18: 1017 | AI18: Brief Product Description | AJ18: done | AK18: 2 | AL18: 1 | AM18: 1 | AN18: 1 | AO18: 1 | AS18: 110 | AT18: LIM - Update | AU18: 11
G19: Brief Project Overview and Technical Notes | I19: 1 | L19: 1 | S19: 110 | T19: LIM - Update | V19: 1 | W19: 6 | X19: 4 | Y19: 11 | AH19: 1018 | AI19: Brief Project Overview and Technical Notes | AJ19: done | AK19: 2 | AL19: 1 | AM19: 1 | AN19: 1 | AO19: 1 | AS19: 120 | AT19: EPM Finance - Update | AU19: 2
G20: Case Count | H20: 1 | L20: 1 | S20: 200 | T20: LIM - Approval/NIF Dashboard | W20: 2 | Y20: 2 | AH20: 1019 | AI20: Stated Weight Applicable For | AJ20: done | AK20: 2 | AL20: 1 | AM20: 1 | AN20: 1 | AO20: 1 | AS20: 130 | AT20: Data Integrity (DI) - Review | AU20: 1
G21: Case Count Status | I21: 1 | L21: 1 | P21: WK3 Total | U21: 5 | V21: 6 | W21: 47 | X21: 12 | Y21: 70 | AH21: 1020 | AI21: Stated Weight Status | AJ21: done | AK21: 2 | AL21: 1 | AM21: 1 | AN21: 1 | AO21: 1 | AS21: 140 | AT21: R&D Quality - Update | AU21: 4
G22: Designated Customer Name | I22: 1 | L22: 1 | P22: WK4 | Q22: 45936 | R22: EE | S22: 150 | T22: Nutrition Labeling - Update | U22: 4 | W22: 20 | Y22: 24 | AH22: 1021 | AI22: Stated Net Weight | AJ22: done | AK22: 1 | AL22: 1 | AM22: 1 | AN22: 1 | AO22: 1 | AS22: 150 | AT22: Nutrition Labeling - Update | AU22: 24
G23: Like SKU / Reference Material Number | H23: 1 | L23: 1 | S23: 160 | T23: Packaging Tech - Update | W23: 15 | X23: 4 | Y23: 19 | AH23: 1022 | AI23: Stated Net Weight UOM | AJ23: done | AK23: 1 | AL23: 1 | AM23: 1 | AN23: 1 | AO23: 1 | AS23: 160 | AT23: Packaging Tech - Update | AU23: 19
G24: SAP Material Number | J24: 1 | L24: 1 | P24: WK4 Total | U24: 4 | W24: 35 | X24: 4 | Y24: 43 | AH24: 1023 | AI24: Case Count Status | AJ24: done | AK24: 2 | AL24: 1 | AM24: 1 | AN24: 1 | AO24: 1 | AS24: 170 | AT24: CA Finance Tax | AU24: 2
G25: Stated Net Weight | J25: 1 | L25: 1 | P25: WK5 | Q25: 45943 | R25: FF | S25: 120 | T25: EPM Finance - Update | W25: 2 | Y25: 2 | AH25: 1024 | AI25: Case Count | AJ25: done | AK25: 3 | AL25: 1 | AM25: 1 | AN25: 1 | AO25: 1 | AS25: 180 | AT25: Category Finance - update | AU25: 1
G26: Stated Net Weight UOM | J26: 1 | L26: 1 | S26: 130 | T26: Data Integrity (DI) - Review | W26: 1 | Y26: 1 | AH26: 1025 | AI26: Like SKU / Reference Material Number | AJ26: done | AK26: 3 | AL26: 1 | AM26: 1 | AN26: 1 | AO26: 1 | AS26: 190 | AT26: Data Integrity (DI) - Hierarchy | AU26: 1
G27: Stated Weight Applicable For | I27: 1 | L27: 1 | S27: 140 | T27: R&D Quality - Update | W27: 4 | Y27: 4 | AH27: 1026 | AI27: Approved to sell via Ecommerce | AJ27: done | AK27: 1 | AL27: 1 | AM27: 1 | AN27: 1 | AO27: 1 | AS27: 200 | AT27: LIM - Approval/NIF Dashboard | AU27: 2
G28: Stated Weight Status | I28: 1 | L28: 1 | S28: 170 | T28: CA Finance Tax | W28: 2 | Y28: 2 | AH28: 1027 | AI28: Is product designated to one customer | AJ28: done | AK28: 1 | AL28: 1 | AM28: 1 | AN28: 1 | AO28: 1 | AS28: 210 | AT28: Masterfiles - Approval | AU28: 18
G29: Is product designated to one customer | J29: 1 | L29: 1 | S29: 180 | T29: Category Finance - update | W29: 1 | Y29: 1 | AH29: 1028 | AI29: Designated Customer Name | AJ29: done | AK29: 2 | AL29: 1 | AM29: 1 | AN29: 1 | AO29: 1 | AS29: 220 | AT29: Masterfiles - Create Plant Extensions, pricing & BOM's | AU29: 17
G30: Include Designated Cust In Material Desc | J30: 1 | L30: 1 | S30: 190 | T30: Data Integrity (DI) - Hierarchy | W30: 1 | Y30: 1 | AH30: 1029 | AI30: Include Designated Cust In Material Desc | AJ30: done | AK30: 1 | AL30: 1 | AM30: 1 | AN30: 1 | AO30: 1 | AS30: 230 | AT30: Requestor - Req Launch DTC | AU30: 9
G31: Variety Pack | J31: 1 | L31: 1 | R31: GG | S31: 40 | T31: Masterfiles - Get Codes | W31: 6 | X31: 7 | Y31: 13 | AH31: 1030 | AI31: Variety Pack | AJ31: done | AK31: 1 | AL31: 1 | AM31: 1 | AN31: 1 | AO31: 1 | AS31: Grand Total | AU31: 307
G32: Variety Pack components have UPC codes | J32: 1 | L32: 1 | S32: 60 | T32: Masterfiles - Get Codes Forecast | W32: 2 | Y32: 2 | AH32: 1031 | AI32: Variety Pack components have UPC codes | AJ32: done | AK32: 1 | AL32: 1 | AM32: 1 | AN32: 1 | AO32: 1
A33: WK1 Total | H33: 6 | I33: 7 | J33: 12 | L33: 25 | R33: HH | S33: 210 | T33: Masterfiles - Approval | W33: 15 | X33: 3 | Y33: 18 | AC33: WK1 Total | AL33: 25 | AM33: 25 | AN33: 25 | AO33: 25
A34: WK2 | B34: 45922 | C34: C | D34: AA | E34: 10 | F34: Requestor - Project Initiation | G34: List Existing Export UPC Codes | I34: 1 | L34: 1 | S34: 220 | T34: Masterfiles - Create Plant Extensions, pricing & BOM's | W34: 15 | X34: 2 | Y34: 17 | AC34: WK2 | AD34: 45922 | AE34: C | AF34: 10 | AG34: Requestor - Project Initiation | AH34: 1032 | AI34: Build SKU Using Existing Package UPCs | AJ34: done | AK34: 1 | AL34: 1 | AM34: 1 | AN34: 1 | AO34: 1
G35: List Existing Private UPCs | I35: 1 | L35: 1 | R35: II | S35: 30 | T35: LIM - LIM REPORT | W35: 1 | Y35: 1 | AH35: 1033 | AI35: Is this item owned by Away From Home | AJ35: done | AK35: 1 | AL35: 1 | AM35: 1 | AN35: 1 | AO35: 1
G36: Private Label Name | I36: 1 | L36: 1 | S36: 90 | T36: ZNIF Dashboard - view only | X36: 1 | Y36: 1 | AH36: 1034 | AI36: Is this an Export Product | AJ36: done | AK36: 1 | AL36: 1 | AM36: 1 | AN36: 1 | AO36: 1
G37: Build SKU Using Existing Package UPCs | J37: 1 | L37: 1 | P37: WK5 Total | W37: 50 | X37: 13 | Y37: 63 | AH37: 1035 | AI37: Build SKU Using Existing Export UPCs | AJ37: done | AK37: 1 | AL37: 1 | AM37: 1 | AN37: 1 | AO37: 1
G38: Is this item owned by Away From Home | J38: 1 | L38: 1 | P38: Grand Total | U38: 19 | V38: 37 | W38: 188 | X38: 63 | Y38: 307 | AH38: 1036 | AI38: List Existing Export UPC Codes | AJ38: done | AK38: 2 | AL38: 1 | AM38: 1 | AN38: 1 | AO38: 1
G39: Is this an Export Product | J39: 1 | L39: 1 | AH39: 1037 | AI39: Private Label | AJ39: done | AK39: 1 | AL39: 1 | AM39: 1 | AN39: 1 | AO39: 1
G40: Build SKU Using Existing Export UPCs | J40: 1 | L40: 1 | AH40: 1038 | AI40: Private Label Name | AJ40: done | AK40: 2 | AL40: 1 | AM40: 1 | AN40: 1 | AO40: 1
G41: Private Label | J41: 1 | L41: 1 | AH41: 1039 | AI41: Build SKU Using Existing Private UPCs | AJ41: done | AK41: 1 | AL41: 1 | AM41: 1 | AN41: 1 | AO41: 1
G42: Build SKU Using Existing Private UPCs | J42: 1 | L42: 1 | AH42: 1040 | AI42: List Existing Private UPCs | AJ42: done | AK42: 2 | AL42: 1 | AM42: 1 | AN42: 1 | AO42: 1
G43: Data Sync(GDSN) | J43: 1 | L43: 1 | AH43: 1041 | AI43: Data Sync(GDSN) | AJ43: done | AK43: 1 | AL43: 1 | AM43: 1 | AN43: 1 | AO43: 1
G44: Is this Non Sellable FERT WIP | H44: 1 | L44: 1 | AH44: 1304 | AI44: Is this Non Sellable FERT WIP | AJ44: done | AK44: 3 | AL44: 1 | AM44: 1 | AN44: 1 | AO44: 1
C45: D | D45: AA | E45: 10 | F45: Requestor - Project Initiation | G45: Additional Packaging for Launch | I45: 1 | L45: 1 | AE45: D | AF45: 10 | AG45: Requestor - Project Initiation | AH45: 1006 | AI45: LIM | AJ45: done | AK45: 1 | AL45: 1 | AM45: 1 | AN45: 1 | AO45: 1
G46: Compressed UPC Existing | I46: 1 | L46: 1 | AH46: 1042 | AI46: Material Prefix Description | AJ46: done | AK46: 2 | AL46: 1 | AM46: 1 | AN46: 1 | AO46: 1
G47: LIM | J47: 1 | L47: 1 | AH47: 1043 | AI47: Is a Compressed UPC Required for the Components | AJ47: done | AK47: 2 | AL47: 1 | AM47: 1 | AN47: 1 | AO47: 1
G48: List Any Existing Knumbers That Will Be Used | I48: 1 | L48: 1 | AH48: 1044 | AI48: Package UPC Code | AJ48: done | AK48: 2 | AL48: 1 | AM48: 1 | AN48: 1 | AO48: 1
G49: List UPC Codes If Already Assigned | I49: 1 | L49: 1 | AH49: 1045 | AI49: Package K Number | AJ49: done | AK49: 2 | AL49: 1 | AM49: 1 | AN49: 1 | AO49: 1
G50: Material Prefix Description | I50: 1 | L50: 1 | AH50: 1046 | AI50: Pouch UPC Code | AJ50: done | AK50: 2 | AL50: 1 | AM50: 1 | AN50: 1 | AO50: 1
G51: Package K Number | I51: 1 | L51: 1 | AH51: 1047 | AI51: Pouch K Number | AJ51: done | AK51: 2 | AL51: 1 | AM51: 1 | AN51: 1 | AO51: 1
G52: Package UPC Code | I52: 1 | L52: 1 | AH52: 1048 | AI52: List UPC Codes If Already Assigned | AJ52: done | AK52: 2 | AL52: 1 | AM52: 1 | AN52: 1 | AO52: 1
G53: Pouch K Number | I53: 1 | L53: 1 | AH53: 1049 | AI53: Compressed UPC Existing | AJ53: done | AK53: 2 | AL53: 1 | AM53: 1 | AN53: 1 | AO53: 1
G54: Pouch UPC Code | I54: 1 | L54: 1 | AH54: 1050 | AI54: Sale Samples may be needed | AJ54: done | AK54: 1 | AL54: 1 | AM54: 1 | AN54: 1 | AO54: 1
G55: Sale Samples may be needed | J55: 1 | L55: 1 | AH55: 1052 | AI55: List Any Existing Knumbers That Will Be Used | AJ55: done | AK55: 2 | AL55: 1 | AM55: 1 | AN55: 1 | AO55: 1
G56: Is a Compressed UPC Required for the Components | I56: 1 | L56: 1 | AH56: 1053 | AI56: Additional Packaging for Launch | AJ56: done | AK56: 2 | AL56: 1 | AM56: 1 | AN56: 1 | AO56: 1
C57: E | D57: AA | E57: 10 | F57: Requestor - Project Initiation | G57: Requestor | K57: 1 | L57: 1 | AE57: E | AF57: 10 | AG57: Requestor - Project Initiation | AH57: 1001 | AI57: Requestor Name | AJ57: done | AK57: 0 | AL57: 1 | AM57: 1 | AN57: 1 | AO57: 1
G58: Requestor Date | K58: 1 | L58: 1 | AH58: 1002 | AI58: Requestor Email | AJ58: done | AK58: 0 | AL58: 1 | AM58: 1 | AN58: 1 | AO58: 1
G59: Requestor Email | K59: 1 | L59: 1 | AH59: 1003 | AI59: Requestor Date | AJ59: done | AK59: 0 | AL59: 1 | AM59: 1 | AN59: 1 | AO59: 1
G60: Requestor Name | K60: 1 | L60: 1 | AH60: 1004 | AI60: Version | AJ60: done | AK60: 0 | AL60: 1 | AM60: 1 | AN60: 1 | AO60: 1
G61: Version | K61: 1 | L61: 1 | AH61: 1005 | AI61: Requestor | AJ61: done | AK61: 0 | AL61: 1 | AM61: 1 | AN61: 1 | AO61: 1
G62: Business Area | J62: 1 | L62: 1 | AH62: 1051 | AI62: Unique UPC | AJ62: done | AK62: 0 | AL62: 1 | AM62: 1 | AN62: 1 | AO62: 1
G63: Unique UPC | K63: 1 | L63: 1 | AH63: 1305 | AI63: Business Area | AJ63: done | AK63: 1 | AL63: 1 | AM63: 1 | AN63: 1 | AO63: 1
D64: BB | E64: 50 | F64: LIM - Forecast Approval | G64: <=> | K64: 1 | L64: 1 | AF64: 50 | AG64: LIM - Forecast Approval | AH64: 1083 | AI64: MFG Company | AJ64: done | AK64: 0 | AL64: 1 | AM64: 1 | AN64: 1 | AO64: 1
G65: Base UOM | K65: 1 | L65: 1 | AH65: 1084 | AI65: Material Group | AJ65: done | AK65: 2 | AL65: 1 | AM65: 1 | AN65: 1 | AO65: 1
G66: Brand Description | H66: 1 | L66: 1 | AH66: 1085 | AI66: External Material Group | AJ66: done | AK66: 2 | AL66: 1 | AM66: 1 | AN66: 1 | AO66: 1
G67: Brand Number | K67: 1 | L67: 1 | AH67: 1086 | AI67: Estimated Standard Cost | AJ67: done | AK67: 1 | AL67: 1 | AM67: 1 | AN67: 1 | AO67: 1
G68: Category # | K68: 1 | L68: 1 | AH68: 1087 | AI68: Red K Price | AJ68: done | AK68: 1 | AL68: 1 | AM68: 1 | AN68: 1 | AO68: 1
G69: Country Sold In | I69: 1 | L69: 1 | AH69: 1088 | AI69: Material Prefix | AJ69: done | AK69: 0 | AL69: 1 | AM69: 1 | AN69: 1 | AO69: 1
G70: Departure Country | J70: 1 | L70: 1 | AH70: 1089 | AI70: Transportation Group | AJ70: done | AK70: 2 | AL70: 1 | AM70: 1 | AN70: 1 | AO70: 1
G71: Estimated Standard Cost | J71: 1 | L71: 1 | AH71: 1090 | AI71: Net Case Weight | AJ71: done | AK71: 1 | AL71: 1 | AM71: 1 | AN71: 1 | AO71: 1
G72: External Material Group | I72: 1 | L72: 1 | AH72: 1091 | AI72: Metric Stated Net Pkg Wt | AJ72: done | AK72: 1 | AL72: 1 | AM72: 1 | AN72: 1 | AO72: 1
G73: Flavor | I73: 1 | L73: 1 | AH73: 1092 | AI73: Imperial Stated Net Pkg Wt | AJ73: done | AK73: 1 | AL73: 1 | AM73: 1 | AN73: 1 | AO73: 1
G74: Food Form | I74: 1 | L74: 1 | AH74: 1093 | AI74: Country Sold In | AJ74: done | AK74: 2 | AL74: 1 | AM74: 1 | AN74: 1 | AO74: 1
G75: Forecast Entry Options | J75: 1 | L75: 1 | AH75: 1094 | AI75: Location | AJ75: done | AK75: 2 | AL75: 1 | AM75: 1 | AN75: 1 | AO75: 1
G76: Generate Material Description | J76: 1 | L76: 1 | AH76: 1095 | AI76: Location Description | AJ76: done | AK76: 0 | AL76: 1 | AM76: 1 | AN76: 1 | AO76: 1
G77: Gross Weight | J77: 1 | L77: 1 | AH77: 1096 | AI77: Inbound or Outbound | AJ77: done | AK77: 1 | AL77: 1 | AM77: 1 | AN77: 1 | AO77: 1
G78: Height | J78: 1 | L78: 1 | AH78: 1097 | AI78: Kellogg Owned/Not Owned (Coman) | AJ78: done | AK78: 1 | AL78: 1 | AM78: 1 | AN78: 1 | AO78: 1
G79: Imperial Stated Net Pkg Wt | J79: 1 | L79: 1 | AH79: 1098 | AI79: Flavor | AJ79: done | AK79: 2 | AL79: 1 | AM79: 1 | AN79: 1 | AO79: 1
G80: Kellogg Owned/Not Owned (Coman) | J80: 1 | L80: 1 | AH80: 1099 | AI80: Food Form | AJ80: done | AK80: 2 | AL80: 1 | AM80: 1 | AN80: 1 | AO80: 1
G81: Language | K81: 1 | L81: 1 | AH81: 1100 | AI81: Sub-Food Form | AJ81: done | AK81: 2 | AL81: 1 | AM81: 1 | AN81: 1 | AO81: 1
G82: Length | J82: 1 | L82: 1 | AH82: 1101 | AI82: Material Segment Description | AJ82: done | AK82: 0 | AL82: 1 | AM82: 1 | AN82: 1 | AO82: 1
G83: Length (of Sugg Matl Desc) | K83: 1 | L83: 1 | AH83: 1102 | AI83: Material Segment # | AJ83: done | AK83: 0 | AL83: 1 | AM83: 1 | AN83: 1 | AO83: 1
G84: Location | I84: 1 | L84: 1 | AH84: 1103 | AI84: Category Description | AJ84: done | AK84: 0 | AL84: 1 | AM84: 1 | AN84: 1 | AO84: 1
G85: Location Description | K85: 1 | L85: 1 | AH85: 1104 | AI85: Category # | AJ85: done | AK85: 0 | AL85: 1 | AM85: 1 | AN85: 1 | AO85: 1
G86: Material Description | K86: 1 | L86: 1 | AH86: 1105 | AI86: Sub-Category Description | AJ86: done | AK86: 0 | AL86: 1 | AM86: 1 | AN86: 1 | AO86: 1
G87: Material Description Length | K87: 1 | L87: 1 | AH87: 1106 | AI87: Sub-Category # | AJ87: done | AK87: 0 | AL87: 1 | AM87: 1 | AN87: 1 | AO87: 1
G88: Material Group | I88: 1 | L88: 1 | AH88: 1107 | AI88: Brand Description | AJ88: done | AK88: 3 | AL88: 1 | AM88: 1 | AN88: 1 | AO88: 1
G89: Material Prefix | K89: 1 | L89: 1 | AH89: 1108 | AI89: Brand Number | AJ89: done | AK89: 0 | AL89: 1 | AM89: 1 | AN89: 1 | AO89: 1
G90: Material Segment # | K90: 1 | L90: 1 | AH90: 1109 | AI90: Type Description | AJ90: done | AK90: 3 | AL90: 1 | AM90: 1 | AN90: 1 | AO90: 1
G91: Material Segment Description | K91: 1 | L91: 1 | AH91: 1110 | AI91: Type # | AJ91: done | AK91: 0 | AL91: 1 | AM91: 1 | AN91: 1 | AO91: 1
G92: Metric Stated Net Pkg Wt | J92: 1 | L92: 1 | AH92: 1111 | AI92: Sub-Type Description | AJ92: done | AK92: 3 | AL92: 1 | AM92: 1 | AN92: 1 | AO92: 1
G93: MFG Company | K93: 1 | L93: 1 | AH93: 1112 | AI93: Sub-Type # | AJ93: done | AK93: 0 | AL93: 1 | AM93: 1 | AN93: 1 | AO93: 1
G94: Net Case Weight | J94: 1 | L94: 1 | AH94: 1113 | AI94: Forecast Entry Options | AJ94: hand off | AK94: 1 | AL94: 1 | AM94: 1 | AN94: 1
G95: Red K Price | J95: 1 | L95: 1 | AH95: 1114 | AI95: X | AJ95: pending | AK95: 1 | AL95: 1 | AM95: 1 | AN95: 1
G96: Sub-Category # | K96: 1 | L96: 1 | AH96: 1115 | AI96: <=> | AJ96: pending | AK96: 0 | AL96: 1 | AM96: 1 | AN96: 1
G97: Sub-Category Description | K97: 1 | L97: 1 | AH97: 1116 | AI97: Y | AJ97: pending | AK97: 1 | AL97: 1 | AM97: 1 | AN97: 1
G98: Sub-Food Form | I98: 1 | L98: 1 | AH98: 1117 | AI98: Base UOM | AJ98: pending | AK98: 0 | AL98: 1 | AM98: 1 | AN98: 1
G99: Sub-Type # | K99: 1 | L99: 1 | AH99: 1118 | AI99: Length | AJ99: pending | AK99: 1 | AL99: 1 | AM99: 1 | AN99: 1
G100: Sub-Type Description | H100: 1 | L100: 1 | AH100: 1119 | AI100: Width | AJ100: pending | AK100: 1 | AL100: 1 | AM100: 1 | AN100: 1
G101: Suggested Material Desc | I101: 1 | L101: 1 | AH101: 1120 | AI101: Height | AJ101: pending | AK101: 1 | AL101: 1 | AM101: 1 | AN101: 1
G102: Tax Category | K102: 1 | L102: 1 | AH102: 1121 | AI102: Unit of Dimension | AJ102: pending | AK102: 0 | AL102: 1 | AM102: 1 | AN102: 1
G103: Tax Classification | J103: 1 | L103: 1 | AH103: 1122 | AI103: Volume | AJ103: pending | AK103: 0 | AL103: 1 | AM103: 1 | AN103: 1
...

Sheet Complexity
A1: Complexity: ALL - Most complex sections at top, with number of fields represented in the grid per user role | R1: Complexity: 3 and 2 - AI guidance necessary: 49 unique fields | AA1: Complexity: 1 - AI guidance possibly: 186 unique fields | AJ1: Complexity: 0 - definitions only: 63 unique fields
A6: Count of field names in Trng deck | C6: owner | R6: Count of field names in Trng deck | AA6: Count of field names in Trng deck | AJ6: Count of field names in Trng deck
A7: COMPLEXITY (3..1,0) 3-high 2-med 1-low 0-autofill | B7: Training Section | C7: CA Finance Tax | D7: Category Finance | E7: Data Integrity | F7: EPM Finance | G7: LIM | H7: Masterfiles | I7: Nutrition Labeling | J7: Packaging Tech | K7: R&D Quality | L7: Requestor | M7: Grand Total | R7: COMPLEXITY (3..1,0) 3-high 2-med 1-low 0-autofill | S7: field names in Trng deck | T7: owner | U7: types of fields | V7: section name | W7: Total | AA7: COMPLEXITY (3..1,0) 3-high 2-med 1-low 0-autofill | AB7: field names in Trng deck | AC7: owner | AD7: types of fields | AE7: section name | AF7: Total | AJ7: COMPLEXITY (3..1,0) 3-high 2-med 1-low 0-autofill | AK7: field names in Trng deck | AL7: owner | AM7: types of fields | AN7: section name | AO7: Total
A8: 3 | B8: LIM - Forecast Approval | G8: 3 | M8: 3 | R8: 3 | S8: 1. Validate Retail material Number (button) | T8: Requestor | U8: script button | V8: DTC Product Details | W8: 1 | AA8: 1 | AB8: 1st Arrival Date | AC8: Requestor | AD8: date | AE8: Product Details | AF8: 1 | AJ8: 0 | AK8: <=> | AL8: LIM | AM8: autofill | AN8: Alternate Units of Measure | AO8: 1
B9: Nutrition Labeling - Update | I9: 4 | M9: 4 | S9: 2. Import Alt UOM Table (button) | T9: Requestor | U9: script button | V9: DTC Product Details | W9: 1 | AB9: 1st Ship Date | AC9: Requestor | AD9: date | AE9: Product Details | AF9: 1 | AK9: 1st Arrival Date (Day) | AL9: Requestor | AM9: autofill | AN9: Product Details | AO9: 1
B10: Requestor - Project Initiation | L10: 7 | M10: 7 | S10: Brand Description | T10: LIM | U10: dd: reference list: PRL: Product Hierarchy Brand | V10: Product Hierarchy-Brand | W10: 1 | AB10: Approved to sell via Ecommerce | AC10: Requestor | AD10: dd: YES, NO | AE10: Product Determination Questions | AF10: 1 | AK10: 1st Ship Date (Day) | AL10: Requestor | AM10: autofill | AN10: Product Details | AO10: 1
B11: Requestor - Req Launch DTC | L11: 5 | M11: 5 | S11: Case Count | T11: Requestor | U11: free form | V11: Stated Weights/Case Count | W11: 1 | AB11: Assign Plant | AC11: Masterfiles | AD11: checkbox | AE11: VAS BOM Plant Assingments (CS07) | AF11: 1 | AK11: Alt UOM | AL11: Masterfiles | AM11: autofill | AN11: UPC, K#, and GTIN Codes | AO11: 1
A12: 3 Total | G12: 3 | I12: 4 | L12: 12 | M12: 19 | S12: DTC Form Launched (button) | T12: Requestor | U12: script button | V12: DTC Launch Validation | W12: 1 | AB12: Base Material | AC12: Requestor | AD12: free form | AE12: BOM Setup (VAS) | AF12: 1 | AK12: Alternate Category | AL12: Requestor | AM12: autofill | AN12: Alternate Hierarchy | AO12: 1
A13: 2 | B13: LIM - Forecast Approval | G13: 9 | M13: 9 | S13: Form Type | T13: Requestor | U13: dd: CASE, DISPLAY, WIP | V13: Product Setup | W13: 1 | AB13: Business Unit | AC13: Requestor | AD13: dd: reference list: PRL: Business Unit | AE13: Product Details | AF13: 1 | AK13: Alternate Market Segment | AL13: Requestor | AM13: autofill | AN13: Alternate Hierarchy | AO13: 1
B14: LIM - Initial Review | G14: 1 | M14: 1 | S14: Launch Later (No Save) (button) | T14: Requestor | U14: script button | V14: DTC Launch Validation | W14: 1 | AB14: Calculation Check | AC14: Requestor | AD14: free form | AE14: Variety Pack 0200 BOM Setup | AF14: 1 | AK14: Alternate Sub-Category | AL14: Requestor | AM14: autofill | AN14: Alternate Hierarchy | AO14: 1
B15: LIM - Launch | G15: 1 | M15: 1 | S15: Like SKU / Reference Material Number | T15: Requestor | U15: SAP db list | V15: Reference Material | W15: 1 | AB15: Case | AC15: Nutrition Labeling | AD15: free form | AE15: Net Wt. Statement for Graphics | AF15: 1 | AK15: Base UOM | AL15: LIM | AM15: autofill | AN15: Alternate Units of Measure | AO15: 1
B16: LIM - Update | G16: 1 | M16: 1 | S16: Metric Stated Net Package Weight (g) | T16: Nutrition Labeling | U16: calculation | V16: Food Weights in grams/ounces | W16: 1 | AB16: Category Finance | AC16: LIM | AD16: dd: user roles | AE16: Person Responsible | AF16: 1 | AK16: Brand Number | AL16: LIM | AM16: dd: reference list: PRL: Product Hierarchy Brand | AN16: Product Hierarchy-Brand | AO16: 1
B17: Requestor - Project Initiation | L17: 20 | M17: 20 | S17: Metric Stated Net Pouch Weight (g) | T17: Nutrition Labeling | U17: calculation | V17: Food Weights in grams/ounces | W17: 1 | AB17: Chocolate Enrobed | AC17: LIM | AD17: dd: YES, NO | AE17: General Product Data | AF17: 1 | AK17: Business Unit for Promo | AL17: Requestor | AM17: dd: reference list: PRL: Business Unit for Promo | AN17: Promotion | AO17: 1
B18: Requestor - Req Launch DTC | L18: 1 | M18: 1 | S18: Product Country | T18: Requestor | U18: dd: reference list: PRODUCT_COUNTRY.XLSX | V18: Product Setup | W18: 1 | AB18: Clamp Pressure | AC18: Packaging Tech | AD18: dd: reference list: PRL: Clamp Pressure | AE18: Packaging Details | AF18: 1 | AK18: Category # | AL18: LIM | AM18: dd: reference list: PRL: Product Hierarchy Market Category | AN18: Product Hierarchy-Brand | AO18: 1
B19: Requestor Update | L19: 4 | M19: 4 | S19: Product Sub Type | T19: Requestor | U19: dd: reference list: PRODUCT_SETUP_TYPE.XLSX, Setup_Qualifier column | V19: Product Setup | W19: 1 | AB19: Component | AC19: Masterfiles | AD19: free form | AE19: Packaging - Merge with BOM | AF19: 1 | AK19: Dim Details | AL19: Packaging Tech | AM19: autofill | AN19: Alternate Units of Measure | AO19: 1
A20: 2 Total | G20: 12 | L20: 25 | M20: 37 | S20: Product Type | T20: Requestor | U20: dd: reference list: PRODUCT_SETUP_TYPE.XLSX, Setup_Type column | V20: Product Setup | W20: 1 | AB20: Component Description | AC20: Packaging Tech | AD20: free form | AE20: Packaging Components | AF20: 1 | AK20: Dim/Gross Wght Req | AL20: Packaging Tech | AM20: autofill | AN20: Alternate Units of Measure | AO20: 1
A21: 1 | B21: CA Finance Tax | C21: 2 | M21: 2 | S21: Save and Route (button) | T21: Requestor | U21: script button | V21: DTC Product Details | W21: 1 | AB21: Component Pkgs Per Case | AC21: Requestor | AD21: free form | AE21: BOM Setup (VAS) | AF21: 1 | AK21: Gross Wght Dtls | AL21: Packaging Tech | AM21: autofill | AN21: Alternate Units of Measure | AO21: 1
B22: Category Finance - update | D22: 1 | M22: 1 | S22: Stated Net Package Weight (oz) | T22: Nutrition Labeling | U22: calculation | V22: Food Weights in grams/ounces | W22: 1 | AB22: Components Per Variety Pack | AC22: Requestor | AD22: free form | AE22: Variety Pack 0200 BOM Setup | AF22: 1 | AK22: GTIN Prefix | AL22: Masterfiles | AM22: autofill | AN22: UPC, K#, and GTIN Codes | AO22: 1
B23: Data Integrity (DI) - Hierarchy | E23: 1 | M23: 1 | S23: Stated Net Pouch Weight (oz) | T23: Nutrition Labeling | U23: calculation | V23: Food Weights in grams/ounces | W23: 1 | AB23: Conversion Case Code | AC23: Requestor | AD23: free form | AE23: Product Details | AF23: 1 | AK23: Language | AL23: LIM | AM23: dd: reference list: DESCRIPTION_LANGUAGES.XLSX | AN23: Material Description(s) | AO23: 1
B24: Data Integrity (DI) - Review | E24: 1 | M24: 1 | S24: Sub-Type Description | T24: LIM | U24: dd: reference list: PRL: Product Hierarchy Sub-Type | V24: Product Hierarchy-Brand | W24: 1 | AB24: Conversion Date | AC24: Requestor | AD24: date | AE24: Product Details | AF24: 1 | AK24: Location Description | AL24: LIM | AM24: autofill | AN24: Forecast SKU Requirements | AO24: 1
B25: EPM Finance - Update | F25: 2 | M25: 2 | S25: Type Description | T25: LIM | U25: dd: reference list: PRL: Product Hierarchy Type | V25: Product Hierarchy-Brand | W25: 1 | AB25: Country | AC25: Requestor | AD25: dd: reference list: COUNTRY (not in RDL or PRL) | AE25: DTC Product Details | AF25: 1 | AK25: Material Description | AL25: LIM | AM25: autofill | AN25: Material Description(s) | AO25: 1
B26: LIM - Approval/NIF Dashboard | G26: 2 | M26: 2 | S26: Is this Non Sellable FERT WIP | T26: Requestor | U26: dd: YES, NO | V26: Product Determination Questions | W26: 1 | AB26: Country of Origin | AC26: LIM | AD26: dd: reference list: PRL: Country of Origin | AE26: General Product Data | AF26: 1 | AK26: Material Description Length | AL26: LIM | AM26: autofill | AN26: Material Description(s) | AO26: 1
B27: LIM - Forecast Approval | G27: 17 | M27: 17 | R27: 2 | S27: Additional Packaging for Launch | T27: Requestor | U27: dd: reference list: ADDITIONAL_PACKAGING_LAUNCH.XLSX | V27: Special Packaging Requirements | W27: 1 | AB27: Create Forecast Material | AC27: Masterfiles | AD27: button | AE27: Forecast Scripts | AF27: 1 | AK27: Material Group 1 | AL27: Requestor | AM27: dd: reference list: PRL: Material Group 1 | AN27: Product Details | AO27: 1
B28: LIM - Initial Review | G28: 14 | M28: 14 | S28: Brief Product Description | T28: Requestor | U28: free form | V28: Product Setup | W28: 1 | AB28: Create Plant Extension | AC28: Masterfiles | AD28: checkbox | AE28: Plant Extension Selection | AF28: 1 | AK28: Material Prefix | AL28: LIM | AM28: autofill | AN28: Forecast SKU Requirements | AO28: 1
B29: LIM - LIM REPORT | G29: 1 | M29: 1 | S29: Case Count Status | T29: Requestor | U29: dd: ESTIMATED, FINALIZED | V29: Stated Weights/Case Count | W29: 1 | AB29: Data Integrity | AC29: LIM | AD29: dd: user roles | AE29: Person Responsible | AF29: 1 | AK29: Material Segment # | AL29: LIM | AM29: dd: reference list: PRL: Product Hierarchy Market Segment | AN29: Product Hierarchy-Brand | AO29: 1
B30: LIM - Update | G30: 6 | M30: 6 | S30: Choose File | T30: Requestor | U30: dd: directory | V30: Attachments | W30: 1 | AB30: Data Integrity (CA) | AC30: LIM | AD30: dd: user roles | AE30: Person Responsible | AF30: 1 | AK30: Material Segment Description | AL30: LIM | AM30: dd: reference list: PRL: Product Hierarchy Market Segment | AN30: Product Hierarchy-Brand | AO30: 1
B31: LIM Launch - Update | G31: 1 | M31: 1 | S31: Compressed UPC Existing | T31: Requestor | U31: dd: NO, POUCH, PACKAGE, BOTH | V31: Existing Printed Material Codes | W31: 1 | AB31: Defect Group | AC31: R&D Quality | AD31: dd: reference list: PRL: Defect Group | AE31: R & D Quality | AF31: 1 | AK31: MFG Company | AL31: LIM | AM31: dd: reference list: PRL: Manufacturing Company | AN31: Forecast SKU Requirements | AO31: 1
B32: Masterfiles - Approval | H32: 15 | M32: 15 | S32: Country Sold In | T32: LIM | U32: dd: reference list: COUNTRY (not in RDL or PRL) | V32: Forecast SKU Requirements | W32: 1 | AB32: Departure Country | AC32: LIM | AD32: dd: reference list: COUNTRY (not in RDL or PRL) | AE32: Taxes | AF32: 1 | AK32: New Distribution Channel | AL32: Masterfiles | AM32: autofill | AN32: Sales Organization Extension | AO32: 1
B33: Masterfiles - Create Plant Extensions, pricing & BOM's | H33: 15 | M33: 15 | S33: Designated Customer Name | T33: Requestor | U33: dd: reference list: PRL: Designated Customer Name | V33: Product Determination Questions | W33: 1 | AB33: Dieline | AC33: Packaging Tech | AD33: free form | AE33: Packaging Components | AF33: 1 | AK33: New Sales Organization | AL33: Masterfiles | AM33: autofill | AN33: Sales Organization Extension | AO33: 1
B34: Masterfiles - Get Codes | H34: 6 | M34: 6 | S34: External Material Group | T34: LIM | U34: dd: reference list: PRL: External Material Group | V34: Forecast SKU Requirements | W34: 1 | AB34: Display Vehicle | AC34: LIM | AD34: dd: reference list: PRL: Display Vehicle | AE34: General Product Data | AF34: 1 | AK34: Package Size | AL34: LIM | AM34: autofill | AN34: General Product Data | AO34: 1
B35: Masterfiles - Get Codes Forecast | H35: 2 | M35: 2 | S35: Flavor | T35: LIM | U35: dd: reference list: PRL: Flavor | V35: Fields Used for Material Description | W35: 1 | AB35: Distribution Methods | AC35: Masterfiles | AD35: dd: reference list: DISTRIBUTION_METHODS.XLSX | AE35: Review - Derived Values | AF35: 1 | AK35: Package Size UOM | AL35: LIM | AM35: autofill | AN35: General Product Data | AO35: 1
B36: Nutrition Labeling - Update | I36: 20 | M36: 20 | S36: Food Form | T36: LIM | U36: dd: reference list: PRL: Food Form | V36: Fields Used for Material Description | W36: 1 | AB36: DTC Package Price | AC36: Masterfiles | AD36: free form | AE36: DTC Questions | AF36: 1 | AK36: Plant Number List | AL36: Masterfiles | AM36: autofill | AN36: ZMMU_PLANT_Query | AO36: 1
B37: Packaging Tech - Update | J37: 15 | M37: 15 | S37: List Any Existing Knumbers That Will Be Used | T37: Requestor | U37: free form | V37: List Existing K Numbers | W37: 1 | AB37: EPM Finance | AC37: LIM | AD37: dd: user roles | AE37: Person Responsible | AF37: 1 | AK37: Pouch Size | AL37: LIM | AM37: autofill | AN37: General Product Data | AO37: 1
B38: R&D Quality - Update | K38: 4 | M38: 4 | S38: List Existing Export UPC Codes | T38: Requestor | U38: free form | V38: Product Determination Questions | W38: 1 | AB38: Estimated Standard Cost | AC38: LIM | AD38: free form | AE38: Forecast SKU Requirements | AF38: 1 | AK38: Pouch Size UOM | AL38: LIM | AM38: autofill | AN38: General Product Data | AO38: 1
B39: Requestor - Project Initiation | H39: 1 | L39: 21 | M39: 22 | S39: List Existing Private UPCs | T39: Requestor | U39: free form | V39: Product Determination Questions | W39: 1 | AB39: FERT Type | AC39: Requestor | AD39: dd: reference list: PRL: FERT Type | AE39: Product Details | AF39: 1 | AK39: Pricing Validity Date | AL39: Requestor | AM39: autofill | AN39: Product Details | AO39: 1
B40: Requestor - Req Launch DTC | L40: 3 | M40: 3 | S40: List UPC Codes If Already Assigned | T40: Requestor | U40: free form | V40: Existing Printed Material Codes | W40: 1 | AB40: Final Red K List Price (cs) | AC40: Category Finance | AD40: free form | AE40: Pricing | AF40: 1 | AK40: Pringles Can Size | AL40: Packaging Tech | AM40: autofill | AN40: Packaging Details | AO40: 1
B41: Requestor Update | L41: 38 | M41: 38 | S41: Location | T41: LIM | U41: dd: reference list: ZMMU table (not in RDL or PRL) | V41: Forecast SKU Requirements | W41: 1 | AB41: Food Count (Bars, Waffles, PT, Shakes, RKT) | AC41: Requestor | AD41: free form | AE41: Values used to determine material description | AF41: 1 | AK41: Promo Short Description | AL41: Requestor | AM41: dd: reference list: PRL: Promotion | AN41: Promotion | AO41: 1
A42: 1 Total | C42: 2 | D42: 1 | E42: 2 | F42: 2 | G42: 41 | H42: 39 | I42: 20 | J42: 15 | K42: 4 | L42: 62 | M42: 188 | S42: Material Group | T42: LIM | U42: dd: reference list: PRL: Material Group | V42: Forecast SKU Requirements | W42: 1 | AB42: Forecast Entry Options | AC42: LIM | AD42: radio button: DEFAULTS, ESTIMATED, ACTUALS | AE42: Alternate Units of Measure | AF42: 1 | AK42: Remarket Date | AL42: Requestor | AM42: autofill | AN42: Product Details | AO42: 1
A43: 0 | B43: LIM - Forecast Approval | G43: 23 | M43: 23 | S43: Material Prefix Description | T43: Requestor | U43: dd: reference list: MATERIAL_PREFIX.XLSX | V43: Other UPC Requirements | W43: 1 | AB43: Generate Material Description | AC43: LIM | AD43: button | AE43: Material Description(s) | AF43: 1 | AK43: Requestor | AL43: Requestor | AM43: dd: user roles | AN43: Person Responsible | AO43: 1
B44: LIM - Update | G44: 4 | M44: 4 | S44: Package K Number | T44: Requestor | U44: free form | V44: Existing Printed Material Codes | W44: 1 | AB44: Grams per piece | AC44: Nutrition Labeling | AD44: free form | AE44: Food Weights | AF44: 1 | AK44: Requestor Date | AL44: Requestor | AM44: autofill | AN44: Requestor Initiate | AO44: 1
B45: Masterfiles - Approval | H45: 3 | M45: 3 | S45: Package UPC Code | T45: Requestor | U45: free form | V45: Existing Printed Material Codes | W45: 1 | AB45: Gross Pkg Weight | AC45: Requestor | AD45: free form | AE45: BOM Setup (VAS) | AF45: 1 | AK45: Requestor Email | AL45: Requestor | AM45: autofill | AN45: Requestor Initiate | AO45: 1
B46: Masterfiles - Create Plant Extensions, pricing & BOM's | H46: 2 | M46: 2 | S46: Pouch K Number | T46: Requestor | U46: free form | V46: Existing Printed Material Codes | W46: 1 | AB46: Gross Weight | AC46: LIM | AD46: free form | AE46: Alternate Units of Measure | AF46: 1 | AK46: Requestor Name | AL46: Requestor | AM46: autofill | AN46: Requestor Initiate | AO46: 1
B47: Masterfiles - Get Codes | H47: 7 | M47: 7 | S47: Pouch UPC Code | T47: Requestor | U47: free form | V47: Existing Printed Material Codes | W47: 1 | AB47: Gross Wt UOM | AC47: Requestor | AD47: dd: GM, OZ | AE47: BOM Setup (VAS) | AF47: 1 | AK47: Royalty Licenser | AL47: Requestor | AM47: dd: reference list: PRL: Royalty Licenser | AN47: Promotion | AO47: 1
B48: Packaging Tech - Update | J48: 4 | M48: 4 | S48: Private Label Name | T48: Requestor | U48: dd: reference list: PRL: Private Label Customers | V48: Product Determination Questions | W48: 1 | AB48: GTIN Number | AC48: Masterfiles | AD48: free form | AE48: UPC, K#, and GTIN Codes | AF48: 1 | AK48: Royalty Licenser Abbreviation | AL48: Requestor | AM48: dd: reference list: PRL: Royalty Licenser | AN48: Promotion | AO48: 1
B49: Requestor - Project Initiation | L49: 6 | M49: 6 | S49: Project Type | T49: Requestor | U49: dd: KUBIC, PDR, PWR, SCR | V49: Product Setup | W49: 1 | AB49: Handling Platform Type | AC49: Packaging Tech | AD49: dd: reference list: PRL: Handling Platform Type | AE49: Packaging Details | AF49: 1 | AK49: Sub-Category # | AL49: LIM | AM49: dd: reference list: PRL: Product Hierarchy Market Sub-Category | AN49: Product Hierarchy-Brand | AO49: 1
B50: Requestor Update | G50: 1 | L50: 12 | M50: 13 | S50: Stated Weight Applicable For | T50: Requestor | U50: dd: PACKAGE, INNER ITEM/POUCH | V50: Stated Weights/Case Count | W50: 1 | AB50: Height | AC50: LIM | AD50: free form | AE50: Alternate Units of Measure | AF50: 1 | AK50: Sub-Category Description | AL50: LIM | AM50: dd: reference list: PRL: Product Hierarchy Market Sub-Category | AN50: Product Hierarchy-Brand | AO50: 1
B51: ZNIF Dashboard - view only | G51: 1 | M51: 1 | S51: Stated Weight Status | T51: Requestor | U51: dd: ESTIMATED, FINALIZED | V51: Stated Weights/Case Count | W51: 1 | AB51: Imperial Stated Net Pkg Wt | AC51: LIM | AD51: free form | AE51: Forecast SKU Requirements | AF51: 1 | AK51: Sub-Type # | AL51: LIM | AM51: dd: reference list: PRL: Product Hierarchy Sub-Type | AN51: Product Hierarchy-Brand | AO51: 1
A52: 0 Total | G52: 29 | H52: 12 | J52: 4 | L52: 18 | M52: 63 | S52: Sub-Food Form | T52: LIM | U52: dd: reference list: PRL: Sub Food Form | V52: Fields Used for Material Description | W52: 1 | AB52: Kellogg Owned/Not Owned (Coman) | AC52: LIM | AD52: dd: KELLOGG OWNED, NOT OWNED (COMAN) | AE52: Forecast SKU Requirements | AF52: 1 | AK52: Tax Category | AL52: LIM | AM52: autofill | AN52: Taxes | AO52: 1
A53: Grand Total | C53: 2 | D53: 1 | E53: 2 | F53: 2 | G53: 85 | H53: 51 | I53: 24 | J53: 19 | K53: 4 | L53: 117 | M53: 307 | S53: Suggested Material Desc | T53: LIM | U53: free form | V53: Material Description(s) | W53: 1 | AB53: Length | AC53: LIM | AD53: free form | AE53: Alternate Units of Measure | AF53: 1 | AK53: Type # | AL53: LIM | AM53: dd: reference list: PRL: Product Hierarchy Type | AN53: Product Hierarchy-Brand | AO53: 1
S54: Trade Channel | T54: Requestor | U54: dd: reference list: PRL: Trade Channel | V54: Trade Channel & Country Sold In | W54: 1 | AB54: LIM | AC54: Requestor | AD54: dd: user roles | AE54: Person Responsible | AF54: 1 | AK54: Unit of Dimension | AL54: LIM | AM54: autofill | AN54: Alternate Units of Measure | AO54: 1
S55: Transportation Group | T55: LIM | U55: dd: reference list: PRL: Transportation Group | V55: Forecast SKU Requirements | W55: 1 | AB55: LIM Update | AC55: Masterfiles | AD55: checkbox | AE55: Masterfiles Approval Returns | AF55: 1 | AK55: Version | AL55: Requestor | AM55: autofill | AN55: Requestor Initiate | AO55: 1
S56: VAS Plant Groups | T56: LIM | U56: dd: reference list: VAS_PLANTS.XLSX | V56: Manufacturing Locations | W56: 1 | AB56: List Price (Red K) | AC56: Requestor | AD56: free form | AE56: BOM Setup (VAS) | AF56: 1 | AK56: Volume | AL56: LIM | AM56: autofill | AN56: Alternate Units of Measure | AO56: 1
S57: Brief Project Overview and Technical Notes | T57: Requestor | U57: free form | V57: Product Setup | W57: 1 | AB57: Manually Execute Scripts | AC57: Masterfiles | AD57: expand group with more buttons | AE57: Forecast Scripts | AF57: 1 | AK57: Volume Unit | AL57: LIM | AM57: autofill | AN57: Alternate Units of Measure | AO57: 1
S58: Promo End Date | T58: Requestor | U58: date | V58: Product Details | W58: 1 | AB58: Masterfiles | AC58: LIM | AD58: dd: user roles | AE58: Person Responsible | AF58: 1 | AK58: Weight Unit | AL58: LIM | AM58: autofill | AN58: Alternate Units of Measure | AO58: 1
S59: Pack Size | T59: Requestor | U59: dd: reference list: PRL: Pack Size (CLUB PACK, RETAIL, SINGLE SERVE) | V59: Product Details | W59: 1 | AB59: Material Freight Group | AC59: LIM | AD59: dd: reference list: PRL: Material Freight Group | AE59: General Product Data | AF59: 1 | AK59: statuses of the workflow (X, R, C…) | AL59: LIM | AM59: autofill | AN59: NIF Dashboard | AO59: 1
S60: Is a Compressed UPC Required for the Components | T60: Requestor | U60: dd: NO, POUCH, PACKAGE, BOTH | V60: Other UPC Requirements | W60: 1 | AB60: Material Group 5 | AC60: CA Finance Tax | AD60: dd: reference list: PRL: Material Group 5 | AE60: Material Group/Tax Data | AF60: 1 | AK60: Length (of Sugg Matl Desc) | AL60: LIM | AM60: autofill | AN60: Material Description(s) | AO60: 1
S61: Supply Chain Budget Forecast SKU | T61: LIM | U61: dd: YES, NO | V61: Product Setup | W61: 1 | AB61: Material Number | AC61: Masterfiles | AD61: free form | AE61: Material Number | AF61: 1 | AK61: Material Number (Sales Org Extension) | AL61: Masterfiles | AM61: autofill | AN61: Sales Organization Extension | AO61: 1
S62: VAS | T62: LIM | U62: dd: YES, NO | V62: Product Setup | W62: 1 | AB62: Material Type | AC62: Masterfiles | AD62: dd: reference list | AE62: ZMMU_PLANT_Query | AF62: 1 | AK62: Ct | AL62: Masterfiles | AM62: autofill | AN62: UPC, K#, and GTIN Codes | AO62: 1
S63: Will this item be sold at the package level Direct To Consumer (DTC) | T63: Requestor | U63: dd: YES, NO | V63: Product Hierarchy-Brand | W63: 1 | AB63: Max Storage Period/Ship Life | AC63: R&D Quality | AD63: free form | AE63: Product Details | AF63: 1 | AK63: Material Description (BOM Setup) | AL63: LIM | AM63: autofill | AN63: BOM Setup (VAS) | AO63: 1
R64: Grand Total | W64: 56 | AB64: Metric Stated Net Package Weight (g/kg) | AC64: Nutrition Labeling | AD64: free form | AE64: Food Weights | AF64: 1 | AK64: (12 checkboxes) | AL64: Masterfiles | AM64: checkbox | AN64: Masterfiles Manual Checklist | AO64: 1
AB65: Metric Stated Net Package Weight Unit | AC65: Nutrition Labeling | AD65: autofill | AE65: Food Weights | AF65: 1 | AK65: Category Description | AL65: LIM | AM65: dd: reference list: PRL: Product Hierarchy Market Category | AN65: Product Hierarchy-Brand | AO65: 1
AB66: Metric Stated Net Pkg Wt | AC66: LIM | AD66: free form | AE66: Forecast SKU Requirements | AF66: 1 | AK66: Unique UPC | AL66: Requestor | AM66: autofill | AN66: UPC Table | AO66: 1
AB67: Metric Stated Net Pouch Size Unit | AC67: Nutrition Labeling | AD67: autofill | AE67: Food Weights | AF67: 1 | AK67: UPC Required | AL67: Masterfiles | AM67: autofill | AN67: UPC, K#, and GTIN Codes | AO67: 1
AB68: Metric Stated Net Pouch Weight (g/kg) | AC68: Nutrition Labeling | AD68: free form | AE68: Food Weights | AF68: 1 | AK68: Unique or Same UPC | AL68: Masterfiles | AM68: autofill | AN68: UPC, K#, and GTIN Codes | AO68: 1
AB69: Multi Defect Group | AC69: R&D Quality | AD69: dd: YES, NO | AE69: R & D Quality | AF69: 1 | AK69: GTIN Required | AL69: Masterfiles | AM69: autofill | AN69: UPC, K#, and GTIN Codes | AO69: 1
AB70: Net Case Weight | AC70: LIM | AD70: free form | AE70: Forecast SKU Requirements | AF70: 1 | AK70: Unique or Same GTIN | AL70: Masterfiles | AM70: autofill | AN70: UPC, K#, and GTIN Codes | AO70: 1
AB71: Net Pkg Weight | AC71: Requestor | AD71: free form | AE71: BOM Setup (VAS) | AF71: 1 | AJ71: Grand Total | AO71: 63
AB72: Net Weight | AC72: Packaging Tech | AD72: free form | AE72: Net Weight if no Nutrition Labeling | AF72: 1
AB73: Net Wt UOM | AC73: Requestor | AD73: dd: GM, OZ | AE73: BOM Setup (VAS) | AF73: 1
AB74: Newly Assigned Plant | AC74: Masterfiles | AD74: free form | AE74: VAS BOM Plant Assingments (CS07) | AF74: 1
AB75: Number of Cases Required | AC75: Requestor | AD75: free form | AE75: BOM Setup (VAS) | AF75: 1
AB76: Number Required per UOM | AC76: Packaging Tech | AD76: free form | AE76: Packaging Components | AF76: 1
AB77: Nutrition Labeling | AC77: LIM | AD77: dd: user roles | AE77: Person Responsible | AF77: 1
AB78: Original BOM Plant | AC78: Masterfiles | AD78: free form | AE78: Packaging - Merge with BOM | AF78: 1
AB79: Original Plant | AC79: Masterfiles | AD79: free form | AE79: VAS BOM Plant Assingments (CS07) | AF79: 1
AB80: OTG Type | AC80: Requestor | AD80: dd: reference list: PRL: OTG Type | AE80: Product Details | AF80: 1
AB81: Pack Type Use | AC81: Requestor | AD81: dd: reference list: PRL: Pack Type Use | AE81: Product Details | AF81: 1
AB82: Package | AC82: Nutrition Labeling | AD82: free form | AE82: Net Wt. Statement for Graphics | AF82: 1
AB83: Package Individual Unit Size | AC83: Nutrition Labeling | AD83: free form | AE83: Data Sync Requirements - Nutrition Labeling | AF83: 1
... AB195: Did you submit DTC Form | AC195: Requestor | AD195: dd: YES, NO | AE195: DTC Launch Validation | AF195: 1
AA196: Grand Total | AF196: 188

Sheet marketing questions
C1: These are the questions that Marketing has on their end around Brand and Type:
A2: new Brand | B2: If this is a new Brand requiring a separate Profit Center and separate P&L from existing Brands, then it requires a new Brand, which could take 3 weeks to create. Contact Juliana Hurtado and Christa Clapper. | C2: - Is this a new Brand, requiring a separate Profit Center and separate P&L from existing Brands?
C3: o Yes - If so, it requires a different or new Brand, which could take 3 weeks to create. Contact Juliana Hurtado and Christa Clapper.
A4: new Planning in TPM, or new Type | B4: If this item will be planned in TPM separately from existing products, then it requires a new Type, which could take 3 weeks to create. Contact Supply Chain Data Governance at SCDataGov@kellanova.com. | C4: o No - Will this be planned in TPM separately from existing products?
C5: o Yes - If so, it requires a different or new Type, which could take 3 weeks to create. Contact Supply Chain Data Governance at SCDataGov@kellanova.com.
A6: new Food Form | B6: If this item is a new Food Form that will fall under an existing Brand, then it requires a new Type, which could take 3 weeks to create. Contact Supply Chain Data Governance at SCDataGov@kellanova.com. | C6: o No - Is this a new Food Form that will fall under an existing Brand?
C7: § Yes - It requires a different or new Type, which could take 3 weeks to create. Contact Supply Chain Data Governance at SCDataGov@kellanova.com.
A8: new Size | B8: If this item is a new Size, then it may require a new Type, which could take 3 weeks to create. Contact Commercial Enablement. | C8: § No - Is this a new Size?
C9: § Yes - It may require a different or new Type, which could take 3 weeks to create. - contact Commercial Enablement
A10: new Package Price, or new Price | B10: If this item is a new Package Price, then it may require a new Type, which could take 3 weeks to create. Contact Commercial Enablement. | C10: § No - Is this a new package price?
C11: § Yes - It may require new Type. - contact Commercial Enablement
A12: new Sub Brand, or new Sub-Brand | B12: If this item is a new Sub Brand, then submit a KNA Request Product Value form in Evolve. | C12: § No - Is this a new Sub Brand?
C13: § Yes - submit a KNA Request Product Value form in Evolve
A14: Brand | B14: If this item is On The Go/Convenience Snack Packs, then ensure selection of Brand name during Requestor Update task includes OTG (EX: Caddies Cheez-It OTG). | C14: § No - OTG (On The Go) is usually in a different Brand hierarchy than core. Is this an OTG item?
C15: § Yes - Ensure selection of Brand name during Requestor Update task includes OTG (example: Caddies Cheez-It OTG)
C16: § No - Ensure selection of Brand name during Requestor Update task does not include OTG
C19: Is this a CSP (OTG) item?
A20: Brand | B20: If this item is On The Go/Convenience Snack Packs, then ensure selection of Brand name during Requestor Update task includes OTG (EX: Caddies Cheez-It OTG). | C20: § Yes - Ensure selection of Brand name during Requestor Update task includes OTG (example: Caddies Cheez-It OTG)
C21: § No - Ensure selection of Brand name during Requestor Update task does not include OTG
A22: new Brand | B22: If this is a new Brand requiring a separate Profit Center and separate P&L from existing Brands, then it requires a new Brand, which could take 3 weeks to create. Contact Juliana Hurtado and Christa Clapper. | C22: Is this a new Brand requiring a separate Profit Center and separate P&L from existing Brands?
C23: o Yes - If so, it requires a different or new Brand, which could take 3 weeks to create. Contact Juliana Hurtado and Christa Clapper.
A24: new Planning in TPM, or new Type | B24: If this item will be planned in TPM separately from existing products, then it requires a new Type, which could take 3 weeks to create. Contact Supply Chain Data Governance at SCDataGov@kellanova.com. | C24: o No - Will this be planned in TPM separately from existing products? Refer to the PH Report to review where current items are assigned.
C25: o Yes - If so, it requires a different or new Type, which could take 3 weeks to create. Contact Supply Chain Data Governance at SCDataGov@kellanova.com.
A26: new Food Form | B26: If this item is a new Food Form that will fall under an existing Brand, then it requires a new Type, which could take 3 weeks to create. Contact Supply Chain Data Governance at SCDataGov@kellanova.com. | C26: o No - Is this a new Food Form that will fall under an existing Brand?
C27: § Yes - It requires a different or new Type, which could take 3 weeks to create. Contact Supply Chain Data Governance at SCDataGov@kellanova.com.
A28: new Size | B28: If this item is a new Size, then it may require a new Type, which could take 3 weeks to create. Contact Commercial Enablement. | C28: § No - Is this a new Size?
C29: § Yes - It may require a different or new Type, which could take 3 weeks to create. - contact Commercial Enablement
A30: new Package Price, or new Price | B30: If this item is a new Package Price, then it may require a new Type, which could take 3 weeks to create. Contact Commercial Enablement. | C30: § No - Is this a new package price?
C31: § Yes - It may require new Type. - contact Commercial Enablement
A32: new Sub Brand, or new Sub-Brand | B32: If this item is a new Sub Brand, then submit a KNA Request Product Value form in Evolve. | C32: § No - Is this a new Sub Brand?
C33: § Yes - submit a KNA Request Product Value form in Evolve
A34: Brand | B34: If this item is On The Go/Convenience Snack Packs, then ensure selection of Brand name during Requestor Update task includes OTG (EX: Caddies Cheez-It OTG). | C34: § No - done

Sheet LOV
F4: Business Rule gathering
B5: Training Section | C5: Trng Sectn # | D5: Trng Sectn Priority | F5: Sprint | G5: Week | H5: orig start | I5: orig end | J5: actual start | K5: actual end | L5: Week Beginning Date
B6: Requestor - Project Initiation | C6: 10 | D6: AA | F6: A | G6: WK1 | H6: 45916 | I6: 45919 | J6: 45916 | K6: 45919 | L6: 45916
B7: LIM - Forecast Approval | C7: 50 | D7: BB | F7: B | G7: WK1 | H7: 45922 | I7: 45926 | J7: 45919 | K7: 45922 | L7: 45916
B8: Requestor Update | C8: 100 | D8: CC | F8: C | G8: WK2 | H8: 45929 | I8: 45933 | J8: 45922 | K8: 45922 | L8: 45922
B9: Requestor - Req Launch DTC | C9: 230 | D9: CC | F9: D | G9: WK2 | H9: 45936 | I9: 45940 | J9: 45922 | K9: 45923 | L9: 45922
B10: LIM - Initial Review | C10: 20 | D10: DD | F10: E | G10: WK2 | H10: 45923 | I10: 45926 | J10: 45922 | L10: 45922
B11: LIM - Launch | C11: 70 | D11: DD | F11: F | G11: WK3 | H11: 45929 | I11: 45933 | L11: 45929
B12: LIM Launch - Update | C12: 80 | D12: DD | F12: G | G12: WK4 | H12: 45936 | I12: 45940 | L12: 45936 | N12: Bev OOO on 10/6/25
B13: LIM - Update | C13: 110 | D13: DD | F13: H | G13: WK5 | H13: 45943 | I13: 45947 | L13: 45943
B14: LIM - Approval/NIF Dashboard | C14: 200 | D14: DD
B15: Nutrition Labeling - Update | C15: 150 | D15: EE
B16: Packaging Tech - Update | C16: 160 | D16: EE
B17: CA Finance Tax | C17: 170 | D17: FF
B18: Category Finance - update | C18: 180 | D18: FF
B19: Data Integrity (DI) - Hierarchy | C19: 190 | D19: FF
B20: Data Integrity (DI) - Review | C20: 130 | D20: FF
B21: EPM Finance - Update | C21: 120 | D21: FF
B22: R&D Quality - Update | C22: 140 | D22: FF
B23: Masterfiles - Get Codes | C23: 40 | D23: GG
B24: Masterfiles - Get Codes Forecast | C24: 60 | D24: GG
B25: Masterfiles - Approval | C25: 210 | D25: HH
... B28: LIM - LIM REPORT | C28: 30 | D28: II

Sheet Gen Matl Desc
B1: Generate_Material_Description code for button (from NIF Rules.docx)
B4: Button: Generate Material DescriptionRule: Kellogg Desc - Base
B5: Conditions
B6: if (Pringlesis equal to'No' )
B7: Actions
B8: Set a Field Value:Draft_Material_Desc= concat($form.getValue('/my:myFields/my:Form_Only_Fields/my:Brand_Abbr')," ", $form.getValue('/my:myFields/my:Form_Only_Fields/my:Flavor_Abbr')," ",$form.getValue('/my:myFields/my:Form_Only_Fields/my:Food_Form_Abbr')," ")
B9: Button: Generate Material DescriptionRule: Kellogg Desc - Add Sub Food Form
B10: Conditions
B11: if (SUB_FOOD_FORMis not blank )
B12: Actions
B13: Set a Field Value:Draft_Material_Desc= concat($form.getValue('/my:myFields/my:Form_Only_Fields/my:Draft_Material_Desc'),$form.getValue('/my:myFields/my:Form_Only_Fields/my:Sub_Food_Form_Abbr'), " ")
B14: Button: Generate Material DescriptionRule: Kellogg Desc - Add Count Bars, Size, Case Count
... B108: Set a Field Value:Draft_Material_Desc= concat($form.getValue('/my:myFields/my:Form_Only_Fields/my:Draft_Material_Desc'), ' DTC')

Sheet Definitions
A1: UNIQUE FIELD # (order in Trng deck) | B1: Training Section | C1: section name | D1: field names in Trng deck | E1: Definition
A2: 1001 | B2: Requestor - Project Initiation | C2: Requestor Initiate | D2: Requestor Name | E2: Autopopulated with the name of the person who is initiatiing the NIF.
A3: 1002 | B3: Requestor - Project Initiation | C3: Requestor Initiate | D3: Requestor Email | E3: Autopopulated with the email of the person who is initiatiing the NIF.
A4: 1003 | B4: Requestor - Project Initiation | C4: Requestor Initiate | D4: Requestor Date | E4: Autopopulated with the date the form is initiated.
A5: 1004 | B5: Requestor - Project Initiation | C5: Requestor Initiate | D5: Version | E5: Autopopulated with the current version of the NIF.
A6: 1005 | B6: Requestor - Project Initiation | C6: Person Responsible | D6: Requestor | E6: Autopopulated with the name of the person who is initiating the NIF, and used in the workflow of the form.
A7: 1006 | B7: Requestor - Project Initiation | C7: Person Responsible | D7: LIM | E7: Select the name of the Logistics Innovation Manager assigned to this project from the drop down.
A8: 1305 | B8: Requestor - Project Initiation | C8: Person Responsible | D8: Business Area | E8: Select Kellanova.
A9: 1007 | B9: Requestor - Project Initiation | C9: Product Setup | D9: Form Type | E9: There are three form types: Case, Display (Mod or Shipper) or WIP (Work In Progress/not sold to customers). This will drive the values that will appear in the Product Type dropdown.
A10: 1008 | B10: Requestor - Project Initiation | C10: Product Setup | D10: Product Country | E10: This field represents the country that will own the new item being created.
A11: 1009 | B11: Requestor - Project Initiation | C11: Product Setup | D11: Product Type | E11: This is the primary type of the new item that is being created. Based off the Form Type selected. Determines what setup type should be used.
A12: 1010 | B12: Requestor - Project Initiation | C12: Product Setup | D12: Product Sub Type | E12: Based off the Product Type selected. For example; Product Type Straight Case, the Product Sub Type will only display choices that are relevant to that product type: Package with UPC or Package and pouch/inner item with UPCs
A13: 1011 | B13: Requestor - Project Initiation | C13: Product Setup | D13: Is this a Pringles product | E13: If Pringles, answer yes. This drives logic around description and displays the Pringles Can Size field.
... A57: 1053 | B57: Requestor - Project Initiation | C57: Special Packaging Requirements | D57: Additional Packaging for Launch | E57: Make a selection if your project has special packaging requirements, and Masterfiles will assign an additional Knumber for it. Can add as many lines as needed, using the "+ Add new item" field on the right
A58: ADD | D58: BRAND / HIERARCHY QUESTIONS | E58: These are the questions that Marketing has on their end around Brand and Type: Is this a new Brand, requiring a separate Profit Center and separate P&L from existing Brands? Yes - If so, it requires a different or new Brand, which could take 3 weeks to create. - contact Finance No - Will this be planned in TPM separately from existing products? Yes - If so, it requires a different or new Type, which could take 3 weeks to create. - contact Data Operations No - Is this a new Food Form? Yes - It requires a different or new Type, which could take 3 weeks to create. - contact Data Operations No - Is this a new Size? Yes - It may require a different or new Type, which could take 3 weeks to create. - contact Commercial Enablement No - Is this a new package price? Yes - It may require new Type. - contact Commercial Enablement No - Is this a new Sub Brand? Yes - submit a KNA Request Product Value form in Evolve No - OTG (On The Go) is usually in a different Brand hierarchy than core. Is this an OTG item? Yes - Ensure selection of Brand name during Requestor Update task includes OTG (example: Caddies Cheez-It OTG) No - Ensure selection of Brand name during Requestor Update task does not include OTG
A59: 1054 | B59: LIM - Initial Review | C59: Priority | D59: Priority | E59: Normal, CBP or Urgent - this helps others understand the level of urgency associated with the item so they can prioritize accordingly
A60: 1055 | B60: LIM - Initial Review | C60: Packaging Tech Assignment | D60: Select Packaging Tech Assignment | E60: BPS, Menasha/12 Associates (US VAS) or Canada VAS
A61: 1056 | B61: LIM - Initial Review | C61: Person Responsible | D61: Masterfiles | E61: Select the individual responsible
A62: 1057 | B62: LIM - Initial Review | C62: Person Responsible | D62: EPM Finance | E62: Select the individual responsible
A63: 1058 | B63: LIM - Initial Review | C63: Person Responsible | D63: Data Integrity | E63: Select the individual responsible
A64: 1059 | B64: LIM - Initial Review | C64: Person Responsible | D64: Data Integrity (CA) | E64: Select the individual responsible
A65: 1060 | B65: LIM - Initial Review | C65: Person Responsible | D65: R&D Quality | E65: Select the individual responsible
A66: 1061 | B66: LIM - Initial Review | C66: Person Responsible | D66: Nutrition Labeling | E66: Select the individual responsible
A67: 1062 | B67: LIM - Initial Review | C67: Person Responsible | D67: Packaging Tech (Engineer) | E67: Select the individual responsible
A68: 1063 | B68: LIM - Initial Review | C68: Person Responsible | D68: Category Finance | E68: Select the individual responsible
A69: 1064 | B69: LIM - Initial Review | C69: Person Responsible | D69: Packaging Tech (BPS) | E69: Select the individual responsible
A70: 1065 | B70: LIM - Initial Review | C70: Person Responsible | D70: Packaging Tech (Menasha) | E70: Select the individual responsible
... A76: 1071 | B76: Masterfiles - Get Codes | C76: UPC, K#, and GTIN Codes | D76: Alt UOM | E76: In SAP Material Master, Alternative Unit of Measure (UoM) fields are used to define additional units in which a material can be measured, besides its base unit of measure.
A77: 1073 | B77: Masterfiles - Get Codes | C77: UPC, K#, and GTIN Codes | D77: K # | E77: Refer to the List Any Existing Knumbers That Will Be Used section, and either copy/paste those into the corresponding fields or assign new as appropriate | F77: These fields will show up on Get Codes and ZNIF Dashboard tasks / NIF Admin
A78: 1075 | B78: Masterfiles - Get Codes | C78: UPC, K#, and GTIN Codes | D78: UPC Required | E78: auto-populated from selected Material Type & Sub Type
A79: 1072 | B79: Masterfiles - Get Codes | C79: UPC, K#, and GTIN Codes | D79: UPC # | E79: Assign the appropriate UPC’s according to the Setup Type that has been chosen (see ‘Unique or Same UPC?’ Column), using the Prefix provided by the Requestor. Be sure to refer to the Product DeterminationQuestions, Existing Printed Material Codes, and Other UPC Requirementssections to assist. Also refer to the Check Digit Calculator document - UPC's are always 12 digits (Symbology = UPC-A in the check digit calculator). GTIN's are always 14 digits (Symbology = ITF-14 in the check digit calculator). Drop the "Z" but keep the zeros when entering into the form.
A80: ADD | B80: Masterfiles - Get Codes | C80: UPC, K#, and GTIN Codes | D80: SAP UPC# | E80: This is the 12 digit UPC
A81: 1076 | B81: Masterfiles - Get Codes | C81: UPC, K#, and GTIN Codes | D81: Unique or Same UPC | E81: auto-populated from selected Material Type & Sub Type
A82: 1078 | B82: Masterfiles - Get Codes | C82: UPC, K#, and GTIN Codes | D82: GTIN Required | E82: auto-populated from selected Material Type & Sub Type
A83: 1077 | B83: Masterfiles - Get Codes | C83: UPC, K#, and GTIN Codes | D83: GTIN Number | E83: Assign the appropriate UPC’s according to the Setup Type that has been chosen (see ‘Unique or Same UPC?’ Column), using the Prefix provided by the Requestor. Be sure to refer to the Product Determination Questions, Existing Printed Material Codes, and Other UPC Requirementssections to assist. Also refer to the Check Digit Calculator document
A84: ADD | B84: Masterfiles - Get Codes | C84: UPC, K#, and GTIN Codes | D84: SAP GTIN | E84: This is the GTIN number with the leading "Z"
A85: 1080 | B85: Masterfiles - Get Codes | C85: UPC, K#, and GTIN Codes | D85: Unique or Same GTIN | E85: auto-populated from selected Material Type & Sub Type
A86: 1079 | B86: Masterfiles - Get Codes | C86: UPC, K#, and GTIN Codes | D86: GTIN Prefix | E86: auto-populated from selected Material Type & Sub Type
A87: 1081 | B87: Masterfiles - Get Codes | C87: UPC, K#, and GTIN Codes | D87: Special Launch K Number | E87: Assign additional K#’s as requested.
A88: 1082 | B88: Masterfiles - Get Codes | C88: (buttons) Returns | D88: (MF Get Codes) Return Comments | E88: At MasterFiles Get Codes, the only return that is available is to Requestor Initiate. Returns can only go one level back. If the form has made it past LIM Initial Review, and the set-up type is incorrect, the form will have to be started over. Please be as descriptive as possible and provide the necessary reasons/details as to why you are returning the NIF.
A89: 1083 | B89: LIM - Forecast Approval | C89: Forecast SKU Requirements | D89: MFG Company | E89: The MFG Company is determined by Brand.
A90: 1084 | B90: LIM - Forecast Approval | C90: Forecast SKU Requirements | D90: Material Group | E90: General category of the item you are setting up, used to group together items with the same attributes.
A91: 1085 | B91: LIM - Forecast Approval | C91: Forecast SKU Requirements | D91: External Material Group | E91: This is the Channel owner of the item being created.
A92: 1086 | B92: LIM - Forecast Approval | C92: Forecast SKU Requirements | D92: Estimated Standard Cost | E92: This is the Estimated Standard Cost of item being create.
A93: 1087 | B93: LIM - Forecast Approval | C93: Forecast SKU Requirements | D93: Red K Price | E93: This is the base price for all retail customers - based on case quantity
A94: 1088 | B94: LIM - Forecast Approval | C94: Forecast SKU Requirements | D94: Material Prefix | E94: Manufacturer ID Used to determine UPCs
A95: 1089 | B95: LIM - Forecast Approval | C95: Forecast SKU Requirements | D95: Transportation Group | E95: A grouping of materials thatshare the same route and transportation requirements. Identifies how product will be transported and stored within the Kellanova network – Dry or Frozen
A96: 1090 | B96: LIM - Forecast Approval | C96: Forecast SKU Requirements | D96: Net Case Weight | E96: The total case weight of the food only. It does not include any packaging.
... A308: 1295 | B308: Requestor - Req Launch DTC | C308: DTC Product Details | D308: Country | E308: Choose US or CANADA
A309: 1296 | B309: Requestor - Req Launch DTC | C309: DTC Product Details | D309: Retail Material Number | E309: Enter the number which is in the upper section of the form | F309: This is a completely different form and is the KNA DTC Simple Bundle 1CT Create KNV
A310: 1297 | B310: Requestor - Req Launch DTC | C310: DTC Product Details | D310: 1. Validate Retail material Number (button) | E310: This pulls the retail material data from SAP (i.e. Descriptions, Plant, Storage Location, Sales Organization, Distribution Channel, Hierarchy, and Brand) | F310: This is a completely different form and is the KNA DTC Simple Bundle 1CT Create KNV
A311: 1298 | B311: Requestor - Req Launch DTC | C311: DTC Product Details | D311: 2. Import Alt UOM Table (button) | E311: This pulls retail material alt uom details from SAP. This also reveals the SAVE AND ROUTE button below Sales Org Extensions section | F311: This is a completely different form and is the KNA DTC Simple Bundle 1CT Create KNV
A312: 1299 | B312: Requestor - Req Launch DTC | C312: DTC Product Details | D312: Save and Route (button) | E312: Select this button to send request through workflow | F312: This is a completely different form and is the KNA DTC Simple Bundle 1CT Create KNV
A313: 1300 | B313: Requestor - Req Launch DTC | C313: Attachments | D313: Choose File | E313: Add any files which are helpful | F313: This is a completely different form and is the KNA DTC Simple Bundle 1CT Create KNV
A314: 1301 | B314: Requestor - Req Launch DTC | C314: DTC Launch Validation | D314: Did you submit DTC Form | E314: Click YES after SAVE AND ROUTE, which will show section: DTC Launch Buttons. | F314: This is a completely different form and is the KNA DTC Simple Bundle 1CT Create KNV
A315: 1302 | B315: Requestor - Req Launch DTC | C315: DTC Launch Validation | D315: DTC Form Launched (button) | E315: Click when DTC form has been launched | F315: This is a completely different form and is the KNA DTC Simple Bundle 1CT Create KNV
A316: 1303 | B316: Requestor - Req Launch DTC | C316: DTC Launch Validation | D316: Launch Later (No Save) (button) | E316: This button allows the form to be cancelled and available to launch later. | F316: This is a completely different form and is the KNA DTC Simple Bundle 1CT Create KNV

Sheet Module2-AI
A2: field names in Trng deck | B2: UNIQUE FIELD # (order in Trng deck) | C2: types of fields | D2: Training Section | E2: owner | F2: Definition - copied from Tamaras deck | G2: Business Rules (AI ready)
A3: Field Name | B3: Field Number | C3: Field Type | D3: Field Section | E3: Responsible Party | F3: General Definition | G3: Business Rule
A4: ='All sections of NIF PDF'!D4 -> Requestor Name | B4: =INDEX('All sections of NIF PDF'!$A:$A,MATCH($A4,'All sections of NIF PDF'!$D:$D,0)) -> 1001 | C4: =VLOOKUP($A4,'All sections of NIF PDF'!$D:$N,4,FALSE) -> autofill | D4: =INDEX('All sections of NIF PDF'!$B:$B,MATCH($A4,'All sections of NIF PDF'!$D:$D,0)) -> Requestor - Project Initiation | E4: =VLOOKUP($A4,'All sections of NIF PDF'!$D:$N,6,FALSE) -> Requestor | F4: =IF(VLOOKUP($A4,Definitions!$D:$E,2,FALSE)=0, "", VLOOKUP($A4,Definitions!$D:$E,2,FALSE)) -> Autopopulated with the name of the person who is initiatiing the NIF. | G4: =IF(VLOOKUP($A4,'All sections of NIF PDF'!$D:$N,11,FALSE)=0,"",VLOOKUP($A4,'All sections of NIF PDF'!$D:$N,11,FALSE))
A5: ='All sections of NIF PDF'!D5 -> Requestor Email | B5: =INDEX('All sections of NIF PDF'!$A:$A,MATCH($A5,'All sections of NIF PDF'!$D:$D,0)) -> 1002 | C5: =VLOOKUP($A5,'All sections of NIF PDF'!$D:$N,4,FALSE) -> autofill | D5: =INDEX('All sections of NIF PDF'!$B:$B,MATCH($A5,'All sections of NIF PDF'!$D:$D,0)) -> Requestor - Project Initiation | E5: =VLOOKUP($A5,'All sections of NIF PDF'!$D:$N,6,FALSE) -> Requestor | F5: =IF(VLOOKUP($A5,Definitions!$D:$E,2,FALSE)=0, "", VLOOKUP($A5,Definitions!$D:$E,2,FALSE)) -> Autopopulated with the email of the person who is initiatiing the NIF. | G5: =IF(VLOOKUP($A5,'All sections of NIF PDF'!$D:$N,11,FALSE)=0,"",VLOOKUP($A5,'All sections of NIF PDF'!$D:$N,11,FALSE))
A6: ='All sections of NIF PDF'!D6 -> Requestor Date | B6: =INDEX('All sections of NIF PDF'!$A:$A,MATCH($A6,'All sections of NIF PDF'!$D:$D,0)) -> 1003 | C6: =VLOOKUP($A6,'All sections of NIF PDF'!$D:$N,4,FALSE) -> autofill | D6: =INDEX('All sections of NIF PDF'!$B:$B,MATCH($A6,'All sections of NIF PDF'!$D:$D,0)) -> Requestor - Project Initiation | E6: =VLOOKUP($A6,'All sections of NIF PDF'!$D:$N,6,FALSE) -> Requestor | F6: =IF(VLOOKUP($A6,Definitions!$D:$E,2,FALSE)=0, "", VLOOKUP($A6,Definitions!$D:$E,2,FALSE)) -> Autopopulated with the date the form is initiated. | G6: =IF(VLOOKUP($A6,'All sections of NIF PDF'!$D:$N,11,FALSE)=0,"",VLOOKUP($A6,'All sections of NIF PDF'!$D:$N,11,FALSE))
A7: ='All sections of NIF PDF'!D7 -> Version | B7: =INDEX('All sections of NIF PDF'!$A:$A,MATCH($A7,'All sections of NIF PDF'!$D:$D,0)) -> 1004 | C7: =VLOOKUP($A7,'All sections of NIF PDF'!$D:$N,4,FALSE) -> autofill | D7: =INDEX('All sections of NIF PDF'!$B:$B,MATCH($A7,'All sections of NIF PDF'!$D:$D,0)) -> Requestor - Project Initiation | E7: =VLOOKUP($A7,'All sections of NIF PDF'!$D:$N,6,FALSE) -> Requestor | F7: =IF(VLOOKUP($A7,Definitions!$D:$E,2,FALSE)=0, "", VLOOKUP($A7,Definitions!$D:$E,2,FALSE)) -> Autopopulated with the current version of the NIF. | G7: =IF(VLOOKUP($A7,'All sections of NIF PDF'!$D:$N,11,FALSE)=0,"",VLOOKUP($A7,'All sections of NIF PDF'!$D:$N,11,FALSE))
A8: ='All sections of NIF PDF'!D8 -> Requestor | B8: =INDEX('All sections of NIF PDF'!$A:$A,MATCH($A8,'All sections of NIF PDF'!$D:$D,0)) -> 1005 | C8: =VLOOKUP($A8,'All sections of NIF PDF'!$D:$N,4,FALSE) -> dd: user roles | D8: =INDEX('All sections of NIF PDF'!$B:$B,MATCH($A8,'All sections of NIF PDF'!$D:$D,0)) -> Requestor - Project Initiation | E8: =VLOOKUP($A8,'All sections of NIF PDF'!$D:$N,6,FALSE) -> Requestor | F8: =IF(VLOOKUP($A8,Definitions!$D:$E,2,FALSE)=0, "", VLOOKUP($A8,Definitions!$D:$E,2,FALSE)) -> Autopopulated with the name of the person who is initiating the NIF, and used in the workflow of the form. | G8: =IF(VLOOKUP($A8,'All sections of NIF PDF'!$D:$N,11,FALSE)=0,"",VLOOKUP($A8,'All sections of NIF PDF'!$D:$N,11,FALSE))
A9: ='All sections of NIF PDF'!D9 -> LIM | B9: =INDEX('All sections of NIF PDF'!$A:$A,MATCH($A9,'All sections of NIF PDF'!$D:$D,0)) -> 1006 | C9: =VLOOKUP($A9,'All sections of NIF PDF'!$D:$N,4,FALSE) -> dd: reference list: PRL: LIM_Users | D9: =INDEX('All sections of NIF PDF'!$B:$B,MATCH($A9,'All sections of NIF PDF'!$D:$D,0)) -> Requestor - Project Initiation | E9: =VLOOKUP($A9,'All sections of NIF PDF'!$D:$N,6,FALSE) -> Requestor | F9: =IF(VLOOKUP($A9,Definitions!$D:$E,2,FALSE)=0, "", VLOOKUP($A9,Definitions!$D:$E,2,FALSE)) -> Select the name of the Logistics Innovation Manager assigned to this project from the drop down. | G9: =IF(VLOOKUP($A9,'All sections of NIF PDF'!$D:$N,11,FALSE)=0,"",VLOOKUP($A9,'All sections of NIF PDF'!$D:$N,11,FALSE))
A10: ='All sections of NIF PDF'!D10 -> Business Area | B10: =INDEX('All sections of NIF PDF'!$A:$A,MATCH($A10,'All sections of NIF PDF'!$D:$D,0)) -> 1305 | C10: =VLOOKUP($A10,'All sections of NIF PDF'!$D:$N,4,FALSE) -> dd: WKKC, KELLANOVA | D10: =INDEX('All sections of NIF PDF'!$B:$B,MATCH($A10,'All sections of NIF PDF'!$D:$D,0)) -> Requestor - Project Initiation | E10: =VLOOKUP($A10,'All sections of NIF PDF'!$D:$N,6,FALSE) -> Requestor | F10: =IF(VLOOKUP($A10,Definitions!$D:$E,2,FALSE)=0, "", VLOOKUP($A10,Definitions!$D:$E,2,FALSE)) -> Select Kellanova. | G10: =IF(VLOOKUP($A10,'All sections of NIF PDF'!$D:$N,11,FALSE)=0,"",VLOOKUP($A10,'All sections of NIF PDF'!$D:$N,11,FALSE))
A11: ='All sections of NIF PDF'!D11 -> Form Type | B11: =INDEX('All sections of NIF PDF'!$A:$A,MATCH($A11,'All sections of NIF PDF'!$D:$D,0)) -> 1007 | C11: =VLOOKUP($A11,'All sections of NIF PDF'!$D:$N,4,FALSE) -> dd: CASE, DISPLAY, WIP | D11: =INDEX('All sections of NIF PDF'!$B:$B,MATCH($A11,'All sections of NIF PDF'!$D:$D,0)) -> Requestor - Project Initiation | E11: =VLOOKUP($A11,'All sections of NIF PDF'!$D:$N,6,FALSE) -> Requestor | F11: =IF(VLOOKUP($A11,Definitions!$D:$E,2,FALSE)=0, "", VLOOKUP($A11,Definitions!$D:$E,2,FALSE)) -> There are three form types: Case, Display (Mod or Shipper) or WIP (Work In Progress/not sold to customers). This will drive the values that will appear in the Product Type dropdown. | G11: =IF(VLOOKUP($A11,'All sections of NIF PDF'!$D:$N,11,FALSE)=0,"",VLOOKUP($A11,'All sections of NIF PDF'!$D:$N,11,FALSE)) -> Reliant on Product Country
A12: ='All sections of NIF PDF'!D12 -> Product Country | B12: =INDEX('All sections of NIF PDF'!$A:$A,MATCH($A12,'All sections of NIF PDF'!$D:$D,0)) -> 1008 | C12: =VLOOKUP($A12,'All sections of NIF PDF'!$D:$N,4,FALSE) -> dd: reference list: PRODUCT_COUNTRY.XLSX | D12: =INDEX('All sections of NIF PDF'!$B:$B,MATCH($A12,'All sections of NIF PDF'!$D:$D,0)) -> Requestor - Project Initiation | E12: =VLOOKUP($A12,'All sections of NIF PDF'!$D:$N,6,FALSE) -> Requestor | F12: =IF(VLOOKUP($A12,Definitions!$D:$E,2,FALSE)=0, "", VLOOKUP($A12,Definitions!$D:$E,2,FALSE)) -> This field represents the country that will own the new item being created. | G12: =IF(VLOOKUP($A12,'All sections of NIF PDF'!$D:$N,11,FALSE)=0,"",VLOOKUP($A12,'All sections of NIF PDF'!$D:$N,11,FALSE))
A13: ='All sections of NIF PDF'!D13 -> Product Type | B13: =INDEX('All sections of NIF PDF'!$A:$A,MATCH($A13,'All sections of NIF PDF'!$D:$D,0)) -> 1009 | C13: =VLOOKUP($A13,'All sections of NIF PDF'!$D:$N,4,FALSE) -> dd: reference list: PRODUCT_SETUP_TYPE.XLSX, Setup_Type column | D13: =INDEX('All sections of NIF PDF'!$B:$B,MATCH($A13,'All sections of NIF PDF'!$D:$D,0)) -> Requestor - Project Initiation | E13: =VLOOKUP($A13,'All sections of NIF PDF'!$D:$N,6,FALSE) -> Requestor | F13: =IF(VLOOKUP($A13,Definitions!$D:$E,2,FALSE)=0, "", VLOOKUP($A13,Definitions!$D:$E,2,FALSE)) -> This is the primary type of the new item that is being created. Based off the Form Type selected. Determines what setup type should be used. | G13: =IF(VLOOKUP($A13,'All sections of NIF PDF'!$D:$N,11,FALSE)=0,"",VLOOKUP($A13,'All sections of NIF PDF'!$D:$N,11,FALSE)) -> Reliant on Product Country / Form Type
A14: ='All sections of NIF PDF'!D14 -> Product Sub Type | B14: =INDEX('All sections of NIF PDF'!$A:$A,MATCH($A14,'All sections of NIF PDF'!$D:$D,0)) -> 1010 | C14: =VLOOKUP($A14,'All sections of NIF PDF'!$D:$N,4,FALSE) -> dd: reference list: PRODUCT_SETUP_TYPE.XLSX, Setup_Qualifier column | D14: =INDEX('All sections of NIF PDF'!$B:$B,MATCH($A14,'All sections of NIF PDF'!$D:$D,0)) -> Requestor - Project Initiation | E14: =VLOOKUP($A14,'All sections of NIF PDF'!$D:$N,6,FALSE) -> Requestor | F14: =IF(VLOOKUP($A14,Definitions!$D:$E,2,FALSE)=0, "", VLOOKUP($A14,Definitions!$D:$E,2,FALSE)) -> Based off the Product Type selected. For example; Product Type Straight Case, the Product Sub Type will only display choices that are relevant to that product type: Package with UPC or Package and pouch/inner item with UPCs | G14: =IF(VLOOKUP($A14,'All sections of NIF PDF'!$D:$N,11,FALSE)=0,"",VLOOKUP($A14,'All sections of NIF PDF'!$D:$N,11,FALSE)) -> Reliant on Product Country / Form Type / Product Type
A15: ='All sections of NIF PDF'!D15 -> Is this a Pringles product | B15: =INDEX('All sections of NIF PDF'!$A:$A,MATCH($A15,'All sections of NIF PDF'!$D:$D,0)) -> 1011 | C15: =VLOOKUP($A15,'All sections of NIF PDF'!$D:$N,4,FALSE) -> dd: YES, NO | D15: =INDEX('All sections of NIF PDF'!$B:$B,MATCH($A15,'All sections of NIF PDF'!$D:$D,0)) -> Requestor - Project Initiation | E15: =VLOOKUP($A15,'All sections of NIF PDF'!$D:$N,6,FALSE) -> Requestor | F15: =IF(VLOOKUP($A15,Definitions!$D:$E,2,FALSE)=0, "", VLOOKUP($A15,Definitions!$D:$E,2,FALSE)) -> If Pringles, answer yes. This drives logic around description and displays the Pringles Can Size field. | G15: =IF(VLOOKUP($A15,'All sections of NIF PDF'!$D:$N,11,FALSE)=0,"",VLOOKUP($A15,'All sections of NIF PDF'!$D:$N,11,FALSE))
... A319: ='All sections of NIF PDF'!D319 -> 0 | B319: =INDEX('All sections of NIF PDF'!$A:$A,MATCH($A319,'All sections of NIF PDF'!$D:$D,0)) -> #N/A | C319: =VLOOKUP($A319,'All sections of NIF PDF'!$D:$N,4,FALSE) -> #N/A | D319: =INDEX('All sections of NIF PDF'!$B:$B,MATCH($A319,'All sections of NIF PDF'!$D:$D,0)) -> #N/A | E319: =VLOOKUP($A319,'All sections of NIF PDF'!$D:$N,6,FALSE) -> #N/A | F319: =IF(VLOOKUP($A319,Definitions!$D:$E,2,FALSE)=0, "", VLOOKUP($A319,Definitions!$D:$E,2,FALSE)) -> #N/A | G319: =IF(VLOOKUP($A319,'All sections of NIF PDF'!$D:$N,11,FALSE)=0,"",VLOOKUP($A319,'All sections of NIF PDF'!$D:$N,11,FALSE)) -> #N/A

Sheet glossary
A1: Term | B1: Definition
A2: 0200 BOM | B2: This BOM setup is required for US Variety Packs where the inner items have UPC’s on them. The Data Synchronization process requires that the inner items in the package be sent to customers. This however does not apply to Canada at this time.
A3: AB | B3: All Bran
A4: AFH, or Away From Home | B4: Away From Home represents businesses where Kellanova sells food that doesn't sell for at-home consumption. (EX: Restaurants, Convenience stores, Vending machines). Sales team formerly referred to as "Specialty".
A5: ASTN | B5: Austin
A6: Base Material, Base SKU, or Base item | B6: “Base” is used to refer to an item that is considered the Base Material. It is typically the everyday item that most customers order. The components inside the Base item are used for “child” items, which are repacked items or reduced case pack items.
A7: BNKD | B7: Bear Naked
A8: BOM | B8: Bill of Material
A9: BPS | B9: Business Process & Systems (Packaging)
A10: Brand | B10: If this item is On The Go (OTG)/Convenience Snack Packs (CSP), then ensure selection of Brand name during Requestor Update task includes OTG (EX: Caddies Cheez-It OTG).
A11: CA | B11: Canada
A12: CARMEL | B12: Caramel
... A144: ZMMU | B144: Material Master Update table in SAP. This is a transaction used by Data Operations to extend items to different locations based on item setup type.

Sheet POC files
A3: Kellanova to send to NIFTY? | B3: file name | C3: contains | D3: # pages / tabs | E3: # columns | F3: # rows | G3: Company where link is pointing | H3: link | I3: comments | J3: one time? | K3: maintain file?
B4: Data-Ops-NIF-Create-a-CASE-Training-Deck---11.24.pdf | C4: Data Operations CASE NIF - 2024 | D4: 9 | G4: DCAI | H4: Data-Ops-NIF-Create-a-CASE-Training-Deck---11.24.pdf | I4: x
B5: NIF Value Stream Catalog.docx | C5: details of NIF workflow steps | D5: 9 | G5: DCAI | H5: NIF Value Stream Catalog.docx | I5: x
B6: NIF-Value-Stream-Drawing (1).pdf | C6: details of NIF workflow steps - drawing | D6: 1 | G6: DCAI | H6: NIF-Value-Stream-Drawing (1).pdf
B7: KNA NIF Create KNV Document Report.xlsx | C7: download from Winshuttle/Evolve database | D7: 2 | E7: 87 | F7: 1533 | G7: DCAI | H7: KNA NIF Create KNV Document Report.xlsx | I7: recommend a daily download
B8: NIF_Example.xlsx | C8: download from Winshuttle/Evolve database | D8: 1 | E8: 87 | F8: 6 | G8: Kellanova | H8: NIF_Example.xlsx | I8: (same as another file)
B9: New - Guide on Creating an NIF for RX BAR and RX WIP 1.28.25.pptx | C9: DTC Setup Types in the NIF | D9: 47 | G9: DCAI | H9: New - Guide on Creating an NIF for RX BAR 1.28.25.pptx | I9: add
B10: New - Guide on Creating an NIF for RX BAR and RX WIP 5.8.25.pptx | C10: DTC Setup Types in the NIF | D10: 54 | G10: DCAI | H10: New - Guide on Creating an NIF for RX BAR and RX WIP 5.8.25.pptx | I10: add
B11: RX Guide on Creating an NIF for RX BAR and RX WIP 5.8.25.pptx | C11: DTC Setup Types in the NIF | D11: 54 | G11: DCAI | H11: RX Guide on Creating an NIF for RX BAR and RX WIP 5.8.25.pptx | I11: add
B12: RX DTC Simple Bundle vs Static Bundle.docx | C12: DTC Simple Bundle vs Static Bundle | D12: 3 | G12: DCAI | H12: RX DTC Simple Bundle vs Static Bundle.docx | I12: review
B13: Description Generator with NIF Key - KNV.xlsm | C13: generator of material descriptions | D13: 3 | G13: DCAI | H13: Description Generator with NIF Key - KNV.xlsm | I13: x
B14: GS1 Rules.pdf | C14: GS 1 GTIN Management Rules - US and Canada | D14: 34 | G14: DCAI | H14: GS1 Rules.pdf | I14: x
B15: Sample questions using co pilot.docx | C15: illustrative only questions for NIFTY | D15: 16 | G15: DCAI | H15: Sample questions using co pilot.docx | I15: review
B16: Kellanova Powerpoint Template.pptx | C16: Kellanova standards for Powerpoint | D16: 31 | G16: DCAI | H16: Kellanova Powerpoint Template.pptx | I16: x
B17: One-Pager-Case-Setup-Guide.pptx | C17: NIF Case Setup Types Examples | D17: 1 | G17: DCAI | H17: One-Pager-Case-Setup-Guide.pptx | I17: x
B18: NIF Training Deck v4 (1).pdf | C18: NIF Training Deck | D18: 191 | G18: DCAI | H18: NIF Training Deck v4 (1).pdf | I18: DCAI used during POC
B19: ** 20 various NIF PDF files - non-RX | C19: PDF reports generated at end of NIF process-non RX | D19: 20 | G19: DCAI | H19: NIFs | I19: repository
B20: ** 13 various NIF PDF files - RX related | C20: PDF reports generated at end of NIF process-RX | D20: 13 | G20: DCAI | H20: RX NIFs | I20: repository
... B25: RX WIP Set-up Process Quick Reference Guide.pptx | C25: RX WIP Set-up Process / How-To | D25: 8 | G25: DCAI | H25: RX WIP Set-up Process Quick Reference Guide.pptx | I25: review
B26: Project Nifty Questions.xlsx | C26: sample questions for NIFTY | D26: 2 | F26: 19+55 | G26: DCAI | H26: Project Nifty Questions.xlsx | I26: review
B27: KNV Active Brands 07-24-2024.xlsx | C27: SAP download of Materials | D27: 3 | E27: 133 | F27: 2379 | G27: DCAI | H27: KNV Active Brands 07-24-2024.xlsx | I27: DCAI planning on incorporating
B28: Material_Master.xlsx | C28: SAP download of Materials | D28: 1 | E28: 133 | F28: 10 | G28: Kellanova | H28: Material_Master.xlsx | I28: (same as another file)??
B29: SAP AI Fields.docx | C29: SAP ECC & Winshuttle Data Extraction Guide for AI Training – Product Configuration (e.g., Pop-Tarts) | D29: 5 | G29: DCAI | H29: SAP AI Fields.docx | I29: review
B30: Pre-Ini NIF Checklist 03.26.25.xlsx | C30: things you need to know to setup a NIF | D30: 3 | G30: DCAI | H30: Pre-Ini NIF Checklist 03.26.25.xlsx | I30: review
B31: Setup Type Guide.pdf | C31: Visual Guide to Setup Types | D31: 43 | G31: DCAI | H31: Setup Type Guide.pdf | I31: review

Sheet testing questions
A1: Testing questions?
A3: From doc: | B3: Question | C3: Answer
A4: Sample questions using co pilot.docx | B4: How do I create a NIF if I have never created one before? | C4: Answer: 1. Training materials on sharepoint site, 2. Join training session 3.Make sure you have access 4. Contact Support 5. Give step by step overview of the first few steps and than reference the guides that are step by step
A5: Sample questions using co pilot.docx | B5: I have a new brand that I want to put into a NIF | C5: Answer: 1. Confirm you have a new brand by giving examples of existing brands and giving a definition of what a new brand is. 2 Submit a product hierarchy maintenance request and how (that is item #4), 3. Attend training session if you have questions 4. Contact support.
A6: Sample questions using co pilot.docx | B6: How do I complete the product type and sub type on the NIF | C6: Answer: 1. Give definition and description of those fields, 2. Sharepoint training site setup type quick reference guide 3. Ask questions to get information on the product and give the answer using the guide on sharepoint that has the answers
A7: Sample questions using co pilot.docx | B7: Give me the NIF information for material number 2410012414 | C7: Answer: see [2410012414] tab
A8: Sample questions using co pilot.docx | B8: How do I setup apple flavored pringles in the NIF? | C8: Answer: I would have expected it to walk you through how to create it step by step, and referenced various training guides, training sessions etc.
A9: Sample questions using co pilot.docx | B9: How would I setup a apple flavored pringle in the NIF at Kellanova. | C9: The answer was still pretty sub-par
A10: Sample questions using co pilot.docx | B10: Who do I contact for help with the NIF | C10: Answer: Nice answer but it should have said to contact the LIM as #1, the LIM launch innovation managers are who manage the NIF we just administer it.
A11: Sample questions using co pilot.docx | B11: I have a product with a upc on the package which selection should I put on the NIF | C11: [long answer - but includes 4 common setup types for products with UPCs]
A12: Sample questions using co pilot.docx | B12: I am developing a Halloween cheese its product, how should I complete the NIF | C12: no answer in copilot
A13: Sample questions using co pilot.docx | B13: What is the status of my NIF that I just created? | C13: no answer in copilot
A14: Sample questions using co pilot.docx | B14: How many NIFs do I currently have in flight? In progress? Completed? | C14: no answer in copilot
... A80: Project Nifty Questions.xlsx - [User Base Questions] | B80: Can you give me the details of the following SKU | C80: MAKTX, PRODH, VKORG, VRKME, EAN11, NUMTP, ZVARIANT, BRAND, SUBBRAND
A81: Project Nifty Questions.xlsx - [User Base Questions] | B81: What type of product hierachy do you recommend
A82: Project Nifty Questions.xlsx - [User Base Questions] | B82: How is this product sold
A83: Project Nifty Questions.xlsx - [User Base Questions] | B83: I need my product to be expedited
A84: Project Nifty Questions.xlsx - [User Base Questions] | B84: How long will it take to get my product into SAP | C84: two weeks
A85: Project Nifty Questions.xlsx - [User Base Questions] | B85: This is a brand new product and packaging form
A86: Project Nifty Questions.xlsx - [User Base Questions] | B86: I don't see my product options in the drop down | C86: Is this a new new packaging form or product category
A87: Project Nifty Questions.xlsx - [User Base Questions] | B87: What fields can be edited after I submit this form | C87: Refer to training documents
A88: Project Nifty Questions.xlsx - [User Base Questions] | B88: What stage is my NIF at
A89: Project Nifty Questions.xlsx - [User Base Questions] | B89: Why was the NIF rejected
A90: Project Nifty Questions.xlsx - [User Base Questions] | B90: I need my product to be in a tray | C90: refer to setup types that only have a tray
A91: Project Nifty Questions.xlsx - [User Base Questions] | B91: My product is sold in bulk by weight or pallet | C91: refer to setup types that are only sold in bulk without an independent package upc
A92: Project Nifty Questions.xlsx - [User Base Questions] | B92: My product is seasonal | C92: Ask whether or not the individual packages that are consumed have a upc on them
A93: Project Nifty Questions.xlsx - [User Base Questions] | B93: My product is for a holiday | C93: Ask whether or not the individual packages that are consumed have a upc on them
A94: Project Nifty Questions.xlsx - [User Base Questions] | B94: The brand we need is brand new and never been used before | C94: Give me some examples so I can double check
A95: Project Nifty Questions.xlsx - [User Base Questions] | B95: The brand is new | C95: You will need to submit an IT request to get the brand added in as a value
A96: Project Nifty Questions.xlsx - [User Base Questions] | B96: My food form is brand new | C96: You will need to submit an IT request to get the new food form added in as a value
A97: Project Nifty Questions.xlsx - [User Base Questions] | B97: I don't know how to use this form | C97: Refer to training guides or I can guide you through a series of questions to help guide you
A98: Project Nifty Questions.xlsx - [User Base Questions] | B98: Where do I locate help documents | C98: Refer to the sharepoint site here is the link or I can guide you through a series of questions to help you
A99: Project Nifty Questions.xlsx - [User Base Questions] | B99: Are there trainings available | C99: Yes, there is a biweekly training hosted see Tommy Jones at Kellanova to get added to the distrubution list
A100: Mtgs-Kellanova Nifty-Bev.docx | B100: What is Alternate Units of Measure? | C100: Populate with all the appropriate values. If this setup type is a Repack, ensure you are using the exact weights and dimensions of the existing package (and pouches if applicable). If the weights or dimensions differ, it will cause issues for Data Synchronization to our customers, possibly resulting in fines. Note: the UL (unit load) Gross Weight will auto- populate if you enter the dimensions first, then the cases per unit load. Use the last three columns to guide you with the data population, and refer to the following slide for assistance: Visual Guide to Setup Types. *Please note: the Length, Width, Height and Gross Weights are not marked as required (*) in the form, but they are required for setup.
B101: What is the Product Sub type? | C101: Do a test with Product Subtype, and see if it pulls in both the “field definition” and the “glossary definition”
B102: What is the Product Subtype? | C102: Do a test with Product Subtype, and see if it pulls in both the “field definition” and the “glossary definition”

Sheet 2410012414
B2: Answer to question:
B3: Give me the NIF information for material number 2410012414
B6: Here is the NIF information for material number 2410012414:
B7: General Information
B8: Material Number: 2410012414 [1] [2]
B9: Base Material Number: 2410012414 [1]
B10: Material Segment Description: CONVENIENCE FOODS PH1 [1]
B11: Packaging Information
B12: Package UPC Code: 24100124121 [1]
B13: Package K Number: K233571000 [1]
B14: Pouch UPC Code: 24100121472 [1]
B15: Pouch K Number: K226979001 [1]
... B40: [3] Data Ops NIF Create a CASE Training Deck - 11.24 1

Sheet Flowchart testing
A3: Scenarios to go down all the Flowchart levels for Product Country / Form Type / Product Type / Product Subtype | I3: NIFTY should return these values:
A5: Answers to the questions (using the Flowchart.pptx file) | I5: Product Country | J5: Form Type | K5: Product Type | L5: Product Subtype
A6: US | B6: Display | C6: Shipper | I6: US - United States | J6: DISPLAY | K6: Shipper | L6: <not required>
A7: US | B7: Display | C7: Mod | D7: Full | I7: US - United States | J7: DISPLAY | K7: Full Mod | L7: <not required>
A8: US | B8: Display | C8: Mod | D8: Half | I8: US - United States | J8: DISPLAY | K8: Half Mod | L8: <not required>
A9: US | B9: Display | C9: Mod | D9: Quarter | I9: US - United States | J9: DISPLAY | K9: Qtr Mod | L9: <not required>
A10: US | B10: Display | C10: Mod | D10: Rainbow | I10: US - United States | J10: DISPLAY | K10: Rainbow Mod | L10: <not required>
A11: US | B11: Case | C11: Club Stores | D11: new | E11: full unit load | I11: US - United States | J11: CASE | K11: Club | L11: Traditional 1PKG=1CS
A12: US | B12: Case | C12: Club Stores | D12: new | E12: case level | I12: US - United States | J12: CASE | K12: Club | L12: Non-Traditional
A13: US | B13: Case | C13: Club Stores | D13: existing | E13: full unit load | I13: US - United States | J13: CASE | K13: Club Repack/RCP | L13: Traditional 1PKG=1CS
A14: US | B14: Case | C14: Club Stores | D14: existing | E14: case level | I14: US - United States | J14: CASE | K14: Club Repack/RCP | L14: Non-Traditional
A15: US | B15: Case | C15: Traditional Retailers | D15: straight case | E15: new | F15: yes | I15: US - United States | J15: CASE | K15: Straight Case | L15: Package and pouch/inner item with UPCs
A16: US | B16: Case | C16: Traditional Retailers | D16: straight case | E16: new | F16: no | I16: US - United States | J16: CASE | K16: Straight Case | L16: Package with UPC
A17: US | B17: Case | C17: Traditional Retailers | D17: straight case | E17: existing | F17: yes | I17: US - United States | J17: CASE | K17: Straight Case Repack/RCP | L17: Package and pouch/inner item with UPCs
A18: US | B18: Case | C18: Traditional Retailers | D18: straight case | E18: existing | F18: no | I18: US - United States | J18: CASE | K18: Straight Case Repack/RCP | L18: Package with UPC
A19: US | B19: Case | C19: Traditional Retailers | D19: bulk case | E19: yes | F19: new | I19: US - United States | J19: CASE | K19: Bulk Case | L19: Package with UPC
A20: US | B20: Case | C20: Traditional Retailers | D20: bulk case | E20: yes | F20: existing | I20: US - United States | J20: CASE | K20: Bulk Repack/RCP | L20: Package with UPC
A21: US | B21: Case | C21: Traditional Retailers | D21: bulk case | E21: no | I21: US - United States | J21: CASE | K21: Bulk Case | L21: No Package UPC
A22: US | B22: Case | C22: Traditional Retailers | D22: single serve tray | E22: new | I22: US - United States | J22: CASE | K22: Single Serve | L22: With Tray
A23: US | B23: Case | C23: Traditional Retailers | D23: single serve tray | E23: existing | I23: US - United States | J23: CASE | K23: Single Serve Repack/RCP | L23: With Tray
A24: US | B24: Case | C24: E-commerce Retailer | D24: brown corrugate box | I24: US - United States | J24: CASE | K24: ECOMM | L24: CASE (Brown Box)
A25: US | B25: Case | C25: E-commerce Retailer | D25: printed box | I25: US - United States | J25: CASE | K25: ECOMM | L25: CASE (Printed Box)
A26: US | B26: Case | C26: RX DTC | I26: US - United States | J26: CASE | K26: DTC Bundle | L26: Static (Pre-Determined Mix of Products)
A27: US | B27: WIP | C27: Case | I27: US - United States | J27: WIP | K27: WIP Case | L27: <not required>
A28: US | B28: WIP | C28: Tote/Kone | I28: US - United States | J28: WIP | K28: WIP Tote | L28: <not required>
A30: CA | B30: Case | C30: Club Stores | D30: yes | I30: CA - Canada | J30: CASE | K30: Canada Club | L30: Unit Load
A31: CA | B31: Case | C31: Club Stores | D31: no | I31: CA - Canada | J31: CASE | K31: Canada Club | L31: Traditional 1PKG=1CS
A32: CA | B32: Case | C32: Traditional Retailers | D32: straight case | E32: new | F32: yes | I32: CA - Canada | J32: CASE | K32: Canada Straight Case | L32: Package and pouch/inner item with UPCs
A33: CA | B33: Case | C33: Traditional Retailers | D33: straight case | E33: new | F33: no | I33: CA - Canada | J33: CASE | K33: Canada Straight Case | L33: Package with UPC
A34: CA | B34: Case | C34: Traditional Retailers | D34: straight case | E34: existing | F34: yes | I34: CA - Canada | J34: CASE | K34: Canada Straight Case Repack/RCP – existing PKG UPC | L34: Package and pouch/inner item with UPCs
A35: CA | B35: Case | C35: Traditional Retailers | D35: straight case | E35: existing | F35: no | I35: CA - Canada | J35: CASE | K35: Canada Straight Case Repack/RCP – existing PKG UPC | L35: Package with UPC
A36: CA | B36: Case | C36: Traditional Retailers | D36: bulk case | I36: CA - Canada | J36: CASE | K36: Canada Bulk Case | L36: <not required>
A38: LA | B38: Display | C38: Shipper | I38: LA - Latin America | J38: DISPLAY | K38: Shipper | L38: <not required>
A39: LA | B39: Display | C39: Mod | D39: Full | I39: LA - Latin America | J39: DISPLAY | K39: Full Mod | L39: <not required>
A40: LA | B40: Display | C40: Mod | D40: Half | I40: LA - Latin America | J40: DISPLAY | K40: Half Mod | L40: <not required>
A41: LA | B41: Display | C41: Mod | D41: Quarter | I41: LA - Latin America | J41: DISPLAY | K41: Qtr Mod | L41: <not required>
A42: LA | B42: Display | C42: Mod | D42: Rainbow | I42: LA - Latin America | J42: DISPLAY | K42: Rainbow Mod | L42: <not required>
A43: LA | B43: Case | C43: Club Stores | D43: new | E43: full unit load | I43: LA - Latin America | J43: CASE | K43: Club | L43: Traditional 1PKG=1CS
A44: LA | B44: Case | C44: Club Stores | D44: new | E44: case level | I44: LA - Latin America | J44: CASE | K44: Club | L44: Non-Traditional
A45: LA | B45: Case | C45: Club Stores | D45: existing | E45: full unit load | I45: LA - Latin America | J45: CASE | K45: Club Repack/RCP | L45: Traditional 1PKG=1CS
A46: LA | B46: Case | C46: Club Stores | D46: existing | E46: case level | I46: LA - Latin America | J46: CASE | K46: Club Repack/RCP | L46: Non-Traditional
A47: LA | B47: Case | C47: Traditional Retailers | D47: straight case | E47: new | F47: yes | I47: LA - Latin America | J47: CASE | K47: Straight Case | L47: Package and pouch/inner item with UPCs
A48: LA | B48: Case | C48: Traditional Retailers | D48: straight case | E48: new | F48: no | I48: LA - Latin America | J48: CASE | K48: Straight Case | L48: Package with UPC
A49: LA | B49: Case | C49: Traditional Retailers | D49: straight case | E49: existing | F49: yes | I49: LA - Latin America | J49: CASE | K49: Straight Case Repack/RCP | L49: Package and pouch/inner item with UPCs
A50: LA | B50: Case | C50: Traditional Retailers | D50: straight case | E50: existing | F50: no | I50: LA - Latin America | J50: CASE | K50: Straight Case Repack/RCP | L50: Package with UPC
A51: LA | B51: Case | C51: Traditional Retailers | D51: bulk case | E51: yes | F51: new | I51: LA - Latin America | J51: CASE | K51: Bulk Case | L51: Package with UPC
A52: LA | B52: Case | C52: Traditional Retailers | D52: bulk case | E52: yes | F52: existing | I52: LA - Latin America | J52: CASE | K52: Bulk Repack/RCP | L52: Package with UPC
A53: LA | B53: Case | C53: Traditional Retailers | D53: bulk case | E53: no | I53: LA - Latin America | J53: CASE | K53: Bulk Case | L53: No Package UPC
A54: LA | B54: Case | C54: Traditional Retailers | D54: single serve tray | E54: new | I54: LA - Latin America | J54: CASE | K54: Single Serve | L54: With Tray
A55: LA | B55: Case | C55: Traditional Retailers | D55: single serve tray | E55: existing | I55: LA - Latin America | J55: CASE | K55: Single Serve Repack/RCP | L55: With Tray
A56: LA | B56: Case | C56: E-commerce Retailer | D56: brown corrugate box | I56: LA - Latin America | J56: CASE | K56: ECOMM | L56: CASE (Brown Box)
A57: LA | B57: Case | C57: E-commerce Retailer | D57: printed box | I57: LA - Latin America | J57: CASE | K57: ECOMM | L57: CASE (Printed Box)
A58: LA | B58: Case | C58: RX DTC | I58: LA - Latin America | J58: CASE | K58: DTC Bundle | L58: Static (Pre-Determined Mix of Products)
A59: LA | B59: WIP | C59: Case | I59: LA - Latin America | J59: WIP | K59: WIP Case | L59: <not required>
A60: LA | B60: WIP | C60: Tote/Kone | I60: LA - Latin America | J60: WIP | K60: WIP Tote | L60: <not required>
A62: EU | B62: Display | C62: Shipper | I62: EU - Europe | J62: DISPLAY | K62: Shipper | L62: <not required>
A63: EU | B63: Display | C63: Mod | D63: Full | I63: EU - Europe | J63: DISPLAY | K63: Full Mod | L63: <not required>
A64: EU | B64: Display | C64: Mod | D64: Half | I64: EU - Europe | J64: DISPLAY | K64: Half Mod | L64: <not required>
A65: EU | B65: Display | C65: Mod | D65: Quarter | I65: EU - Europe | J65: DISPLAY | K65: Qtr Mod | L65: <not required>
A66: EU | B66: Display | C66: Mod | D66: Rainbow | I66: EU - Europe | J66: DISPLAY | K66: Rainbow Mod | L66: <not required>
A67: EU | B67: Case | C67: Club Stores | D67: new | E67: full unit load | I67: EU - Europe | J67: CASE | K67: Club | L67: Traditional 1PKG=1CS
A68: EU | B68: Case | C68: Club Stores | D68: new | E68: case level | I68: EU - Europe | J68: CASE | K68: Club | L68: Non-Traditional
A69: EU | B69: Case | C69: Club Stores | D69: existing | E69: full unit load | I69: EU - Europe | J69: CASE | K69: Club Repack/RCP | L69: Traditional 1PKG=1CS
A70: EU | B70: Case | C70: Club Stores | D70: existing | E70: case level | I70: EU - Europe | J70: CASE | K70: Club Repack/RCP | L70: Non-Traditional
A71: EU | B71: Case | C71: Traditional Retailers | D71: straight case | E71: new | F71: yes | I71: EU - Europe | J71: CASE | K71: Straight Case | L71: Package and pouch/inner item with UPCs
A72: EU | B72: Case | C72: Traditional Retailers | D72: straight case | E72: new | F72: no | I72: EU - Europe | J72: CASE | K72: Straight Case | L72: Package with UPC
A73: EU | B73: Case | C73: Traditional Retailers | D73: straight case | E73: existing | F73: yes | I73: EU - Europe | J73: CASE | K73: Straight Case Repack/RCP | L73: Package and pouch/inner item with UPCs
A74: EU | B74: Case | C74: Traditional Retailers | D74: straight case | E74: existing | F74: no | I74: EU - Europe | J74: CASE | K74: Straight Case Repack/RCP | L74: Package with UPC
A75: EU | B75: Case | C75: Traditional Retailers | D75: bulk case | E75: yes | F75: new | I75: EU - Europe | J75: CASE | K75: Bulk Case | L75: Package with UPC
A76: EU | B76: Case | C76: Traditional Retailers | D76: bulk case | E76: yes | F76: existing | I76: EU - Europe | J76: CASE | K76: Bulk Repack/RCP | L76: Package with UPC
A77: EU | B77: Case | C77: Traditional Retailers | D77: bulk case | E77: no | I77: EU - Europe | J77: CASE | K77: Bulk Case | L77: No Package UPC
A78: EU | B78: Case | C78: Traditional Retailers | D78: single serve tray | E78: new | I78: EU - Europe | J78: CASE | K78: Single Serve | L78: With Tray
A79: EU | B79: Case | C79: Traditional Retailers | D79: single serve tray | E79: existing | I79: EU - Europe | J79: CASE | K79: Single Serve Repack/RCP | L79: With Tray
A80: EU | B80: Case | C80: E-commerce Retailer | D80: brown corrugate box | I80: EU - Europe | J80: CASE | K80: ECOMM | L80: CASE (Brown Box)
A81: EU | B81: Case | C81: E-commerce Retailer | D81: printed box | I81: EU - Europe | J81: CASE | K81: ECOMM | L81: CASE (Printed Box)
A82: EU | B82: Case | C82: RX DTC | I82: EU - Europe | J82: CASE | K82: DTC Bundle | L82: Static (Pre-Determined Mix of Products)
A83: EU | B83: WIP | C83: Case | I83: EU - Europe | J83: WIP | K83: WIP Case | L83: <not required>
A84: EU | B84: WIP | C84: Tote/Kone | I84: EU - Europe | J84: WIP | K84: WIP Tote | L84: <not required>
A86: AMEA | B86: Display | C86: Shipper | I86: AMEA - Asia-Pacific, Middle East, Africa | J86: DISPLAY | K86: Shipper | L86: <not required>
A87: AMEA | B87: Display | C87: Mod | D87: Full | I87: AMEA - Asia-Pacific, Middle East, Africa | J87: DISPLAY | K87: Full Mod | L87: <not required>
A88: AMEA | B88: Display | C88: Mod | D88: Half | I88: AMEA - Asia-Pacific, Middle East, Africa | J88: DISPLAY | K88: Half Mod | L88: <not required>
A89: AMEA | B89: Display | C89: Mod | D89: Quarter | I89: AMEA - Asia-Pacific, Middle East, Africa | J89: DISPLAY | K89: Qtr Mod | L89: <not required>
A90: AMEA | B90: Display | C90: Mod | D90: Rainbow | I90: AMEA - Asia-Pacific, Middle East, Africa | J90: DISPLAY | K90: Rainbow Mod | L90: <not required>
A91: AMEA | B91: Case | C91: Club Stores | D91: new | E91: full unit load | I91: AMEA - Asia-Pacific, Middle East, Africa | J91: CASE | K91: Club | L91: Traditional 1PKG=1CS
A92: AMEA | B92: Case | C92: Club Stores | D92: new | E92: case level | I92: AMEA - Asia-Pacific, Middle East, Africa | J92: CASE | K92: Club | L92: Non-Traditional
A93: AMEA | B93: Case | C93: Club Stores | D93: existing | E93: full unit load | I93: AMEA - Asia-Pacific, Middle East, Africa | J93: CASE | K93: Club Repack/RCP | L93: Traditional 1PKG=1CS
A94: AMEA | B94: Case | C94: Club Stores | D94: existing | E94: case level | I94: AMEA - Asia-Pacific, Middle East, Africa | J94: CASE | K94: Club Repack/RCP | L94: Non-Traditional
A95: AMEA | B95: Case | C95: Traditional Retailers | D95: straight case | E95: new | F95: yes | I95: AMEA - Asia-Pacific, Middle East, Africa | J95: CASE | K95: Straight Case | L95: Package and pouch/inner item with UPCs
A96: AMEA | B96: Case | C96: Traditional Retailers | D96: straight case | E96: new | F96: no | I96: AMEA - Asia-Pacific, Middle East, Africa | J96: CASE | K96: Straight Case | L96: Package with UPC
A97: AMEA | B97: Case | C97: Traditional Retailers | D97: straight case | E97: existing | F97: yes | I97: AMEA - Asia-Pacific, Middle East, Africa | J97: CASE | K97: Straight Case Repack/RCP | L97: Package and pouch/inner item with UPCs
A98: AMEA | B98: Case | C98: Traditional Retailers | D98: straight case | E98: existing | F98: no | I98: AMEA - Asia-Pacific, Middle East, Africa | J98: CASE | K98: Straight Case Repack/RCP | L98: Package with UPC
A99: AMEA | B99: Case | C99: Traditional Retailers | D99: bulk case | E99: yes | F99: new | I99: AMEA - Asia-Pacific, Middle East, Africa | J99: CASE | K99: Bulk Case | L99: Package with UPC
A100: AMEA | B100: Case | C100: Traditional Retailers | D100: bulk case | E100: yes | F100: existing | I100: AMEA - Asia-Pacific, Middle East, Africa | J100: CASE | K100: Bulk Repack/RCP | L100: Package with UPC
A101: AMEA | B101: Case | C101: Traditional Retailers | D101: bulk case | E101: no | I101: AMEA - Asia-Pacific, Middle East, Africa | J101: CASE | K101: Bulk Case | L101: No Package UPC
A102: AMEA | B102: Case | C102: Traditional Retailers | D102: single serve tray | E102: new | I102: AMEA - Asia-Pacific, Middle East, Africa | J102: CASE | K102: Single Serve | L102: With Tray
A103: AMEA | B103: Case | C103: Traditional Retailers | D103: single serve tray | E103: existing | I103: AMEA - Asia-Pacific, Middle East, Africa | J103: CASE | K103: Single Serve Repack/RCP | L103: With Tray
A104: AMEA | B104: Case | C104: E-commerce Retailer | D104: brown corrugate box | I104: AMEA - Asia-Pacific, Middle East, Africa | J104: CASE | K104: ECOMM | L104: CASE (Brown Box)
A105: AMEA | B105: Case | C105: E-commerce Retailer | D105: printed box | I105: AMEA - Asia-Pacific, Middle East, Africa | J105: CASE | K105: ECOMM | L105: CASE (Printed Box)
A106: AMEA | B106: Case | C106: RX DTC | I106: AMEA - Asia-Pacific, Middle East, Africa | J106: CASE | K106: DTC Bundle | L106: Static (Pre-Determined Mix of Products)
A107: AMEA | B107: WIP | C107: Case | I107: AMEA - Asia-Pacific, Middle East, Africa | J107: WIP | K107: WIP Case | L107: <not required>
...

Sheet w-Masterfiles extra fields
A1: Review of NIF PDF format - Bev Tyler | G1: dd = drop downs | J1: BR.xlsx file = https://demandchainai.sharepoint.com/:x:/s/KellanovaPOC/Ebpe4JJnLcJDsKN74E_FN2oBGy3SMnB3ieLdjMvL_nwzIg?e=VenuuF | O1: Complexity: | P1: 3 | Q1: 2 | R1: 1 | S1: 0
J2: Trng_deck.ppt = https://demandchainai.sharepoint.com/:b:/s/KellanovaPOC/EUbYiN0y3vRHupu27Q5q6Q8BBsRldO5V1fX6na9le0eAuA?e=crBJEK | O2: Hours: | P2: 1.5 | Q2: 1 | R2: 0.5 | S2: 0
A3: order in Trng deck | B3: Training Section | C3: section name | D3: field names in Trng deck | E3: #fields enterable in Trng deck | F3: page(s) of Trng deck | G3: types of fields | H3: owner | I3: additional roles who can modify | J3: column referenced in BR.xlsx file (from Tamara) | K3: comments | L3: training needed? | M3: status | N3: PRIORITY (1..9) 1-highest 5-mid 9-lowest | O3: COMPLEXITY (3..1,0) 3-high 2-med 1-low 0-autofill | P3: Hours | Q3: Sprint
A4: 1 | B4: Requestor - Project Initiation | C4: Requestor Initiate | D4: Requestor Name | E4: 0 | F4: 23 | G4: autofill | H4: Requestor | O4: 0 | P4: =IF(ISNUMBER(O4),HLOOKUP(O4,$O$1:$S$2,2,FALSE)*E4,"") -> 0
A5: 2 | B5: Requestor - Project Initiation | C5: Requestor Initiate | D5: Requestor Email | E5: 0 | F5: 23 | G5: autofill | H5: Requestor | O5: 0 | P5: =IF(ISNUMBER(O5),HLOOKUP(O5,$O$1:$S$2,2,FALSE)*E5,"") -> 0
A6: 3 | B6: Requestor - Project Initiation | C6: Requestor Initiate | D6: Requestor Date | E6: 0 | F6: 23 | G6: autofill | H6: Requestor | O6: 0 | P6: =IF(ISNUMBER(O6),HLOOKUP(O6,$O$1:$S$2,2,FALSE)*E6,"") -> 0
A7: 4 | B7: Requestor - Project Initiation | C7: Requestor Initiate | D7: Version | E7: 0 | F7: 23 | G7: autofill | H7: Requestor | O7: 0 | P7: =IF(ISNUMBER(O7),HLOOKUP(O7,$O$1:$S$2,2,FALSE)*E7,"") -> 0
A8: 5 | B8: Requestor - Project Initiation | C8: Person Responsible | D8: Requestor | E8: 0 | F8: 23 | G8: autofill | H8: Requestor | O8: 0 | P8: =IF(ISNUMBER(O8),HLOOKUP(O8,$O$1:$S$2,2,FALSE)*E8,"") -> 0
A9: 6 | B9: Requestor - Project Initiation | C9: Person Responsible | D9: LIM | E9: 1 | F9: 23, 32, 61 | G9: dd: user roles | H9: Requestor | I9: LIM | N9: 4 | O9: 1 | P9: =IF(ISNUMBER(O9),HLOOKUP(O9,$O$1:$S$2,2,FALSE)*E9,"") -> 0.5 | Q9: D
A10: 7 | B10: Requestor - Project Initiation | C10: Product Setup | D10: Form Type | E10: 1 | F10: 24 | G10: dd: CASE, DISPLAY, WIP | H10: Requestor | J10: col A | L10: Flowchart: Product Type / Product Sub Type | M10: verify | N10: 1 | O10: 3 | P10: =IF(ISNUMBER(O10),HLOOKUP(O10,$O$1:$S$2,2,FALSE)*E10,"") -> 1.5 | Q10: A
A11: 8 | B11: Requestor - Project Initiation | C11: Product Setup | D11: Product Country | E11: 1 | F11: 24 | G11: dd: US, CA, MX | H11: Requestor | J11: NOT in BR.xlsx | L11: Flowchart: Product Type / Product Sub Type | M11: verify | N11: 1 | O11: 3 | P11: =IF(ISNUMBER(O11),HLOOKUP(O11,$O$1:$S$2,2,FALSE)*E11,"") -> 1.5 | Q11: A
A12: 9 | B12: Requestor - Project Initiation | C12: Product Setup | D12: Product Type | E12: 1 | F12: 24 | G12: dd: reference list | H12: Requestor | J12: col B | K12: dependent on FORM TYPE | L12: Flowchart: Product Type / Product Sub Type | M12: verify | N12: 1 | O12: 3 | P12: =IF(ISNUMBER(O12),HLOOKUP(O12,$O$1:$S$2,2,FALSE)*E12,"") -> 1.5 | Q12: A
A13: 10 | B13: Requestor - Project Initiation | C13: Product Setup | D13: Product Sub Type | E13: 1 | F13: 24 | G13: dd: reference list | H13: Requestor | J13: col C | K13: dependent on PRODUCT TYPE | L13: Flowchart: Product Type / Product Sub Type | M13: verify | N13: 1 | O13: 3 | P13: =IF(ISNUMBER(O13),HLOOKUP(O13,$O$1:$S$2,2,FALSE)*E13,"") -> 1.5 | Q13: A
A14: 11 | B14: Requestor - Project Initiation | C14: Product Setup | D14: Is this a Pringles product? | E14: 1 | F14: 24 | G14: dd: YES, NO | H14: Requestor | J14: NOT in BR.xlsx | N14: 1 | O14: 1 | P14: =IF(ISNUMBER(O14),HLOOKUP(O14,$O$1:$S$2,2,FALSE)*E14,"") -> 0.5 | Q14: A
A15: 12 | B15: Requestor - Project Initiation | C15: Product Setup | D15: Is this an RX Product? | E15: 1 | F15: 24 | G15: dd: YES, NO | H15: Requestor | J15: NOT in BR.xlsx | N15: 1 | O15: 1 | P15: =IF(ISNUMBER(O15),HLOOKUP(O15,$O$1:$S$2,2,FALSE)*E15,"") -> 0.5 | Q15: A
A16: 13 | B16: Requestor - Project Initiation | C16: Product Setup | D16: SAP Material Number | E16: 0 | F16: 24, 45 | G16: free form | H16: Masterfiles | O16: 1 | P16: =IF(ISNUMBER(O16),HLOOKUP(O16,$O$1:$S$2,2,FALSE)*E16,"") -> 0
A17: 14 | B17: Requestor - Project Initiation | C17: Product Setup | D17: Project Type | E17: 1 | F17: 24 | G17: dd: KUBIC, PDR, PWR, SCR | H17: Requestor | J17: col E | N17: 1 | O17: 2 | P17: =IF(ISNUMBER(O17),HLOOKUP(O17,$O$1:$S$2,2,FALSE)*E17,"") -> 1 | Q17: A
A18: 15 | B18: Requestor - Project Initiation | C18: Product Setup | D18: Project Name or Number | E18: 1 | F18: 24 | G18: free form | H18: Requestor | J18: col G | K18: PDR and SCR is text (ex Tasty) PWR is numeric | N18: 1 | O18: 1 | P18: =IF(ISNUMBER(O18),HLOOKUP(O18,$O$1:$S$2,2,FALSE)*E18,"") -> 0.5 | Q18: A
A19: 16 | C19: Product Setup | D19: Set Category | E19: 1 | G19: dd: reference list | H19: Requestor | J19: col I | K19: …not in Trng_deck.ppt | N19: 1 | O19: 3 | P19: =IF(ISNUMBER(O19),HLOOKUP(O19,$O$1:$S$2,2,FALSE)*E19,"") -> 1.5 | Q19: A
A20: 17 | B20: Requestor - Project Initiation | C20: Product Setup | D20: Brief Product Description | E20: 1 | F20: 24, 33, 73 | G20: free form | H20: Requestor | I20: LIM | J20: col K | K20: used for naming NIF form | N20: 1 | O20: 2 | P20: =IF(ISNUMBER(O20),HLOOKUP(O20,$O$1:$S$2,2,FALSE)*E20,"") -> 1 | Q20: B
A21: 18 | B21: Requestor - Project Initiation | C21: Product Setup | D21: Brief Project Overview | E21: 1 | F21: 24, 33, 73 | G21: free form | H21: Requestor | I21: LIM | J21: col M | K21: Be as detailed as possible and provide the flavor, package size and can size, if known | L21: (check name of field in NIF) | N21: 1 | O21: 2 | P21: =IF(ISNUMBER(O21),HLOOKUP(O21,$O$1:$S$2,2,FALSE)*E21,"") -> 1 | Q21: B
A22: 19 | B22: Requestor - Project Initiation | C22: Stated Weights/Case Count | D22: Stated Weight Applicable For | E22: 1 | F22: 24, 33, 73 | G22: dd: PACKAGE, INNER ITEM/POUCH | H22: Requestor | I22: LIM | J22: col O | N22: 2 | O22: 2 | P22: =IF(ISNUMBER(O22),HLOOKUP(O22,$O$1:$S$2,2,FALSE)*E22,"") -> 1 | Q22: B
A23: 20 | B23: Requestor - Project Initiation | C23: Stated Weights/Case Count | D23: Stated Weight Status | E23: 1 | F23: 24, 33, 73 | G23: dd: ESTIMATED, FINALIZED | H23: Requestor | I23: LIM | J23: col Q | N23: 2 | O23: 2 | P23: =IF(ISNUMBER(O23),HLOOKUP(O23,$O$1:$S$2,2,FALSE)*E23,"") -> 1 | Q23: B
A24: 21 | B24: Requestor - Project Initiation | C24: Stated Weights/Case Count | D24: Stated Net Weight | E24: 1 | F24: 24, 33, 73 | G24: free form | H24: Requestor | I24: LIM | J24: col S | N24: 2 | O24: 1 | P24: =IF(ISNUMBER(O24),HLOOKUP(O24,$O$1:$S$2,2,FALSE)*E24,"") -> 0.5 | Q24: B
A25: 22 | B25: Requestor - Project Initiation | C25: Stated Weights/Case Count | D25: Stated Net Weight UOM | E25: 1 | F25: 24, 33, 73 | G25: dd: OZ, LB, G, KG | H25: Requestor | I25: LIM | J25: col U | N25: 2 | O25: 1 | P25: =IF(ISNUMBER(O25),HLOOKUP(O25,$O$1:$S$2,2,FALSE)*E25,"") -> 0.5 | Q25: B
A26: 23 | B26: Requestor - Project Initiation | C26: Stated Weights/Case Count | D26: Case Count Status | E26: 1 | F26: 24, 33, 73 | G26: dd: ESTIMATED, FINALIZED | H26: Requestor | I26: LIM | J26: col W | N26: 2 | O26: 2 | P26: =IF(ISNUMBER(O26),HLOOKUP(O26,$O$1:$S$2,2,FALSE)*E26,"") -> 1 | Q26: B
A27: 24 | B27: Requestor - Project Initiation | C27: Stated Weights/Case Count | D27: Case Count | E27: 1 | F27: 24, 33, 73 | G27: free form | H27: Requestor | I27: LIM | J27: col Y | N27: 2 | O27: 3 | P27: =IF(ISNUMBER(O27),HLOOKUP(O27,$O$1:$S$2,2,FALSE)*E27,"") -> 1.5 | Q27: B
A28: 25 | B28: Requestor - Project Initiation | C28: Reference Material | D28: Like SKU / Reference Material Number | E28: 1 | F28: 25 | G28: SAP db list | H28: Requestor | J28: NOT in BR.xlsx | K28: Only Project Type: KUBIC | N28: 3 | O28: 3 | P28: =IF(ISNUMBER(O28),HLOOKUP(O28,$O$1:$S$2,2,FALSE)*E28,"") -> 1.5 | Q28: B
A29: 26 | B29: Requestor - Project Initiation | C29: CASE Product Determination Questions - Case | D29: Approved to sell via Ecommerce | E29: 1 | F29: 25 | G29: dd: YES, NO | H29: Requestor | J29: col Z | N29: 3 | O29: 1 | P29: =IF(ISNUMBER(O29),HLOOKUP(O29,$O$1:$S$2,2,FALSE)*E29,"") -> 0.5 | Q29: B
A30: 27 | B30: Requestor - Project Initiation | C30: CASE Product Determination Questions - Case | D30: Is product designated to one customer? | E30: 1 | F30: 25 | G30: dd: YES, NO | H30: Requestor | J30: col AB | N30: 3 | O30: 1 | P30: =IF(ISNUMBER(O30),HLOOKUP(O30,$O$1:$S$2,2,FALSE)*E30,"") -> 0.5 | Q30: B
A31: 28 | B31: Requestor - Project Initiation | C31: CASE Product Determination Questions - Case | D31: Designated Customer Name | E31: 1 | F31: 25 | G31: dd: reference list | H31: Requestor | J31: col AD | N31: 3 | O31: 2 | P31: =IF(ISNUMBER(O31),HLOOKUP(O31,$O$1:$S$2,2,FALSE)*E31,"") -> 1 | Q31: B
A32: 29 | B32: Requestor - Project Initiation | C32: CASE Product Determination Questions - Case | D32: Include Designated Cust. In Material Desc? | E32: 1 | F32: 25 | G32: dd: YES, NO | H32: Requestor | J32: col AF | N32: 3 | O32: 1 | P32: =IF(ISNUMBER(O32),HLOOKUP(O32,$O$1:$S$2,2,FALSE)*E32,"") -> 0.5 | Q32: B
A33: 30 | B33: Requestor - Project Initiation | C33: CASE Product Determination Questions - Case | D33: Variety Pack? | E33: 1 | F33: 25 | G33: dd: YES, NO | H33: Requestor | J33: col AH | N33: 3 | O33: 1 | P33: =IF(ISNUMBER(O33),HLOOKUP(O33,$O$1:$S$2,2,FALSE)*E33,"") -> 0.5 | Q33: B
A34: 31 | B34: Requestor - Project Initiation | C34: CASE Product Determination Questions - Case | D34: Variety Pack components have UPC codes? | E34: 1 | F34: 25 | G34: dd: YES, NO | H34: Requestor | J34: col AJ | N34: 3 | O34: 1 | P34: =IF(ISNUMBER(O34),HLOOKUP(O34,$O$1:$S$2,2,FALSE)*E34,"") -> 0.5 | Q34: B
A35: 32 | B35: Requestor - Project Initiation | C35: CASE Product Determination Questions - Case | D35: Build SKU Using Existing Package UPCs? | E35: 1 | F35: 25 | G35: dd: YES, NO | H35: Requestor | J35: col AL | N35: 3 | O35: 1 | P35: =IF(ISNUMBER(O35),HLOOKUP(O35,$O$1:$S$2,2,FALSE)*E35,"") -> 0.5 | Q35: C
A36: 33 | B36: Requestor - Project Initiation | C36: CASE Product Determination Questions - Case | D36: Is this item owned by Away From Home? | E36: 1 | F36: 25 | G36: dd: YES, NO | H36: Requestor | J36: col AN | N36: 3 | O36: 1 | P36: =IF(ISNUMBER(O36),HLOOKUP(O36,$O$1:$S$2,2,FALSE)*E36,"") -> 0.5 | Q36: C
A37: 34 | B37: Requestor - Project Initiation | C37: CASE Product Determination Questions - Case | D37: Is this an Export Product? | E37: 1 | F37: 28 | G37: dd: YES, NO | H37: Requestor | J37: col AP | N37: 3 | O37: 1 | P37: =IF(ISNUMBER(O37),HLOOKUP(O37,$O$1:$S$2,2,FALSE)*E37,"") -> 0.5 | Q37: C
A38: 35 | B38: Requestor - Project Initiation | C38: CASE Product Determination Questions - Case | D38: Build SKU Using Existing Export UPCs? | E38: 1 | F38: 28 | G38: dd: YES, NO | H38: Requestor | J38: col AR | N38: 3 | O38: 1 | P38: =IF(ISNUMBER(O38),HLOOKUP(O38,$O$1:$S$2,2,FALSE)*E38,"") -> 0.5 | Q38: C
A39: 36 | B39: Requestor - Project Initiation | C39: CASE Product Determination Questions - Case | D39: List Existing Export UPC Codes | E39: 1 | F39: 28 | G39: free form | H39: Requestor | J39: col AT | N39: 3 | O39: 2 | P39: =IF(ISNUMBER(O39),HLOOKUP(O39,$O$1:$S$2,2,FALSE)*E39,"") -> 1 | Q39: C
A40: 37 | B40: Requestor - Project Initiation | C40: CASE Product Determination Questions - Case | D40: Private Label? | E40: 1 | F40: 28 | G40: dd: YES, NO | H40: Requestor | J40: col AU | N40: 3 | O40: 1 | P40: =IF(ISNUMBER(O40),HLOOKUP(O40,$O$1:$S$2,2,FALSE)*E40,"") -> 0.5 | Q40: C
... A52: 49 | B52: Requestor - Project Initiation | C52: DISPLAY Product Determination Questions - Display | D52: Data Sync(GDSN)? | E52: 1 | F52: 26 | G52: dd: YES, NO | H52: Requestor | J52: NOT in BR.xlsx | N52: 3 | O52: 1 | P52: =IF(ISNUMBER(O52),HLOOKUP(O52,$O$1:$S$2,2,FALSE)*E52,"") -> 0.5 | Q52: C
A53: 50 | B53: Requestor - Project Initiation | C53: WIP Product Determination Questions - WIP | D53: Build SKU Using Existing Package UPCs? | E53: 0 | F53: 27 | G53: autofill | H53: Requestor | J53: col AL | K53: NO for WIP | N53: 3 | O53: 0 | P53: =IF(ISNUMBER(O53),HLOOKUP(O53,$O$1:$S$2,2,FALSE)*E53,"") -> 0 | Q53: C
A54: 51 | B54: Requestor - Project Initiation | C54: WIP Product Determination Questions - WIP | D54: Is this item owned by Away From Home? | E54: 1 | F54: 27 | G54: dd: YES, NO | H54: Requestor | J54: col AN | N54: 3 | O54: 1 | P54: =IF(ISNUMBER(O54),HLOOKUP(O54,$O$1:$S$2,2,FALSE)*E54,"") -> 0.5 | Q54: C
A55: 52 | B55: Requestor - Project Initiation | C55: WIP Product Determination Questions - WIP | D55: Is this an Export Product? | E55: 1 | F55: 27 | G55: dd: YES, NO | H55: Requestor | J55: col AP | N55: 3 | O55: 1 | P55: =IF(ISNUMBER(O55),HLOOKUP(O55,$O$1:$S$2,2,FALSE)*E55,"") -> 0.5 | Q55: C
A56: 53 | B56: Requestor - Project Initiation | C56: WIP Product Determination Questions - WIP | D56: Build SKU Using Existing Export UPCs? | E56: 1 | F56: 27 | G56: dd: YES, NO | H56: Requestor | J56: col AR | N56: 3 | O56: 1 | P56: =IF(ISNUMBER(O56),HLOOKUP(O56,$O$1:$S$2,2,FALSE)*E56,"") -> 0.5 | Q56: C
A57: 54 | B57: Requestor - Project Initiation | C57: WIP Product Determination Questions - WIP | D57: List Existing Export UPC Codes | E57: 1 | F57: 27 | G57: free form | H57: Requestor | J57: col AT | N57: 3 | O57: 2 | P57: =IF(ISNUMBER(O57),HLOOKUP(O57,$O$1:$S$2,2,FALSE)*E57,"") -> 1 | Q57: D
A58: 55 | B58: Requestor - Project Initiation | C58: WIP Product Determination Questions - WIP | D58: Private Label? | E58: 1 | F58: 27 | G58: dd: YES, NO | H58: Requestor | J58: col AU | N58: 3 | O58: 1 | P58: =IF(ISNUMBER(O58),HLOOKUP(O58,$O$1:$S$2,2,FALSE)*E58,"") -> 0.5 | Q58: D
A59: 56 | B59: Requestor - Project Initiation | C59: WIP Product Determination Questions - WIP | D59: Private Label Name | E59: 1 | F59: 27 | G59: dd: reference list | H59: Requestor | J59: col AW | N59: 3 | O59: 2 | P59: =IF(ISNUMBER(O59),HLOOKUP(O59,$O$1:$S$2,2,FALSE)*E59,"") -> 1 | Q59: D
A60: 57 | B60: Requestor - Project Initiation | C60: WIP Product Determination Questions - WIP | D60: Build SKU Using Existing Private UPCs? | E60: 1 | F60: 27 | G60: dd: YES, NO | H60: Requestor | J60: col AY | N60: 3 | O60: 1 | P60: =IF(ISNUMBER(O60),HLOOKUP(O60,$O$1:$S$2,2,FALSE)*E60,"") -> 0.5 | Q60: D
A61: 58 | B61: Requestor - Project Initiation | C61: WIP Product Determination Questions - WIP | D61: List Existing Private UPCs | E61: 1 | F61: 27 | G61: free form | H61: Requestor | J61: col BA | N61: 3 | O61: 2 | P61: =IF(ISNUMBER(O61),HLOOKUP(O61,$O$1:$S$2,2,FALSE)*E61,"") -> 1 | Q61: D
A62: 59 | B62: Requestor - Project Initiation | C62: WIP Product Determination Questions - WIP | D62: Data Sync(GDSN)? | E62: 1 | F62: 27 | G62: dd: YES, NO | H62: Requestor | J62: NOT in BR.xlsx | N62: 3 | O62: 1 | P62: =IF(ISNUMBER(O62),HLOOKUP(O62,$O$1:$S$2,2,FALSE)*E62,"") -> 0.5 | Q62: D
A63: 60 | B63: Requestor - Project Initiation | C63: Other UPC Requirements | D63: Material Prefix Description | E63: 1 | F63: 28 | G63: dd: reference list | H63: Requestor | J63: col BB | N63: 3 | O63: 2 | P63: =IF(ISNUMBER(O63),HLOOKUP(O63,$O$1:$S$2,2,FALSE)*E63,"") -> 1 | Q63: D
A64: 61 | B64: Requestor - Project Initiation | C64: Other UPC Requirements | D64: Is a Compressed UPC Required for the Components? | E64: 1 | F64: 28 | G64: dd: NO, POUCH, PACKAGE, BOTH | H64: Requestor | J64: col BD | N64: 3 | O64: 2 | P64: =IF(ISNUMBER(O64),HLOOKUP(O64,$O$1:$S$2,2,FALSE)*E64,"") -> 1 | Q64: D
A65: 62 | B65: Requestor - Project Initiation | C65: Existing Printed Material Codes | D65: Package UPC Code | E65: 1 | F65: 29 | G65: free form | H65: Requestor | J65: col BF | N65: 4 | O65: 2 | P65: =IF(ISNUMBER(O65),HLOOKUP(O65,$O$1:$S$2,2,FALSE)*E65,"") -> 1 | Q65: D
... A70: 67 | B70: Requestor - Project Initiation | C70: Existing Printed Material Codes | D70: Compressed UPC Existing | E70: 1 | F70: 29 | G70: dd: NO, POUCH, PACKAGE, BOTH | H70: Requestor | J70: NOT in BR.xlsx | N70: 4 | O70: 2 | P70: =IF(ISNUMBER(O70),HLOOKUP(O70,$O$1:$S$2,2,FALSE)*E70,"") -> 1 | Q70: D
A71: 68 | C71: Existing Printed Material Codes | D71: Sale Samples may be needed | E71: 1 | G71: dd: YES, NO | H71: Requestor | J71: col BN | K71: …not in Trng_deck.ppt | N71: 4 | O71: 2 | P71: =IF(ISNUMBER(O71),HLOOKUP(O71,$O$1:$S$2,2,FALSE)*E71,"") -> 1 | Q71: D
A72: 69 | B72: Requestor - Project Initiation | C72: UPC Table | D72: Alt UOM | E72: 0 | F72: 29 | G72: autofill | H72: Requestor | K72: This section corresponds to the Setup Type that has been chosen, and will show you the UPC requirements. | O72: 0 | P72: =IF(ISNUMBER(O72),HLOOKUP(O72,$O$1:$S$2,2,FALSE)*E72,"") -> 0
A73: 70 | B73: Requestor - Project Initiation | C73: UPC Table | D73: Base UOM | E73: 0 | F73: 29 | G73: autofill | H73: Requestor | K73: This section corresponds to the Setup Type that has been chosen, and will show you the UPC requirements. | O73: 0 | P73: =IF(ISNUMBER(O73),HLOOKUP(O73,$O$1:$S$2,2,FALSE)*E73,"") -> 0
A74: 71 | B74: Requestor - Project Initiation | C74: UPC Table | D74: UPC Required? | E74: 0 | F74: 29 | G74: autofill | H74: Requestor | K74: This section corresponds to the Setup Type that has been chosen, and will show you the UPC requirements. | O74: 0 | P74: =IF(ISNUMBER(O74),HLOOKUP(O74,$O$1:$S$2,2,FALSE)*E74,"") -> 0
A75: 72 | B75: Requestor - Project Initiation | C75: UPC Table | D75: Unique UPC? | E75: 0 | F75: 29 | G75: autofill | H75: Requestor | K75: This section corresponds to the Setup Type that has been chosen, and will show you the UPC requirements. | O75: 0 | P75: =IF(ISNUMBER(O75),HLOOKUP(O75,$O$1:$S$2,2,FALSE)*E75,"") -> 0
A76: 73 | B76: Requestor - Project Initiation | C76: List Existing K Numbers | D76: List Any Existing Knumbers That Will Be Used | E76: 1 | F76: 30 | G76: free form | H76: Requestor | J76: col AT,BA?? | N76: 4 | O76: 2 | P76: =IF(ISNUMBER(O76),HLOOKUP(O76,$O$1:$S$2,2,FALSE)*E76,"") -> 1 | Q76: D
A77: 74 | B77: Requestor - Project Initiation | C77: Special Packaging Requirements | D77: Additional Packaging for Launch | E77: 1 | F77: 30 | G77: dd: reference list | H77: Requestor | J77: col BP | L77: rows - multiple possible | N77: 4 | O77: 2 | P77: =IF(ISNUMBER(O77),HLOOKUP(O77,$O$1:$S$2,2,FALSE)*E77,"") -> 1 | Q77: D
A78: 75 | B78: Requestor - Project Initiation | C78: Special Packaging Requirements | D78: Special Launch Number | E78: 0 | F78: 30 | G78: free form | H78: Masterfiles | O78: 0 | P78: =IF(ISNUMBER(O78),HLOOKUP(O78,$O$1:$S$2,2,FALSE)*E78,"") -> 0
A79: 76 | B79: LIM - Initial Review | C79: Priority | D79: Priority | E79: 1 | F79: 31 | G79: radio button: NORMAL, CBP, URGENT | H79: LIM | K79: used for naming NIF form | O79: 1 | P79: =IF(ISNUMBER(O79),HLOOKUP(O79,$O$1:$S$2,2,FALSE)*E79,"") -> 0.5
A80: 77 | B80: LIM - Initial Review | C80: Packaging Tech Assignment | D80: Select Packaging Tech Assignment | E80: 1 | F80: 32, 61 | G80: radio button: BPS, Menasha/12 Associates, Canada VAS | H80: LIM | O80: 1 | P80: =IF(ISNUMBER(O80),HLOOKUP(O80,$O$1:$S$2,2,FALSE)*E80,"") -> 0.5
A81: 78 | B81: LIM - Initial Review | C81: Person Responsible | D81: Masterfiles | E81: 1 | F81: 32, 61 | G81: dd: user roles | H81: LIM | O81: 1 | P81: =IF(ISNUMBER(O81),HLOOKUP(O81,$O$1:$S$2,2,FALSE)*E81,"") -> 0.5
A82: 79 | B82: LIM - Initial Review | C82: Person Responsible | D82: EPM Finance | E82: 1 | F82: 32, 61 | G82: dd: user roles | H82: LIM | O82: 1 | P82: =IF(ISNUMBER(O82),HLOOKUP(O82,$O$1:$S$2,2,FALSE)*E82,"") -> 0.5
A83: 80 | B83: LIM - Initial Review | C83: Person Responsible | D83: Data Integrity | E83: 1 | F83: 32, 61 | G83: dd: user roles | H83: LIM | O83: 1 | P83: =IF(ISNUMBER(O83),HLOOKUP(O83,$O$1:$S$2,2,FALSE)*E83,"") -> 0.5
A84: 81 | B84: LIM - Initial Review | C84: Person Responsible | D84: Data Integrity (CA) | E84: 1 | F84: 32, 61 | G84: dd: user roles | H84: LIM | O84: 1 | P84: =IF(ISNUMBER(O84),HLOOKUP(O84,$O$1:$S$2,2,FALSE)*E84,"") -> 0.5
A85: 82 | B85: LIM - Initial Review | C85: Person Responsible | D85: R&D Quality | E85: 1 | F85: 32, 61 | G85: dd: user roles | H85: LIM | O85: 1 | P85: =IF(ISNUMBER(O85),HLOOKUP(O85,$O$1:$S$2,2,FALSE)*E85,"") -> 0.5
A86: 83 | B86: LIM - Initial Review | C86: Person Responsible | D86: Nutrition Labeling | E86: 1 | F86: 32, 61 | G86: dd: user roles | H86: LIM | O86: 1 | P86: =IF(ISNUMBER(O86),HLOOKUP(O86,$O$1:$S$2,2,FALSE)*E86,"") -> 0.5
A87: 84 | B87: LIM - Initial Review | C87: Person Responsible | D87: Packaging Tech (Engineer) | E87: 1 | F87: 32, 61 | G87: dd: user roles | H87: LIM | O87: 1 | P87: =IF(ISNUMBER(O87),HLOOKUP(O87,$O$1:$S$2,2,FALSE)*E87,"") -> 0.5
A88: 85 | B88: LIM - Initial Review | C88: Person Responsible | D88: Category Finance | E88: 1 | F88: 32, 61 | G88: dd: user roles | H88: LIM | O88: 1 | P88: =IF(ISNUMBER(O88),HLOOKUP(O88,$O$1:$S$2,2,FALSE)*E88,"") -> 0.5
A89: 86 | B89: LIM - Initial Review | C89: Person Responsible | D89: Packaging Tech(BPS) | E89: 1 | F89: 32, 61 | G89: dd: user roles | H89: LIM | O89: 1 | P89: =IF(ISNUMBER(O89),HLOOKUP(O89,$O$1:$S$2,2,FALSE)*E89,"") -> 0.5
A90: 87 | B90: LIM - Initial Review | C90: Person Responsible | D90: Packaging Tech (Menasha) | E90: 1 | F90: 32, 61 | G90: dd: user roles | H90: LIM | O90: 1 | P90: =IF(ISNUMBER(O90),HLOOKUP(O90,$O$1:$S$2,2,FALSE)*E90,"") -> 0.5
A91: 88 | B91: LIM - Initial Review | C91: Person Responsible | D91: Packaging The(Canada VAS) | E91: 1 | F91: 32, 61 | G91: dd: user roles | H91: LIM | O91: 1 | P91: =IF(ISNUMBER(O91),HLOOKUP(O91,$O$1:$S$2,2,FALSE)*E91,"") -> 0.5
A92: 89 | B92: LIM - Initial Review | C92: Product Setup | D92: Supply Chain Budget Forecast SKU? | E92: 1 | F92: 33 | G92: dd: YES, NO | H92: LIM | O92: 2 | P92: =IF(ISNUMBER(O92),HLOOKUP(O92,$O$1:$S$2,2,FALSE)*E92,"") -> 1
A93: 90 | B93: LIM - LIM REPORT | C93: LIM REPORT section | D93: export (buttons) | E93: 5 | F93: 37-41 | G93: export buttons | H93: LIM | K93: read only form for exporting data to Excel | O93: 1 | P93: =IF(ISNUMBER(O93),HLOOKUP(O93,$O$1:$S$2,2,FALSE)*E93,"") -> 2.5
A94: 91 | B94: Masterfiles - Get Codes | C94: Material Number | D94: Material Number | E94: 1 | F94: 45, 56 | G94: free form | H94: Masterfiles | O94: 1 | P94: =IF(ISNUMBER(O94),HLOOKUP(O94,$O$1:$S$2,2,FALSE)*E94,"") -> 0.5
A95: 92 | B95: Masterfiles - Get Codes | C95: UPC, K#, and GTIN Codes | D95: Alt UOM | E95: 0 | F95: 47, 56, 113 | G95: autofill | H95: Masterfiles | O95: 0 | P95: =IF(ISNUMBER(O95),HLOOKUP(O95,$O$1:$S$2,2,FALSE)*E95,"") -> 0
A96: 93 | B96: Masterfiles - Get Codes | C96: UPC, K#, and GTIN Codes | D96: UPC# | E96: 1 | F96: 47, 56, 113 | G96: free form | H96: Masterfiles | L96: rows of data: 4 (CS, PKG, LYR, UL); PCH?? | O96: 1 | P96: =IF(ISNUMBER(O96),HLOOKUP(O96,$O$1:$S$2,2,FALSE)*E96,"") -> 0.5
A97: 94 | B97: Masterfiles - Get Codes | C97: UPC, K#, and GTIN Codes | D97: K# | E97: 1 | F97: 47, 56, 113 | G97: free form | H97: Masterfiles | L97: rows of data: 4 (CS, PKG, LYR, UL); PCH?? | O97: 1 | P97: =IF(ISNUMBER(O97),HLOOKUP(O97,$O$1:$S$2,2,FALSE)*E97,"") -> 0.5
A98: 95 | B98: Masterfiles - Get Codes | C98: UPC, K#, and GTIN Codes | D98: UPC Required? | E98: 0 | F98: 47, 56, 113 | G98: autofill | H98: Masterfiles | O98: 0 | P98: =IF(ISNUMBER(O98),HLOOKUP(O98,$O$1:$S$2,2,FALSE)*E98,"") -> 0
A99: 96 | B99: Masterfiles - Get Codes | C99: UPC, K#, and GTIN Codes | D99: Unique or Same UPC? | E99: 0 | F99: 47, 56, 113 | G99: autofill | H99: Masterfiles | O99: 0 | P99: =IF(ISNUMBER(O99),HLOOKUP(O99,$O$1:$S$2,2,FALSE)*E99,"") -> 0
A100: 97 | B100: Masterfiles - Get Codes | C100: UPC, K#, and GTIN Codes | D100: GTIN Number | E100: 1 | F100: 47, 56, 113 | G100: free form | H100: Masterfiles | L100: rows of data: 4 (CS, PKG, LYR, UL); PCH?? | O100: 1 | P100: =IF(ISNUMBER(O100),HLOOKUP(O100,$O$1:$S$2,2,FALSE)*E100,"") -> 0.5
A101: 98 | B101: Masterfiles - Get Codes | C101: UPC, K#, and GTIN Codes | D101: GTIN Required? | E101: 0 | F101: 47, 56, 113 | G101: autofill | H101: Masterfiles | O101: 0 | P101: =IF(ISNUMBER(O101),HLOOKUP(O101,$O$1:$S$2,2,FALSE)*E101,"") -> 0
A102: 99 | B102: Masterfiles - Get Codes | C102: UPC, K#, and GTIN Codes | D102: GTIN Prefix | E102: 0 | F102: 47, 56, 113 | G102: autofill | H102: Masterfiles | O102: 0 | P102: =IF(ISNUMBER(O102),HLOOKUP(O102,$O$1:$S$2,2,FALSE)*E102,"") -> 0
A103: 100 | B103: Masterfiles - Get Codes | C103: UPC, K#, and GTIN Codes | D103: Unique or Same GTIN? | E103: 0 | F103: 47, 56, 113 | G103: autofill | H103: Masterfiles | O103: 0 | P103: =IF(ISNUMBER(O103),HLOOKUP(O103,$O$1:$S$2,2,FALSE)*E103,"") -> 0
A104: 101 | B104: Masterfiles - Get Codes | C104: UPC, K#, and GTIN Codes | D104: Additional Packaging for Launch | E104: 0 | F104: 47, 56, 113 | G104: autofill | H104: Masterfiles | O104: 0 | P104: =IF(ISNUMBER(O104),HLOOKUP(O104,$O$1:$S$2,2,FALSE)*E104,"") -> 0
A105: 102 | B105: Masterfiles - Get Codes | C105: UPC, K#, and GTIN Codes | D105: Special Launch Number | E105: 1 | F105: 47, 56, 113 | G105: free form | H105: Masterfiles | L105: rows - multiple possible | O105: 1 | P105: =IF(ISNUMBER(O105),HLOOKUP(O105,$O$1:$S$2,2,FALSE)*E105,"") -> 0.5
A106: 103 | B106: LIM - Forecast Approval | C106: Forecast SKU Requirements | D106: MFG Company | E106: 0 | F106: 51 | G106: autofill | H106: LIM | K106: LIM approval to setup Forecast sku | O106: 0 | P106: =IF(ISNUMBER(O106),HLOOKUP(O106,$O$1:$S$2,2,FALSE)*E106,"") -> 0
A107: 104 | B107: LIM - Forecast Approval | C107: Forecast SKU Requirements | D107: Material Group | E107: 1 | F107: 51 | G107: dd: reference list | H107: LIM | O107: 2 | P107: =IF(ISNUMBER(O107),HLOOKUP(O107,$O$1:$S$2,2,FALSE)*E107,"") -> 1
A108: 105 | B108: LIM - Forecast Approval | C108: Forecast SKU Requirements | D108: External Material Group | E108: 1 | F108: 51 | G108: dd: reference list | H108: LIM | O108: 2 | P108: =IF(ISNUMBER(O108),HLOOKUP(O108,$O$1:$S$2,2,FALSE)*E108,"") -> 1
A109: 106 | B109: LIM - Forecast Approval | C109: Forecast SKU Requirements | D109: Estimated Standard Cost | E109: 1 | F109: 51 | G109: free form | H109: LIM | O109: 1 | P109: =IF(ISNUMBER(O109),HLOOKUP(O109,$O$1:$S$2,2,FALSE)*E109,"") -> 0.5
